Workbook

Sheet Ordenes
A1: BELNR_ID | B1: ItemCode | C1: Descripción del artículo | D1: Sec | E1: Fecha Inicio | F1: Cantidad Base | G1: Horas | H1: Maquina | I1: Planificado | J1: Proceso | K1: Horas Programadas | L1: Línea
A2: 3955 | B2: 2140150001 | C2: Archivador Plastificado Negro, Lomo Ancho, t/Oficio Layconsa Office | D2: =+_xlfn.XLOOKUP(B2,BD_Spec!$A$1:$A$20529,BD_Spec!$L$1:$L$20529) -> 1 | E2: 46113 | F2: =+VLOOKUP(B2,Tiempos!$A$1:$N$7479,3,FALSE) -> 3500 | G2: =+VLOOKUP(B2,Tiempos!$A$1:$N$7479,5,FALSE) -> 12 | H2: =+VLOOKUP(B2,Tiempos!$A$1:$N$7479,7,FALSE) -> AMAN02 | I2: =+VLOOKUP(A2,OP!$A$1:$I$27881,9,FALSE) -> 30000 | J2: =(VLOOKUP(B2,BD_Spec!$A$1:$K$20517,6,FALSE)) -> Terminado | K2: 12 | L2: =+VLOOKUP(B2,BD_Spec!$A$1:$K$20517,7,FALSE) -> Manuales
A3: 3940 | B3: 2110080227 | C3: Bolígrafo Layconsa crystal L-036 Azul | D3: =+_xlfn.XLOOKUP(B3,BD_Spec!$A$1:$A$20529,BD_Spec!$L$1:$L$20529) -> 1 | E3: 46113 | F3: =+VLOOKUP(B3,Tiempos!$A$1:$N$7479,3,FALSE) -> 35000 | G3: =+VLOOKUP(B3,Tiempos!$A$1:$N$7479,5,FALSE) -> 12 | H3: =+VLOOKUP(B3,Tiempos!$A$1:$N$7479,7,FALSE) -> ENS03 | I3: =+VLOOKUP(A3,OP!$A$1:$I$27881,9,FALSE) -> 34000 | J3: =(VLOOKUP(B3,BD_Spec!$A$1:$K$20517,6,FALSE)) -> Terminado | K3: 12 | L3: =+VLOOKUP(B3,BD_Spec!$A$1:$K$20517,7,FALSE) -> Línea_036
A4: 3935 | B4: 2310040571 | C4: Formado Crayón Triangular Jumbo LYC Blanco | D4: =+_xlfn.XLOOKUP(B4,BD_Spec!$A$1:$A$20529,BD_Spec!$L$1:$L$20529) -> 9 | E4: 46118 | F4: =+VLOOKUP(B4,Tiempos!$A$1:$N$7479,3,FALSE) -> 25000 | G4: =+VLOOKUP(B4,Tiempos!$A$1:$N$7479,5,FALSE) -> 12 | H4: =+VLOOKUP(B4,Tiempos!$A$1:$N$7479,7,FALSE) -> FORM01 | I4: =+VLOOKUP(A4,OP!$A$1:$I$27881,9,FALSE) -> 5753 | J4: =(VLOOKUP(B4,BD_Spec!$A$1:$K$20517,6,FALSE)) -> Semiterminado | K4: 12 | L4: =+VLOOKUP(B4,BD_Spec!$A$1:$K$20517,7,FALSE) -> Crayones
A5: 3925 | B5: 2310040362 | C5: Formado Crayón Triangular Jumbo LYC Amarillo | D5: =+_xlfn.XLOOKUP(B5,BD_Spec!$A$1:$A$20529,BD_Spec!$L$1:$L$20529) -> 1 | E5: 46113 | F5: =+VLOOKUP(B5,Tiempos!$A$1:$N$7479,3,FALSE) -> 25000 | G5: =+VLOOKUP(B5,Tiempos!$A$1:$N$7479,5,FALSE) -> 12 | H5: =+VLOOKUP(B5,Tiempos!$A$1:$N$7479,7,FALSE) -> FORM01 | I5: =+VLOOKUP(A5,OP!$A$1:$I$27881,9,FALSE) -> 6410 | J5: =(VLOOKUP(B5,BD_Spec!$A$1:$K$20517,6,FALSE)) -> Semiterminado | K5: 12 | L5: =+VLOOKUP(B5,BD_Spec!$A$1:$K$20517,7,FALSE) -> Crayones
A6: 3926 | B6: 2310040364 | C6: Formado Crayón Triangular Jumbo LYC Anaranjado | D6: =+_xlfn.XLOOKUP(B6,BD_Spec!$A$1:$A$20529,BD_Spec!$L$1:$L$20529) -> 2 | E6: 46118 | F6: =+VLOOKUP(B6,Tiempos!$A$1:$N$7479,3,FALSE) -> 25000 | G6: =+VLOOKUP(B6,Tiempos!$A$1:$N$7479,5,FALSE) -> 12 | H6: =+VLOOKUP(B6,Tiempos!$A$1:$N$7479,7,FALSE) -> FORM01 | I6: =+VLOOKUP(A6,OP!$A$1:$I$27881,9,FALSE) -> 5855 | J6: =(VLOOKUP(B6,BD_Spec!$A$1:$K$20517,6,FALSE)) -> Semiterminado | K6: 12 | L6: =+VLOOKUP(B6,BD_Spec!$A$1:$K$20517,7,FALSE) -> Crayones
A7: 3933 | B7: 2310040371 | C7: Formado Crayón Triangular Jumbo LYC Rosado | D7: =+_xlfn.XLOOKUP(B7,BD_Spec!$A$1:$A$20529,BD_Spec!$L$1:$L$20529) -> 3 | E7: 46118 | F7: =+VLOOKUP(B7,Tiempos!$A$1:$N$7479,3,FALSE) -> 25000 | G7: =+VLOOKUP(B7,Tiempos!$A$1:$N$7479,5,FALSE) -> 12 | H7: =+VLOOKUP(B7,Tiempos!$A$1:$N$7479,7,FALSE) -> FORM01 | I7: =+VLOOKUP(A7,OP!$A$1:$I$27881,9,FALSE) -> 5889 | J7: =(VLOOKUP(B7,BD_Spec!$A$1:$K$20517,6,FALSE)) -> Semiterminado | K7: 12 | L7: =+VLOOKUP(B7,BD_Spec!$A$1:$K$20517,7,FALSE) -> Crayones
A8: 3924 | B8: 2310040361 | C8: Formado Crayón Triangular Jumbo LYC Rojo | D8: =+_xlfn.XLOOKUP(B8,BD_Spec!$A$1:$A$20529,BD_Spec!$L$1:$L$20529) -> 4 | E8: 46118 | F8: =+VLOOKUP(B8,Tiempos!$A$1:$N$7479,3,FALSE) -> 25000 | G8: =+VLOOKUP(B8,Tiempos!$A$1:$N$7479,5,FALSE) -> 12 | H8: =+VLOOKUP(B8,Tiempos!$A$1:$N$7479,7,FALSE) -> FORM01 | I8: =+VLOOKUP(A8,OP!$A$1:$I$27881,9,FALSE) -> 5882 | J8: =(VLOOKUP(B8,BD_Spec!$A$1:$K$20517,6,FALSE)) -> Semiterminado | K8: 12 | L8: =+VLOOKUP(B8,BD_Spec!$A$1:$K$20517,7,FALSE) -> Crayones
A9: 3929 | B9: 2310040367 | C9: Formado Crayón Triangular Jumbo LYC Celeste | D9: =+_xlfn.XLOOKUP(B9,BD_Spec!$A$1:$A$20529,BD_Spec!$L$1:$L$20529) -> 8 | E9: 46118 | F9: =+VLOOKUP(B9,Tiempos!$A$1:$N$7479,3,FALSE) -> 25000 | G9: =+VLOOKUP(B9,Tiempos!$A$1:$N$7479,5,FALSE) -> 12 | H9: =+VLOOKUP(B9,Tiempos!$A$1:$N$7479,7,FALSE) -> FORM01 | I9: =+VLOOKUP(A9,OP!$A$1:$I$27881,9,FALSE) -> 5882 | J9: =(VLOOKUP(B9,BD_Spec!$A$1:$K$20517,6,FALSE)) -> Semiterminado | K9: 12 | L9: =+VLOOKUP(B9,BD_Spec!$A$1:$K$20517,7,FALSE) -> Crayones
A10: 3930 | B10: 2310040368 | C10: Formado Crayón Triangular Jumbo LYC Azul | D10: =+_xlfn.XLOOKUP(B10,BD_Spec!$A$1:$A$20529,BD_Spec!$L$1:$L$20529) -> 7 | E10: 46118 | F10: =+VLOOKUP(B10,Tiempos!$A$1:$N$7479,3,FALSE) -> 25000 | G10: =+VLOOKUP(B10,Tiempos!$A$1:$N$7479,5,FALSE) -> 12 | H10: =+VLOOKUP(B10,Tiempos!$A$1:$N$7479,7,FALSE) -> FORM01 | I10: =+VLOOKUP(A10,OP!$A$1:$I$27881,9,FALSE) -> 5827 | J10: =(VLOOKUP(B10,BD_Spec!$A$1:$K$20517,6,FALSE)) -> Semiterminado | K10: 12 | L10: =+VLOOKUP(B10,BD_Spec!$A$1:$K$20517,7,FALSE) -> Crayones
A11: 3927 | B11: 2310040365 | C11: Formado Crayón Triangular Jumbo LYC Verde Claro | D11: =+_xlfn.XLOOKUP(B11,BD_Spec!$A$1:$A$20529,BD_Spec!$L$1:$L$20529) -> 5 | E11: 46118 | F11: =+VLOOKUP(B11,Tiempos!$A$1:$N$7479,3,FALSE) -> 25000 | G11: =+VLOOKUP(B11,Tiempos!$A$1:$N$7479,5,FALSE) -> 12 | H11: =+VLOOKUP(B11,Tiempos!$A$1:$N$7479,7,FALSE) -> FORM01 | I11: =+VLOOKUP(A11,OP!$A$1:$I$27881,9,FALSE) -> 5828 | J11: =(VLOOKUP(B11,BD_Spec!$A$1:$K$20517,6,FALSE)) -> Semiterminado | K11: 12 | L11: =+VLOOKUP(B11,BD_Spec!$A$1:$K$20517,7,FALSE) -> Crayones
A12: 3928 | B12: 2310040366 | C12: Formado Crayón Triangular Jumbo LYC Verde Oscuro | D12: =+_xlfn.XLOOKUP(B12,BD_Spec!$A$1:$A$20529,BD_Spec!$L$1:$L$20529) -> 6 | E12: 46118 | F12: =+VLOOKUP(B12,Tiempos!$A$1:$N$7479,3,FALSE) -> 25000 | G12: =+VLOOKUP(B12,Tiempos!$A$1:$N$7479,5,FALSE) -> 12 | H12: =+VLOOKUP(B12,Tiempos!$A$1:$N$7479,7,FALSE) -> FORM01 | I12: =+VLOOKUP(A12,OP!$A$1:$I$27881,9,FALSE) -> 5875 | J12: =(VLOOKUP(B12,BD_Spec!$A$1:$K$20517,6,FALSE)) -> Semiterminado | K12: 12 | L12: =+VLOOKUP(B12,BD_Spec!$A$1:$K$20517,7,FALSE) -> Crayones
A13: 3931 | B13: 2310040369 | C13: Formado Crayón Triangular Jumbo LYC Violeta | D13: =+_xlfn.XLOOKUP(B13,BD_Spec!$A$1:$A$20529,BD_Spec!$L$1:$L$20529) -> 10 | E13: 46118 | F13: =+VLOOKUP(B13,Tiempos!$A$1:$N$7479,3,FALSE) -> 25000 | G13: =+VLOOKUP(B13,Tiempos!$A$1:$N$7479,5,FALSE) -> 12 | H13: =+VLOOKUP(B13,Tiempos!$A$1:$N$7479,7,FALSE) -> FORM01 | I13: =+VLOOKUP(A13,OP!$A$1:$I$27881,9,FALSE) -> 5841 | J13: =(VLOOKUP(B13,BD_Spec!$A$1:$K$20517,6,FALSE)) -> Semiterminado | K13: 12 | L13: =+VLOOKUP(B13,BD_Spec!$A$1:$K$20517,7,FALSE) -> Crayones
... A29: 3862 | B29: 2310090441 | C29: Barril Para Plumón 045 - NP Negro | D29: =+_xlfn.XLOOKUP(B29,BD_Spec!$A$1:$A$20529,BD_Spec!$L$1:$L$20529) -> 12 | E29: 46118 | F29: =+VLOOKUP(B29,Tiempos!$A$1:$N$7479,3,FALSE) -> 98742.857 | G29: =+VLOOKUP(B29,Tiempos!$A$1:$N$7479,5,FALSE) -> 24 | H29: =+VLOOKUP(B29,Tiempos!$A$1:$N$7479,7,FALSE) -> INY05 | I29: =+VLOOKUP(A29,OP!$A$1:$I$27881,9,FALSE) -> 213000 | J29: =(VLOOKUP(B29,BD_Spec!$A$1:$K$20517,6,FALSE)) -> Inyección | K29: 24 | L29: =+VLOOKUP(B29,BD_Spec!$A$1:$K$20517,7,FALSE) -> Línea_045
A30: 3950 | B30: 2310160270 | C30: Tapa Para Témpera 30cc Sin Logo Color Blanco P.S. | D30: 1 | E30: 46118 | F30: =+VLOOKUP(B30,Tiempos!$A$1:$N$7479,3,FALSE) -> 63123.288 | G30: =+VLOOKUP(B30,Tiempos!$A$1:$N$7479,5,FALSE) -> 24 | H30: =+VLOOKUP(B30,Tiempos!$A$1:$N$7479,7,FALSE) -> INY06 | I30: 150000 | J30: =(VLOOKUP(B30,BD_Spec!$A$1:$K$20517,6,FALSE)) -> Inyección | K30: 24 | L30: =+VLOOKUP(B30,BD_Spec!$A$1:$K$20517,7,FALSE) -> Línea_Temp
A31: 3915 | B31: 2310160558 | C31: Tapa 30 cc P.S. | D31: =+_xlfn.XLOOKUP(B31,BD_Spec!$A$1:$A$20529,BD_Spec!$L$1:$L$20529) -> 1 | E31: 46132 | F31: =+VLOOKUP(B31,Tiempos!$A$1:$N$7479,3,FALSE) -> 38400 | G31: =+VLOOKUP(B31,Tiempos!$A$1:$N$7479,5,FALSE) -> 24 | H31: =+VLOOKUP(B31,Tiempos!$A$1:$N$7479,7,FALSE) -> INY08 | I31: =+VLOOKUP(A31,OP!$A$1:$I$27881,9,FALSE) -> 367000 | J31: =(VLOOKUP(B31,BD_Spec!$A$1:$K$20517,6,FALSE)) -> Inyección | K31: 24 | L31: =+VLOOKUP(B31,BD_Spec!$A$1:$K$20517,7,FALSE) -> Línea_Temp
A32: 3881 | B32: 2310160479 | C32: Tapa Para Plumón 045 - NP Piel | D32: =+_xlfn.XLOOKUP(B32,BD_Spec!$A$1:$A$20529,BD_Spec!$L$1:$L$20529) -> 1 | E32: 46118 | F32: =+VLOOKUP(B32,Tiempos!$A$1:$N$7479,3,FALSE) -> 96000 | G32: =+VLOOKUP(B32,Tiempos!$A$1:$N$7479,5,FALSE) -> 24 | H32: =+VLOOKUP(B32,Tiempos!$A$1:$N$7479,7,FALSE) -> INY09 | I32: =+VLOOKUP(A32,OP!$A$1:$I$27881,9,FALSE) -> 242000 | J32: =(VLOOKUP(B32,BD_Spec!$A$1:$K$20517,6,FALSE)) -> Inyección | K32: 24 | L32: =+VLOOKUP(B32,BD_Spec!$A$1:$K$20517,7,FALSE) -> Línea_045
A33: 3904 | B33: 2310160472 | C33: Tapa Para Plumón 045 - NP Amarillo | D33: =+_xlfn.XLOOKUP(B33,BD_Spec!$A$1:$A$20529,BD_Spec!$L$1:$L$20529) -> 2 | E33: 46118 | F33: =+VLOOKUP(B33,Tiempos!$A$1:$N$7479,3,FALSE) -> 96000 | G33: =+VLOOKUP(B33,Tiempos!$A$1:$N$7479,5,FALSE) -> 24 | H33: =+VLOOKUP(B33,Tiempos!$A$1:$N$7479,7,FALSE) -> INY09 | I33: =+VLOOKUP(A33,OP!$A$1:$I$27881,9,FALSE) -> 245000 | J33: =(VLOOKUP(B33,BD_Spec!$A$1:$K$20517,6,FALSE)) -> Inyección | K33: 24 | L33: =+VLOOKUP(B33,BD_Spec!$A$1:$K$20517,7,FALSE) -> Línea_045
A34: 3879 | B34: 2310160476 | C34: Tapa Para Plumón 045 - NP Anaranjado | D34: =+_xlfn.XLOOKUP(B34,BD_Spec!$A$1:$A$20529,BD_Spec!$L$1:$L$20529) -> 3 | E34: 46118 | F34: =+VLOOKUP(B34,Tiempos!$A$1:$N$7479,3,FALSE) -> 96000 | G34: =+VLOOKUP(B34,Tiempos!$A$1:$N$7479,5,FALSE) -> 24 | H34: =+VLOOKUP(B34,Tiempos!$A$1:$N$7479,7,FALSE) -> INY09 | I34: =+VLOOKUP(A34,OP!$A$1:$I$27881,9,FALSE) -> 243000 | J34: =(VLOOKUP(B34,BD_Spec!$A$1:$K$20517,6,FALSE)) -> Inyección | K34: 24 | L34: =+VLOOKUP(B34,BD_Spec!$A$1:$K$20517,7,FALSE) -> Línea_045
A35: 3878 | B35: 2310160475 | C35: Tapa Para Plumón 045 - NP Rosado | D35: =+_xlfn.XLOOKUP(B35,BD_Spec!$A$1:$A$20529,BD_Spec!$L$1:$L$20529) -> 4 | E35: 46118 | F35: =+VLOOKUP(B35,Tiempos!$A$1:$N$7479,3,FALSE) -> 96000 | G35: =+VLOOKUP(B35,Tiempos!$A$1:$N$7479,5,FALSE) -> 24 | H35: =+VLOOKUP(B35,Tiempos!$A$1:$N$7479,7,FALSE) -> INY09 | I35: =+VLOOKUP(A35,OP!$A$1:$I$27881,9,FALSE) -> 243000 | J35: =(VLOOKUP(B35,BD_Spec!$A$1:$K$20517,6,FALSE)) -> Inyección | K35: 24 | L35: =+VLOOKUP(B35,BD_Spec!$A$1:$K$20517,7,FALSE) -> Línea_045
A36: 3873 | B36: 2310160469 | C36: Tapa Para Plumón 045 - NP Rojo | D36: =+_xlfn.XLOOKUP(B36,BD_Spec!$A$1:$A$20529,BD_Spec!$L$1:$L$20529) -> 5 | E36: 46118 | F36: =+VLOOKUP(B36,Tiempos!$A$1:$N$7479,3,FALSE) -> 96000 | G36: =+VLOOKUP(B36,Tiempos!$A$1:$N$7479,5,FALSE) -> 24 | H36: =+VLOOKUP(B36,Tiempos!$A$1:$N$7479,7,FALSE) -> INY09 | I36: =+VLOOKUP(A36,OP!$A$1:$I$27881,9,FALSE) -> 231000 | J36: =(VLOOKUP(B36,BD_Spec!$A$1:$K$20517,6,FALSE)) -> Inyección | K36: 24 | L36: =+VLOOKUP(B36,BD_Spec!$A$1:$K$20517,7,FALSE) -> Línea_045
A37: 3880 | B37: 2310160477 | C37: Tapa Para Plumón 045 - NP Celeste | D37: =+_xlfn.XLOOKUP(B37,BD_Spec!$A$1:$A$20529,BD_Spec!$L$1:$L$20529) -> 6 | E37: 46118 | F37: =+VLOOKUP(B37,Tiempos!$A$1:$N$7479,3,FALSE) -> 96000 | G37: =+VLOOKUP(B37,Tiempos!$A$1:$N$7479,5,FALSE) -> 24 | H37: =+VLOOKUP(B37,Tiempos!$A$1:$N$7479,7,FALSE) -> INY09 | I37: =+VLOOKUP(A37,OP!$A$1:$I$27881,9,FALSE) -> 239000 | J37: =(VLOOKUP(B37,BD_Spec!$A$1:$K$20517,6,FALSE)) -> Inyección | K37: 24 | L37: =+VLOOKUP(B37,BD_Spec!$A$1:$K$20517,7,FALSE) -> Línea_045
A38: 3872 | B38: 2310160468 | C38: Tapa Para Plumón 045 - NP Azul | D38: =+_xlfn.XLOOKUP(B38,BD_Spec!$A$1:$A$20529,BD_Spec!$L$1:$L$20529) -> 7 | E38: 46118 | F38: =+VLOOKUP(B38,Tiempos!$A$1:$N$7479,3,FALSE) -> 96000 | G38: =+VLOOKUP(B38,Tiempos!$A$1:$N$7479,5,FALSE) -> 24 | H38: =+VLOOKUP(B38,Tiempos!$A$1:$N$7479,7,FALSE) -> INY09 | I38: =+VLOOKUP(A38,OP!$A$1:$I$27881,9,FALSE) -> 229000 | J38: =(VLOOKUP(B38,BD_Spec!$A$1:$K$20517,6,FALSE)) -> Inyección | K38: 24 | L38: =+VLOOKUP(B38,BD_Spec!$A$1:$K$20517,7,FALSE) -> Línea_045
A39: 3877 | B39: 2310160474 | C39: Tapa Para Plumón 045 - NP Verde Claro | D39: =+_xlfn.XLOOKUP(B39,BD_Spec!$A$1:$A$20529,BD_Spec!$L$1:$L$20529) -> 8 | E39: 46118 | F39: =+VLOOKUP(B39,Tiempos!$A$1:$N$7479,3,FALSE) -> 96000 | G39: =+VLOOKUP(B39,Tiempos!$A$1:$N$7479,5,FALSE) -> 24 | H39: =+VLOOKUP(B39,Tiempos!$A$1:$N$7479,7,FALSE) -> INY09 | I39: =+VLOOKUP(A39,OP!$A$1:$I$27881,9,FALSE) -> 244000 | J39: =(VLOOKUP(B39,BD_Spec!$A$1:$K$20517,6,FALSE)) -> Inyección | K39: 24 | L39: =+VLOOKUP(B39,BD_Spec!$A$1:$K$20517,7,FALSE) -> Línea_045
A40: 3875 | B40: 2310160471 | C40: Tapa Para Plumón 045 - NP Verde | D40: =+_xlfn.XLOOKUP(B40,BD_Spec!$A$1:$A$20529,BD_Spec!$L$1:$L$20529) -> 9 | E40: 46118 | F40: =+VLOOKUP(B40,Tiempos!$A$1:$N$7479,3,FALSE) -> 96000 | G40: =+VLOOKUP(B40,Tiempos!$A$1:$N$7479,5,FALSE) -> 24 | H40: =+VLOOKUP(B40,Tiempos!$A$1:$N$7479,7,FALSE) -> INY09 | I40: =+VLOOKUP(A40,OP!$A$1:$I$27881,9,FALSE) -> 242000 | J40: =(VLOOKUP(B40,BD_Spec!$A$1:$K$20517,6,FALSE)) -> Inyección | K40: 24 | L40: =+VLOOKUP(B40,BD_Spec!$A$1:$K$20517,7,FALSE) -> Línea_045
A41: 3882 | B41: 2310160500 | C41: Tapa Para Plumón 045 - NP Violeta | D41: =+_xlfn.XLOOKUP(B41,BD_Spec!$A$1:$A$20529,BD_Spec!$L$1:$L$20529) -> 10 | E41: 46118 | F41: =+VLOOKUP(B41,Tiempos!$A$1:$N$7479,3,FALSE) -> 96000 | G41: =+VLOOKUP(B41,Tiempos!$A$1:$N$7479,5,FALSE) -> 24 | H41: =+VLOOKUP(B41,Tiempos!$A$1:$N$7479,7,FALSE) -> INY09 | I41: =+VLOOKUP(A41,OP!$A$1:$I$27881,9,FALSE) -> 248000 | J41: =(VLOOKUP(B41,BD_Spec!$A$1:$K$20517,6,FALSE)) -> Inyección | K41: 24 | L41: =+VLOOKUP(B41,BD_Spec!$A$1:$K$20517,7,FALSE) -> Línea_045
A42: 3876 | B42: 2310160473 | C42: Tapa Para Plumón 045 - NP Marrón Oscuro | D42: =+_xlfn.XLOOKUP(B42,BD_Spec!$A$1:$A$20529,BD_Spec!$L$1:$L$20529) -> 11 | E42: 46118 | F42: =+VLOOKUP(B42,Tiempos!$A$1:$N$7479,3,FALSE) -> 96000 | G42: =+VLOOKUP(B42,Tiempos!$A$1:$N$7479,5,FALSE) -> 24 | H42: =+VLOOKUP(B42,Tiempos!$A$1:$N$7479,7,FALSE) -> INY09 | I42: =+VLOOKUP(A42,OP!$A$1:$I$27881,9,FALSE) -> 239000 | J42: =(VLOOKUP(B42,BD_Spec!$A$1:$K$20517,6,FALSE)) -> Inyección | K42: 24 | L42: =+VLOOKUP(B42,BD_Spec!$A$1:$K$20517,7,FALSE) -> Línea_045
... A60: 3911 | B60: 2310160264 | C60: Tapa Azul Para Tinta LT-4 P.S. | D60: =+_xlfn.XLOOKUP(B60,BD_Spec!$A$1:$A$20529,BD_Spec!$L$1:$L$20529) -> 1 | E60: 46139 | F60: =+VLOOKUP(B60,Tiempos!$A$1:$N$7479,3,FALSE) -> 14706.383 | G60: =+VLOOKUP(B60,Tiempos!$A$1:$N$7479,5,FALSE) -> 24 | H60: =+VLOOKUP(B60,Tiempos!$A$1:$N$7479,7,FALSE) -> INY15 | I60: =+VLOOKUP(A60,OP!$A$1:$I$27881,9,FALSE) -> 30000 | J60: =(VLOOKUP(B60,BD_Spec!$A$1:$K$20517,6,FALSE)) -> Inyección | K60: 24 | L60: =+VLOOKUP(B60,BD_Spec!$A$1:$K$20517,7,FALSE) -> Línea_126
A61: 3912 | B61: 2310160265 | C61: Tapa Negra Para Tinta LT-4 P.S. | D61: 2 | E61: 46118 | F61: =+VLOOKUP(B61,Tiempos!$A$1:$N$7479,3,FALSE) -> 14706.383 | G61: =+VLOOKUP(B61,Tiempos!$A$1:$N$7479,5,FALSE) -> 24 | H61: =+VLOOKUP(B61,Tiempos!$A$1:$N$7479,7,FALSE) -> INY15 | I61: =+VLOOKUP(A61,OP!$A$1:$I$27881,9,FALSE) -> 30000 | J61: =(VLOOKUP(B61,BD_Spec!$A$1:$K$20517,6,FALSE)) -> Inyección | K61: 24 | L61: =+VLOOKUP(B61,BD_Spec!$A$1:$K$20517,7,FALSE) -> Línea_126
A62: 3913 | B62: 2310160266 | C62: Tapa Roja Para Tinta LT-4 P.S. | D62: 3 | E62: 46118 | F62: =+VLOOKUP(B62,Tiempos!$A$1:$N$7479,3,FALSE) -> 14706.383 | G62: =+VLOOKUP(B62,Tiempos!$A$1:$N$7479,5,FALSE) -> 24 | H62: =+VLOOKUP(B62,Tiempos!$A$1:$N$7479,7,FALSE) -> INY15 | I62: =+VLOOKUP(A62,OP!$A$1:$I$27881,9,FALSE) -> 50000 | J62: =(VLOOKUP(B62,BD_Spec!$A$1:$K$20517,6,FALSE)) -> Inyección | K62: 24 | L62: =+VLOOKUP(B62,BD_Spec!$A$1:$K$20517,7,FALSE) -> Línea_126
A63: 3944 | B63: 2500120066 | C63: Frascos Transparente de 125cc Para Témpera P.S. | D63: 1 | E63: 46113 | F63: =+VLOOKUP(B63,Tiempos!$A$1:$N$7479,3,FALSE) -> 6545.4545 | G63: =+VLOOKUP(B63,Tiempos!$A$1:$N$7479,5,FALSE) -> 24 | H63: =+VLOOKUP(B63,Tiempos!$A$1:$N$7479,7,FALSE) -> SOP01 | I63: =+VLOOKUP(A63,OP!$A$1:$I$27881,9,FALSE) -> 62000 | J63: =(VLOOKUP(B63,BD_Spec!$A$1:$K$20517,6,FALSE)) -> Soplado | K63: 24 | L63: =+VLOOKUP(B63,BD_Spec!$A$1:$K$20517,7,FALSE) -> Línea_Temp
A64: 3907 | B64: 2310230056 | C64: Frasco 126 Plata Para Tinta | D64: 2 | E64: 46118 | F64: =+VLOOKUP(B64,Tiempos!$A$1:$N$7479,3,FALSE) -> 6400 | G64: =+VLOOKUP(B64,Tiempos!$A$1:$N$7479,5,FALSE) -> 24 | H64: =+VLOOKUP(B64,Tiempos!$A$1:$N$7479,7,FALSE) -> SOP01 | I64: =+VLOOKUP(A64,OP!$A$1:$I$27881,9,FALSE) -> 61000 | J64: =(VLOOKUP(B64,BD_Spec!$A$1:$K$20517,6,FALSE)) -> Soplado | K64: 24 | L64: =+VLOOKUP(B64,BD_Spec!$A$1:$K$20517,7,FALSE) -> Soplado
A65: 3938 | B65: 2310230012 | C65: Frasco Transparente de 250Gr Para Témpera P.S. | D65: =+_xlfn.XLOOKUP(B65,BD_Spec!$A$1:$A$20529,BD_Spec!$L$1:$L$20529) -> 1 | E65: 46113 | F65: =+VLOOKUP(B65,Tiempos!$A$1:$N$7479,3,FALSE) -> 13090.909 | G65: =+VLOOKUP(B65,Tiempos!$A$1:$N$7479,5,FALSE) -> 24 | H65: =+VLOOKUP(B65,Tiempos!$A$1:$N$7479,7,FALSE) -> SOP02 | I65: =+VLOOKUP(A65,OP!$A$1:$I$27881,9,FALSE) -> 20000 | J65: =(VLOOKUP(B65,BD_Spec!$A$1:$K$20517,6,FALSE)) -> Soplado | K65: 24 | L65: =+VLOOKUP(B65,BD_Spec!$A$1:$K$20517,7,FALSE) -> Línea_Temp
A66: 3921 | B66: 2310230030 | C66: Frasco Blanco Ovalado Para Cola Sintética con Aplicador 250Gr P.S. | D66: 2 | E66: 46118 | F66: =+VLOOKUP(B66,Tiempos!$A$1:$N$7479,3,FALSE) -> 13090.909 | G66: =+VLOOKUP(B66,Tiempos!$A$1:$N$7479,5,FALSE) -> 24 | H66: =+VLOOKUP(B66,Tiempos!$A$1:$N$7479,7,FALSE) -> SOP02 | I66: =+VLOOKUP(A66,OP!$A$1:$I$27881,9,FALSE) -> 252000 | J66: =(VLOOKUP(B66,BD_Spec!$A$1:$K$20517,6,FALSE)) -> Soplado | K66: 24 | L66: =+VLOOKUP(B66,BD_Spec!$A$1:$K$20517,7,FALSE) -> Línea_Cola
A67: 3983 | B67: 2110040047 | C67: Crayón triangular cj. cartón Layconsa Puppy Jumbo x 12 | D67: 1 | E67: 46121 | F67: =+VLOOKUP(B67,Tiempos!$A$1:$N$7479,3,FALSE) -> 4000 | G67: 12 | H67: =+VLOOKUP(B67,Tiempos!$A$1:$N$7479,7,FALSE) -> ENCJ03 | I67: =+VLOOKUP(A67,OP!$A$1:$I$27881,9,FALSE) -> 3000 | J67: =(VLOOKUP(B67,BD_Spec!$A$1:$K$20517,6,FALSE)) -> Terminado | K67: 24 | L67: =+VLOOKUP(B67,BD_Spec!$A$1:$K$20517,7,FALSE) -> Crayones
A68: 3986 | B68: 2310360001 | C68: Tubito Para Bolígrafo 036 | D68: 1 | E68: 46120 | F68: =+VLOOKUP(B68,Tiempos!$A$1:$N$7479,3,FALSE) -> 50000 | G68: =+VLOOKUP(B68,Tiempos!$A$1:$N$7479,5,FALSE) -> 12 | H68: =+VLOOKUP(B68,Tiempos!$A$1:$N$7479,7,FALSE) -> EXT01 | I68: =+VLOOKUP(A68,OP!$A$1:$I$27881,9,FALSE) -> 330000 | J68: Semiterminado | K68: 24 | L68: =+VLOOKUP(B68,BD_Spec!$A$1:$K$20517,7,FALSE) -> Línea_036

Sheet BD_Spec
A1: Código_Material | B1: Descripción_Material | C1: Línea_PT | D1: Tipo_Material | E1: Familia_PT | F1: Proceso_Interno | G1: Líneas | H1: Subcomponente | I1: Sublìnea | J1: CONTAR.SI | K1: CV | L1: Secuencia | M1: Color | N1: Tipo_Material2 | Q1: A | R1: A | S1: A | T1: A
A2: 2310340006 | B2: Punta Carga 036F + Adaptador | C2: N/A | D2: Semiterminado | E2: N/A | F2: Semiterminado | G2: Bolígrafo 036 | H2: Colores | I2: Adaptador | J2: 1 | K2: 1 | L2: =IFERROR(_xlfn.XLOOKUP(A2,$Q$2:$Q$155,$T$2:$T$155),1) -> 1 | M2: =IFERROR(VLOOKUP(A2,$Q$2:$S$1310,3,FALSE),"N/A") -> N/A | N2: =IFERROR(VLOOKUP(A2,Materiales!$A$1:$G$5090,7,FALSE),F2) -> Semiterminado | Q2: 2310090469 | R2: Barril Para Marcador 042 - NP Piel P.S. | S2: Piel | T2: =+VLOOKUP(S2,$W$2:$X$13,2,FALSE) -> 1 | W2: Piel | X2: 1
A3: 2310340010 | B3: Punta Carga 036M + Adaptador | C3: N/A | D3: Semiterminado | E3: N/A | F3: Semiterminado | G3: Bolígrafo 036 | H3: Colores | I3: Adaptador | J3: 1 | K3: 1 | L3: =IFERROR(_xlfn.XLOOKUP(A3,$Q$2:$Q$155,$T$2:$T$155),1) -> 1 | M3: =IFERROR(VLOOKUP(A3,$Q$2:$S$1310,3,FALSE),"N/A") -> N/A | N3: =IFERROR(VLOOKUP(A3,Materiales!$A$1:$G$5090,7,FALSE),F3) -> Semiterminado | Q3: 2310090461 | R3: Barril Para Marcador 042 - NP Amarillo P.S. | S3: Amarillo | T3: =+VLOOKUP(S3,$W$2:$X$13,2,FALSE) -> 2 | W3: Amarillo | X3: 2
A4: 2320071180 | B4: Respaldo Boligrafo Layconsa 36 x 10 pz. | C4: N/A | D4: Imprenta | E4: N/A | F4: Semiterminado | G4: Bolígrafo 036 | H4: Colores | I4: Adaptador | J4: 1 | K4: 1 | L4: =IFERROR(_xlfn.XLOOKUP(A4,$Q$2:$Q$155,$T$2:$T$155),1) -> 1 | M4: =IFERROR(VLOOKUP(A4,$Q$2:$S$1310,3,FALSE),"N/A") -> N/A | N4: =IFERROR(VLOOKUP(A4,Materiales!$A$1:$G$5090,7,FALSE),F4) -> Semiterminado | Q4: 2310090466 | R4: Barril Para Marcador 042 - NP Anaranjado P.S. | S4: Anaranjado | T4: =+VLOOKUP(S4,$W$2:$X$13,2,FALSE) -> 3 | W4: Anaranjado | X4: 3
A5: 2320071173 | B5: Respaldo de Marcador 123x4 | C5: N/A | D5: Imprenta | E5: N/A | F5: Semiterminado | G5: Bolígrafo 036 | H5: Colores | I5: Adaptador | J5: 1 | K5: 1 | L5: =IFERROR(_xlfn.XLOOKUP(A5,$Q$2:$Q$155,$T$2:$T$155),1) -> 1 | M5: =IFERROR(VLOOKUP(A5,$Q$2:$S$1310,3,FALSE),"N/A") -> N/A | N5: =IFERROR(VLOOKUP(A5,Materiales!$A$1:$G$5090,7,FALSE),F5) -> Semiterminado | Q5: 2310090464 | R5: Barril Para Marcador 042 - NP Rosado P.S. | S5: Rosado | T5: =+VLOOKUP(S5,$W$2:$X$13,2,FALSE) -> 4 | W5: Rosado | X5: 4
A6: 2310320326 | B6: Homopolímero de Acetato de Vinilo PVA | C6: N/A | D6: Semiterminado | E6: N/A | F6: Masas y Tintas | G6: Masas y Tintas | H6: Cola | I6: Aditivos | J6: 1 | K6: 1 | L6: =IFERROR(_xlfn.XLOOKUP(A6,$Q$2:$Q$155,$T$2:$T$155),1) -> 1 | M6: =IFERROR(VLOOKUP(A6,$Q$2:$S$1310,3,FALSE),"N/A") -> N/A | N6: =IFERROR(VLOOKUP(A6,Materiales!$A$1:$G$5090,7,FALSE),F6) -> Masas y Tintas | Q6: 2310090459 | R6: Barril Para Marcador 042 - NP Rojo P.S. | S6: Rojo | T6: =+VLOOKUP(S6,$W$2:$X$13,2,FALSE) -> 5 | W6: Rojo | X6: 5
A7: 2310030273 | B7: Látex Vinil Acrílico al 55% Témperas | C7: N/A | D7: Semiterminado | E7: N/A | F7: Masas y Tintas | G7: Masas y Tintas | H7: Masa_Temp | I7: Aditivos | J7: 1 | K7: 1 | L7: =IFERROR(_xlfn.XLOOKUP(A7,$Q$2:$Q$155,$T$2:$T$155),1) -> 1 | M7: =IFERROR(VLOOKUP(A7,$Q$2:$S$1310,3,FALSE),"N/A") -> N/A | N7: =IFERROR(VLOOKUP(A7,Materiales!$A$1:$G$5090,7,FALSE),F7) -> Masas y Tintas | Q7: 2310090465 | R7: Barril Para Marcador 042 - NP Morado P.S. | S7: Morado | T7: =+VLOOKUP(S7,$W$2:$X$13,2,FALSE) -> 10 | W7: Morado | X7: 10
A8: 2310180048 | B8: Intermedio T.A. - Marcador | C8: N/A | D8: Semiterminado | E8: N/A | F8: Masas y Tintas | G8: Masas y Tintas | H8: Marcadores | I8: Aditivos | J8: 1 | K8: 1 | L8: =IFERROR(_xlfn.XLOOKUP(A8,$Q$2:$Q$155,$T$2:$T$155),1) -> 1 | M8: =IFERROR(VLOOKUP(A8,$Q$2:$S$1310,3,FALSE),"N/A") -> N/A | N8: =IFERROR(VLOOKUP(A8,Materiales!$A$1:$G$5090,7,FALSE),F8) -> Masas y Tintas | Q8: 2310090463 | R8: Barril Para Marcador 042 - NP Celeste P.S. | S8: Celeste | T8: =+VLOOKUP(S8,$W$2:$X$13,2,FALSE) -> 6 | W8: Celeste | X8: 6
A9: 2310030236 | B9: Dispersión al Agua Azul Rojizo | C9: N/A | D9: Semiterminado | E9: N/A | F9: Masas y Tintas | G9: Masas y Tintas | H9: Masa_Temp | I9: Aditivos | J9: 1 | K9: 1 | L9: =IFERROR(_xlfn.XLOOKUP(A9,$Q$2:$Q$155,$T$2:$T$155),1) -> 1 | M9: =IFERROR(VLOOKUP(A9,$Q$2:$S$1310,3,FALSE),"N/A") -> N/A | N9: =IFERROR(VLOOKUP(A9,Materiales!$A$1:$G$5090,7,FALSE),F9) -> Masas y Tintas | Q9: 2310090457 | R9: Barril Para Marcador 042 - NP Azul P.S. | S9: Azul | T9: =+VLOOKUP(S9,$W$2:$X$13,2,FALSE) -> 7 | W9: Azul | X9: 7
A10: 2310320356 | B10: Terotex 110 P.S. | C10: N/A | D10: Semiterminado | E10: N/A | F10: Masas y Tintas | G10: Masas y Tintas | H10: Limpiatipo | I10: Aditivos | J10: 1 | K10: 1 | L10: =IFERROR(_xlfn.XLOOKUP(A10,$Q$2:$Q$155,$T$2:$T$155),1) -> 1 | M10: =IFERROR(VLOOKUP(A10,$Q$2:$S$1310,3,FALSE),"N/A") -> N/A | N10: =IFERROR(VLOOKUP(A10,Materiales!$A$1:$G$5090,7,FALSE),F10) -> Masas y Tintas | Q10: 2310090468 | R10: Barril Para Marcador 042 - NP Verde Claro P.S. | S10: Verde Claro | T10: =+VLOOKUP(S10,$W$2:$X$13,2,FALSE) -> 8 | W10: Verde Claro | X10: 8
A11: 2310030240 | B11: Dispersión al Agua Verde | C11: N/A | D11: Semiterminado | E11: N/A | F11: Masas y Tintas | G11: Masas y Tintas | H11: Masa_Temp | I11: Aditivos | J11: 1 | K11: 1 | L11: =IFERROR(_xlfn.XLOOKUP(A11,$Q$2:$Q$155,$T$2:$T$155),1) -> 1 | M11: =IFERROR(VLOOKUP(A11,$Q$2:$S$1310,3,FALSE),"N/A") -> N/A | N11: =IFERROR(VLOOKUP(A11,Materiales!$A$1:$G$5090,7,FALSE),F11) -> Masas y Tintas | Q11: 2310090460 | R11: Barril Para Marcador 042 - NP Verde P.S. | S11: Verde | T11: =+VLOOKUP(S11,$W$2:$X$13,2,FALSE) -> 9 | W11: Verde | X11: 9
A12: 2310040536 | B12: Base Molienda de Crayones Roja LYC P.S. | C12: N/A | D12: Semiterminado | E12: N/A | F12: Masas y Tintas | G12: Masas y Tintas | H12: Colores | I12: Base_crayones | J12: 1 | K12: 1 | L12: =IFERROR(_xlfn.XLOOKUP(A12,$Q$2:$Q$155,$T$2:$T$155),1) -> 1 | M12: =IFERROR(VLOOKUP(A12,$Q$2:$S$1310,3,FALSE),"N/A") -> N/A | N12: =IFERROR(VLOOKUP(A12,Materiales!$A$1:$G$5090,7,FALSE),F12) -> Masas y Tintas | Q12: 2310090462 | R12: Barril Para Marcador 042 - NP Marrón P.S. | S12: Marrón | T12: =+VLOOKUP(S12,$W$2:$X$13,2,FALSE) -> 11 | W12: Marrón | X12: 11
A13: 2310040541 | B13: Base Molienda de Crayones Amarilla LYC P.S. | C13: N/A | D13: Semiterminado | E13: N/A | F13: Masas y Tintas | G13: Masas y Tintas | H13: Colores | I13: Base_crayones | J13: 1 | K13: 1 | L13: =IFERROR(_xlfn.XLOOKUP(A13,$Q$2:$Q$155,$T$2:$T$155),1) -> 1 | M13: =IFERROR(VLOOKUP(A13,$Q$2:$S$1310,3,FALSE),"N/A") -> N/A | N13: =IFERROR(VLOOKUP(A13,Materiales!$A$1:$G$5090,7,FALSE),F13) -> Masas y Tintas | Q13: 2310090458 | R13: Barril Para Marcador 042 - NP Negro P.S. | S13: Negro | T13: =+VLOOKUP(S13,$W$2:$X$13,2,FALSE) -> 12 | W13: Negro | X13: 12
A14: 2310040543 | B14: Base Molienda de Crayones Naranja P.S. | C14: N/A | D14: Semiterminado | E14: N/A | F14: Masas y Tintas | G14: Masas y Tintas | H14: Colores | I14: Base_crayones | J14: 1 | K14: 1 | L14: =IFERROR(_xlfn.XLOOKUP(A14,$Q$2:$Q$155,$T$2:$T$155),1) -> 1 | M14: =IFERROR(VLOOKUP(A14,$Q$2:$S$1310,3,FALSE),"N/A") -> N/A | N14: =IFERROR(VLOOKUP(A14,Materiales!$A$1:$G$5090,7,FALSE),F14) -> Masas y Tintas | Q14: 2310160355 | R14: Tapa Para Marcador 042 - N Piel P.S. | S14: Piel | T14: =+VLOOKUP(S14,$W$2:$X$13,2,FALSE) -> 1
A15: 2310040538 | B15: Base Molienda de Crayones Verde Claro LYC P.S. | C15: N/A | D15: Semiterminado | E15: N/A | F15: Masas y Tintas | G15: Masas y Tintas | H15: Colores | I15: Base_crayones | J15: 1 | K15: 1 | L15: =IFERROR(_xlfn.XLOOKUP(A15,$Q$2:$Q$155,$T$2:$T$155),1) -> 1 | M15: =IFERROR(VLOOKUP(A15,$Q$2:$S$1310,3,FALSE),"N/A") -> N/A | N15: =IFERROR(VLOOKUP(A15,Materiales!$A$1:$G$5090,7,FALSE),F15) -> Masas y Tintas | Q15: 2310160242 | R15: Tapa Para Marcador 042 - N Amarillo P.S. | S15: Amarillo | T15: =+VLOOKUP(S15,$W$2:$X$13,2,FALSE) -> 2 | W15: Blanco | X15: 9
A16: 2310040537 | B16: Base Molienda de Crayones Verde Oscuro LYC P.S. | C16: N/A | D16: Semiterminado | E16: N/A | F16: Masas y Tintas | G16: Masas y Tintas | H16: Colores | I16: Base_crayones | J16: 1 | K16: 1 | L16: =IFERROR(_xlfn.XLOOKUP(A16,$Q$2:$Q$155,$T$2:$T$155),1) -> 1 | M16: =IFERROR(VLOOKUP(A16,$Q$2:$S$1310,3,FALSE),"N/A") -> N/A | N16: =IFERROR(VLOOKUP(A16,Materiales!$A$1:$G$5090,7,FALSE),F16) -> Masas y Tintas | Q16: 2310160247 | R16: Tapa Para Marcador 042 - N Anaranjado P.S. | S16: Anaranjado | T16: =+VLOOKUP(S16,$W$2:$X$13,2,FALSE) -> 3 | W16: Amarillo | X16: 1
A17: 2310040540 | B17: Base Molienda de Crayones Celeste LYC P.S. | C17: N/A | D17: Semiterminado | E17: N/A | F17: Masas y Tintas | G17: Masas y Tintas | H17: Colores | I17: Base_crayones | J17: 1 | K17: 1 | L17: =IFERROR(_xlfn.XLOOKUP(A17,$Q$2:$Q$155,$T$2:$T$155),1) -> 1 | M17: =IFERROR(VLOOKUP(A17,$Q$2:$S$1310,3,FALSE),"N/A") -> N/A | N17: =IFERROR(VLOOKUP(A17,Materiales!$A$1:$G$5090,7,FALSE),F17) -> Masas y Tintas | Q17: 2310160245 | R17: Tapa Para Marcador 042 - N Rosado P.S. | S17: Rosado | T17: =+VLOOKUP(S17,$W$2:$X$13,2,FALSE) -> 4 | W17: Anaranjado | X17: 2
A18: 2310040545 | B18: Base Molienda de Crayones Azul P.S. | C18: N/A | D18: Semiterminado | E18: N/A | F18: Masas y Tintas | G18: Masas y Tintas | H18: Colores | I18: Base_crayones | J18: 1 | K18: 1 | L18: =IFERROR(_xlfn.XLOOKUP(A18,$Q$2:$Q$155,$T$2:$T$155),1) -> 1 | M18: =IFERROR(VLOOKUP(A18,$Q$2:$S$1310,3,FALSE),"N/A") -> N/A | N18: =IFERROR(VLOOKUP(A18,Materiales!$A$1:$G$5090,7,FALSE),F18) -> Masas y Tintas | Q18: 2310160240 | R18: Tapa Para Marcador 042 - N Rojo P.S. | S18: Rojo | T18: =+VLOOKUP(S18,$W$2:$X$13,2,FALSE) -> 5 | W18: Rosado | X18: 3
A19: 2310040572 | B19: Base Molienda de Crayones Blanco P.S. | C19: N/A | D19: Semiterminado | E19: N/A | F19: Masas y Tintas | G19: Masas y Tintas | H19: Colores | I19: Base_crayones | J19: 1 | K19: 1 | L19: =IFERROR(_xlfn.XLOOKUP(A19,$Q$2:$Q$155,$T$2:$T$155),1) -> 1 | M19: =IFERROR(VLOOKUP(A19,$Q$2:$S$1310,3,FALSE),"N/A") -> N/A | N19: =IFERROR(VLOOKUP(A19,Materiales!$A$1:$G$5090,7,FALSE),F19) -> Masas y Tintas | Q19: 2310160246 | R19: Tapa Para Marcador 042 - N Morado P.S. | S19: Morado | T19: =+VLOOKUP(S19,$W$2:$X$13,2,FALSE) -> 10 | W19: Rojo | X19: 4
A20: 2310040539 | B20: Base Molienda de Crayones Violeta LYC P.S. | C20: N/A | D20: Semiterminado | E20: N/A | F20: Masas y Tintas | G20: Masas y Tintas | H20: Colores | I20: Base_crayones | J20: 1 | K20: 1 | L20: =IFERROR(_xlfn.XLOOKUP(A20,$Q$2:$Q$155,$T$2:$T$155),1) -> 1 | M20: =IFERROR(VLOOKUP(A20,$Q$2:$S$1310,3,FALSE),"N/A") -> N/A | N20: =IFERROR(VLOOKUP(A20,Materiales!$A$1:$G$5090,7,FALSE),F20) -> Masas y Tintas | Q20: 2310160244 | R20: Tapa Para Marcador 042 - N Celeste P.S. | S20: Celeste | T20: =+VLOOKUP(S20,$W$2:$X$13,2,FALSE) -> 6 | W20: Morado | X20: 10
A21: 2310040544 | B21: Base Molienda de Crayones Negro P.S. | C21: N/A | D21: Semiterminado | E21: N/A | F21: Masas y Tintas | G21: Masas y Tintas | H21: Colores | I21: Base_crayones | J21: 1 | K21: 1 | L21: =IFERROR(_xlfn.XLOOKUP(A21,$Q$2:$Q$155,$T$2:$T$155),1) -> 1 | M21: =IFERROR(VLOOKUP(A21,$Q$2:$S$1310,3,FALSE),"N/A") -> N/A | N21: =IFERROR(VLOOKUP(A21,Materiales!$A$1:$G$5090,7,FALSE),F21) -> Masas y Tintas | Q21: 2310160238 | R21: Tapa Para Marcador 042 - N Azul P.S. | S21: Azul | T21: =+VLOOKUP(S21,$W$2:$X$13,2,FALSE) -> 7 | W21: Celeste | X21: 8
A22: 2310040546 | B22: Base Molienda de Crayones Rosado P.S. | C22: N/A | D22: Semiterminado | E22: N/A | F22: Masas y Tintas | G22: Masas y Tintas | H22: Colores | I22: Base_crayones | J22: 1 | K22: 1 | L22: =IFERROR(_xlfn.XLOOKUP(A22,$Q$2:$Q$155,$T$2:$T$155),1) -> 1 | M22: =IFERROR(VLOOKUP(A22,$Q$2:$S$1310,3,FALSE),"N/A") -> N/A | N22: =IFERROR(VLOOKUP(A22,Materiales!$A$1:$G$5090,7,FALSE),F22) -> Masas y Tintas | Q22: 2310160356 | R22: Tapa Para Marcador 042 - N Verde Claro P.S. | S22: Verde Claro | T22: =+VLOOKUP(S22,$W$2:$X$13,2,FALSE) -> 8 | W22: Azul | X22: 7
A23: 2310040542 | B23: Base Molienda de Crayones Marrón P.S. | C23: N/A | D23: Semiterminado | E23: N/A | F23: Masas y Tintas | G23: Masas y Tintas | H23: Colores | I23: Base_crayones | J23: 1 | K23: 1 | L23: =IFERROR(_xlfn.XLOOKUP(A23,$Q$2:$Q$155,$T$2:$T$155),1) -> 1 | M23: =IFERROR(VLOOKUP(A23,$Q$2:$S$1310,3,FALSE),"N/A") -> N/A | N23: =IFERROR(VLOOKUP(A23,Materiales!$A$1:$G$5090,7,FALSE),F23) -> Masas y Tintas | Q23: 2310160241 | R23: Tapa Para Marcador 042 - N Verde P.S. | S23: Verde | T23: =+VLOOKUP(S23,$W$2:$X$13,2,FALSE) -> 9 | W23: Verde Claro | X23: 5
A24: 2310360001 | B24: Tubito Para Bolígrafo 036 | C24: N/A | D24: Semiterminado | E24: N/A | F24: Extrusión | G24: Línea_036 | H24: Tubo | I24: Bolígrafo | J24: 1 | K24: 1 | L24: =IFERROR(_xlfn.XLOOKUP(A24,$Q$2:$Q$155,$T$2:$T$155),1) -> 1 | M24: =IFERROR(VLOOKUP(A24,$Q$2:$S$1310,3,FALSE),"N/A") -> N/A | N24: =IFERROR(VLOOKUP(A24,Materiales!$A$1:$G$5090,7,FALSE),F24) -> Extrusión | Q24: 2310160243 | R24: Tapa Para Marcador 042 - N Marrón P.S. | S24: Marrón | T24: =+VLOOKUP(S24,$W$2:$X$13,2,FALSE) -> 11 | W24: Verde | X24: 6
A25: 2310160416 | B25: Tapa Para Bolígrafo 033 Rojo | C25: N/A | D25: Semiterminado | E25: N/A | F25: Inyección | G25: Línea_036 | H25: Tapa | I25: Bolígrafo | J25: 1 | K25: 1 | L25: =IFERROR(_xlfn.XLOOKUP(A25,$Q$2:$Q$155,$T$2:$T$155),1) -> 1 | M25: =IFERROR(VLOOKUP(A25,$Q$2:$S$1310,3,FALSE),"N/A") -> N/A | N25: =IFERROR(VLOOKUP(A25,Materiales!$A$1:$G$5090,7,FALSE),F25) -> Inyección | Q25: 2310160239 | R25: Tapa Para Marcador 042 - N Negro P.S. | S25: Negro | T25: =+VLOOKUP(S25,$W$2:$X$13,2,FALSE) -> 12 | W25: Marrón | X25: 11
A26: 2310160390 | B26: Tapa 036 Amarillo | C26: N/A | D26: Semiterminado | E26: N/A | F26: Inyección | G26: Línea_036 | H26: Tapa | I26: Bolígrafo | J26: 1 | K26: 1 | L26: =IFERROR(_xlfn.XLOOKUP(A26,$Q$2:$Q$155,$T$2:$T$155),1) -> 1 | M26: =IFERROR(VLOOKUP(A26,$Q$2:$S$1310,3,FALSE),"N/A") -> N/A | N26: =IFERROR(VLOOKUP(A26,Materiales!$A$1:$G$5090,7,FALSE),F26) -> Inyección | Q26: 2310160353 | R26: Tapita Para Marcador 042 - N Piel | S26: Piel | T26: =+VLOOKUP(S26,$W$2:$X$13,2,FALSE) -> 1 | W26: Negro | X26: 12
A27: 2310160396 | B27: Tapa 036 Marron | C27: N/A | D27: Semiterminado | E27: N/A | F27: Inyección | G27: Línea_036 | H27: Tapa | I27: Bolígrafo | J27: 1 | K27: 1 | L27: =IFERROR(_xlfn.XLOOKUP(A27,$Q$2:$Q$155,$T$2:$T$155),1) -> 1 | M27: =IFERROR(VLOOKUP(A27,$Q$2:$S$1310,3,FALSE),"N/A") -> N/A | N27: =IFERROR(VLOOKUP(A27,Materiales!$A$1:$G$5090,7,FALSE),F27) -> Inyección | Q27: 2310160252 | R27: Tapita Para Marcador 042 - N Amarillo | S27: Amarillo | T27: =+VLOOKUP(S27,$W$2:$X$13,2,FALSE) -> 2
A28: 2310160393 | B28: Tapa 036 Morado | C28: N/A | D28: Semiterminado | E28: N/A | F28: Inyección | G28: Línea_036 | H28: Tapa | I28: Bolígrafo | J28: 1 | K28: 1 | L28: =IFERROR(_xlfn.XLOOKUP(A28,$Q$2:$Q$155,$T$2:$T$155),1) -> 1 | M28: =IFERROR(VLOOKUP(A28,$Q$2:$S$1310,3,FALSE),"N/A") -> N/A | N28: =IFERROR(VLOOKUP(A28,Materiales!$A$1:$G$5090,7,FALSE),F28) -> Inyección | Q28: 2310160257 | R28: Tapita Para Marcador 042 - N Anaranjado | S28: Anaranjado | T28: =+VLOOKUP(S28,$W$2:$X$13,2,FALSE) -> 3
A29: 2310160391 | B29: Tapa 036 Naranja | C29: N/A | D29: Semiterminado | E29: N/A | F29: Inyección | G29: Línea_036 | H29: Tapa | I29: Bolígrafo | J29: 1 | K29: 1 | L29: =IFERROR(_xlfn.XLOOKUP(A29,$Q$2:$Q$155,$T$2:$T$155),1) -> 1 | M29: =IFERROR(VLOOKUP(A29,$Q$2:$S$1310,3,FALSE),"N/A") -> N/A | N29: =IFERROR(VLOOKUP(A29,Materiales!$A$1:$G$5090,7,FALSE),F29) -> Inyección | Q29: 2310160255 | R29: Tapita Para Marcador 042 - N Rosado | S29: Rosado | T29: =+VLOOKUP(S29,$W$2:$X$13,2,FALSE) -> 4
A30: 2310160392 | B30: Tapa 036 Rosado | C30: N/A | D30: Semiterminado | E30: N/A | F30: Inyección | G30: Línea_036 | H30: Tapa | I30: Bolígrafo | J30: 1 | K30: 1 | L30: =IFERROR(_xlfn.XLOOKUP(A30,$Q$2:$Q$155,$T$2:$T$155),1) -> 1 | M30: =IFERROR(VLOOKUP(A30,$Q$2:$S$1310,3,FALSE),"N/A") -> N/A | N30: =IFERROR(VLOOKUP(A30,Materiales!$A$1:$G$5090,7,FALSE),F30) -> Inyección | Q30: 2310160250 | R30: Tapita Para Marcador 042 - N Rojo | S30: Rojo | T30: =+VLOOKUP(S30,$W$2:$X$13,2,FALSE) -> 5
A31: 2310160394 | B31: Tapa 036 Turqueza | C31: N/A | D31: Semiterminado | E31: N/A | F31: Inyección | G31: Línea_036 | H31: Tapa | I31: Bolígrafo | J31: 1 | K31: 1 | L31: =IFERROR(_xlfn.XLOOKUP(A31,$Q$2:$Q$155,$T$2:$T$155),1) -> 1 | M31: =IFERROR(VLOOKUP(A31,$Q$2:$S$1310,3,FALSE),"N/A") -> N/A | N31: =IFERROR(VLOOKUP(A31,Materiales!$A$1:$G$5090,7,FALSE),F31) -> Inyección | Q31: 2310160256 | R31: Tapita Para Marcador 042 - N Morado | S31: Morado | T31: =+VLOOKUP(S31,$W$2:$X$13,2,FALSE) -> 10
A32: 2310160062 | B32: Tapa Para Bolígrafo 036 Azul | C32: N/A | D32: Semiterminado | E32: N/A | F32: Inyección | G32: Línea_036 | H32: Tapa | I32: Bolígrafo | J32: 1 | K32: 1 | L32: =IFERROR(_xlfn.XLOOKUP(A32,$Q$2:$Q$155,$T$2:$T$155),1) -> 1 | M32: =IFERROR(VLOOKUP(A32,$Q$2:$S$1310,3,FALSE),"N/A") -> N/A | N32: =IFERROR(VLOOKUP(A32,Materiales!$A$1:$G$5090,7,FALSE),F32) -> Inyección | Q32: 2310160254 | R32: Tapita Para Marcador 042 - N Celeste | S32: Celeste | T32: =+VLOOKUP(S32,$W$2:$X$13,2,FALSE) -> 6
A33: 2310160064 | B33: Tapa Para Bolígrafo 036 Negro | C33: N/A | D33: Semiterminado | E33: N/A | F33: Inyección | G33: Línea_036 | H33: Tapa | I33: Bolígrafo | J33: 1 | K33: 1 | L33: =IFERROR(_xlfn.XLOOKUP(A33,$Q$2:$Q$155,$T$2:$T$155),1) -> 1 | M33: =IFERROR(VLOOKUP(A33,$Q$2:$S$1310,3,FALSE),"N/A") -> N/A | N33: =IFERROR(VLOOKUP(A33,Materiales!$A$1:$G$5090,7,FALSE),F33) -> Inyección | Q33: 2310160248 | R33: Tapita Para Marcador 042 - N Azul | S33: Azul | T33: =+VLOOKUP(S33,$W$2:$X$13,2,FALSE) -> 7
A34: 2310160063 | B34: Tapa Para Bolígrafo 036 Rojo | C34: N/A | D34: Semiterminado | E34: N/A | F34: Inyección | G34: Línea_036 | H34: Tapa | I34: Bolígrafo | J34: 1 | K34: 1 | L34: =IFERROR(_xlfn.XLOOKUP(A34,$Q$2:$Q$155,$T$2:$T$155),1) -> 1 | M34: =IFERROR(VLOOKUP(A34,$Q$2:$S$1310,3,FALSE),"N/A") -> N/A | N34: =IFERROR(VLOOKUP(A34,Materiales!$A$1:$G$5090,7,FALSE),F34) -> Inyección | Q34: 2310160354 | R34: Tapita Para Marcador 042 - N Verde Claro | S34: Verde Claro | T34: =+VLOOKUP(S34,$W$2:$X$13,2,FALSE) -> 8
A35: 2310160417 | B35: Tapa Para Bolígrafo 036 Verde Claro | C35: N/A | D35: Semiterminado | E35: N/A | F35: Inyección | G35: Línea_036 | H35: Tapa | I35: Bolígrafo | J35: 1 | K35: 1 | L35: =IFERROR(_xlfn.XLOOKUP(A35,$Q$2:$Q$155,$T$2:$T$155),1) -> 1 | M35: =IFERROR(VLOOKUP(A35,$Q$2:$S$1310,3,FALSE),"N/A") -> N/A | N35: =IFERROR(VLOOKUP(A35,Materiales!$A$1:$G$5090,7,FALSE),F35) -> Inyección | Q35: 2310160251 | R35: Tapita Para Marcador 042 - N Verde | S35: Verde | T35: =+VLOOKUP(S35,$W$2:$X$13,2,FALSE) -> 9
A36: 2310160383 | B36: Tapita 036 Amarillo N | C36: N/A | D36: Semiterminado | E36: N/A | F36: Inyección | G36: Línea_036 | H36: Tapita | I36: Bolígrafo | J36: 1 | K36: 1 | L36: =IFERROR(_xlfn.XLOOKUP(A36,$Q$2:$Q$155,$T$2:$T$155),1) -> 1 | M36: =IFERROR(VLOOKUP(A36,$Q$2:$S$1310,3,FALSE),"N/A") -> N/A | N36: =IFERROR(VLOOKUP(A36,Materiales!$A$1:$G$5090,7,FALSE),F36) -> Inyección | Q36: 2310160253 | R36: Tapita Para Marcador 042 - N Marrón | S36: Marrón | T36: =+VLOOKUP(S36,$W$2:$X$13,2,FALSE) -> 11
A37: 2310160389 | B37: Tapita 036 Marron N | C37: N/A | D37: Semiterminado | E37: N/A | F37: Inyección | G37: Línea_036 | H37: Tapita | I37: Bolígrafo | J37: 1 | K37: 1 | L37: =IFERROR(_xlfn.XLOOKUP(A37,$Q$2:$Q$155,$T$2:$T$155),1) -> 1 | M37: =IFERROR(VLOOKUP(A37,$Q$2:$S$1310,3,FALSE),"N/A") -> N/A | N37: =IFERROR(VLOOKUP(A37,Materiales!$A$1:$G$5090,7,FALSE),F37) -> Inyección | Q37: 2310160249 | R37: Tapita Para Marcador 042 - N Negro | S37: Negro | T37: =+VLOOKUP(S37,$W$2:$X$13,2,FALSE) -> 12
A38: 2310160386 | B38: Tapita 036 Morado N | C38: N/A | D38: Semiterminado | E38: N/A | F38: Inyección | G38: Línea_036 | H38: Tapita | I38: Bolígrafo | J38: 1 | K38: 1 | L38: =IFERROR(_xlfn.XLOOKUP(A38,$Q$2:$Q$155,$T$2:$T$155),1) -> 1 | M38: =IFERROR(VLOOKUP(A38,$Q$2:$S$1310,3,FALSE),"N/A") -> N/A | N38: =IFERROR(VLOOKUP(A38,Materiales!$A$1:$G$5090,7,FALSE),F38) -> Inyección | Q38: 2310090502 | R38: Barril Para Marcador LYC Serigrafiado 047 - MK Piel Imp. Blanco | S38: Piel | T38: =+VLOOKUP(S38,$W$2:$X$13,2,FALSE) -> 1
... A131: 2310160379 | B131: Tapa Para Marcador 042 - N 123 Verde P.S. | C131: N/A | D131: Semiterminado | E131: N/A | F131: Inyección | G131: Línea_042 | H131: Tapa | I131: Colores | J131: 1 | K131: 1 | L131: =IFERROR(_xlfn.XLOOKUP(A131,$Q$2:$Q$155,$T$2:$T$155),1) -> 1 | M131: =IFERROR(VLOOKUP(A131,$Q$2:$S$1310,3,FALSE),"N/A") -> N/A | N131: =IFERROR(VLOOKUP(A131,Materiales!$A$1:$G$5090,7,FALSE),F131) -> Inyección | Q131: 2310210138 | R131: Plumones LYC School 45 Granel Piel NP P.S. | S131: Piel | T131: =+VLOOKUP(S131,$W$2:$X$13,2,FALSE) -> 1
A132: 2310160408 | B132: Tapita Para Marcador 042 (123) - N Rojo | C132: N/A | D132: Semiterminado | E132: N/A | F132: Inyección | G132: Línea_042 | H132: Tapita | I132: Colores | J132: 1 | K132: 1 | L132: =IFERROR(_xlfn.XLOOKUP(A132,$Q$2:$Q$155,$T$2:$T$155),1) -> 1 | M132: =IFERROR(VLOOKUP(A132,$Q$2:$S$1310,3,FALSE),"N/A") -> N/A | N132: =IFERROR(VLOOKUP(A132,Materiales!$A$1:$G$5090,7,FALSE),F132) -> Inyección | Q132: 2310040558 | R132: Formado Crayón Jumbo LYC Marrón | S132: Marrón | T132: =+VLOOKUP(S132,$W$15:$X$26,2,FALSE) -> 11
A133: 2310160503 | B133: Tapa Para Marcador NT Azul 123 P.S. | C133: N/A | D133: Semiterminado | E133: N/A | F133: Inyección | G133: Línea_042 | H133: Tapa | I133: Colores | J133: 1 | K133: 1 | L133: =IFERROR(_xlfn.XLOOKUP(A133,$Q$2:$Q$155,$T$2:$T$155),1) -> 1 | M133: =IFERROR(VLOOKUP(A133,$Q$2:$S$1310,3,FALSE),"N/A") -> N/A | N133: =IFERROR(VLOOKUP(A133,Materiales!$A$1:$G$5090,7,FALSE),F133) -> Inyección | Q133: 2310040552 | R133: Formado Crayón Jumbo LYC Verde Oscuro | S133: Verde | T133: =+VLOOKUP(S133,$W$15:$X$26,2,FALSE) -> 6
A134: 2310160504 | B134: Tapa Para Marcador NT 123 Negro P.S. | C134: N/A | D134: Semiterminado | E134: N/A | F134: Inyección | G134: Línea_042 | H134: Tapa | I134: Colores | J134: 1 | K134: 1 | L134: =IFERROR(_xlfn.XLOOKUP(A134,$Q$2:$Q$155,$T$2:$T$155),1) -> 1 | M134: =IFERROR(VLOOKUP(A134,$Q$2:$S$1310,3,FALSE),"N/A") -> N/A | N134: =IFERROR(VLOOKUP(A134,Materiales!$A$1:$G$5090,7,FALSE),F134) -> Inyección | Q134: 2310040555 | R134: Formado Crayón Jumbo LYC Violeta | S134: Morado | T134: =+VLOOKUP(S134,$W$15:$X$26,2,FALSE) -> 10
A135: 2310160505 | B135: Tapa Para Marcador NT 123 Rojo P.S. | C135: N/A | D135: Semiterminado | E135: N/A | F135: Inyección | G135: Línea_042 | H135: Tapa | I135: Colores | J135: 1 | K135: 1 | L135: =IFERROR(_xlfn.XLOOKUP(A135,$Q$2:$Q$155,$T$2:$T$155),1) -> 1 | M135: =IFERROR(VLOOKUP(A135,$Q$2:$S$1310,3,FALSE),"N/A") -> N/A | N135: =IFERROR(VLOOKUP(A135,Materiales!$A$1:$G$5090,7,FALSE),F135) -> Inyección | Q135: 2310040571 | R135: Formado Crayón Triangular Jumbo LYC Blanco | S135: Blanco | T135: =+VLOOKUP(S135,$W$15:$X$26,2,FALSE) -> 9
A136: 2310160506 | B136: Tapa Para Marcador NT 123 Verde P.S. | C136: N/A | D136: Semiterminado | E136: N/A | F136: Inyección | G136: Línea_042 | H136: Tapa | I136: Colores | J136: 1 | K136: 1 | L136: =IFERROR(_xlfn.XLOOKUP(A136,$Q$2:$Q$155,$T$2:$T$155),1) -> 1 | M136: =IFERROR(VLOOKUP(A136,$Q$2:$S$1310,3,FALSE),"N/A") -> N/A | N136: =IFERROR(VLOOKUP(A136,Materiales!$A$1:$G$5090,7,FALSE),F136) -> Inyección | Q136: 2310040362 | R136: Formado Crayón Triangular Jumbo LYC Amarillo | S136: Amarillo | T136: =+VLOOKUP(S136,$W$15:$X$26,2,FALSE) -> 1
A137: 2310500001 | B137: Pack Pizarra Mágica + Marcador 123 | C137: N/A | D137: Semiterminado | E137: N/A | F137: Inyección | G137: Línea_042 | H137: Tapita | I137: Colores | J137: 1 | K137: 1 | L137: =IFERROR(_xlfn.XLOOKUP(A137,$Q$2:$Q$155,$T$2:$T$155),1) -> 1 | M137: =IFERROR(VLOOKUP(A137,$Q$2:$S$1310,3,FALSE),"N/A") -> N/A | N137: =IFERROR(VLOOKUP(A137,Materiales!$A$1:$G$5090,7,FALSE),F137) -> Inyección | Q137: 2310040364 | R137: Formado Crayón Triangular Jumbo LYC Anaranjado | S137: Anaranjado | T137: =+VLOOKUP(S137,$W$15:$X$26,2,FALSE) -> 2
A138: 2310090505 | B138: Barril Para Resaltador 048 MK fluor Naranja P.S. | C138: N/A | D138: Semiterminado | E138: N/A | F138: Inyección | G138: Línea_048 | H138: Barril | I138: Colores | J138: 1 | K138: 1 | L138: =IFERROR(_xlfn.XLOOKUP(A138,$Q$2:$Q$155,$T$2:$T$155),1) -> 1 | M138: =IFERROR(VLOOKUP(A138,$Q$2:$S$1310,3,FALSE),"N/A") -> N/A | N138: =IFERROR(VLOOKUP(A138,Materiales!$A$1:$G$5090,7,FALSE),F138) -> Inyección | Q138: 2310040368 | R138: Formado Crayón Triangular Jumbo LYC Azul | S138: Azul | T138: =+VLOOKUP(S138,$W$15:$X$26,2,FALSE) -> 7
A139: 2310090506 | B139: Barril Para Resaltador 048 MK fluor Rosado P.S. | C139: N/A | D139: Semiterminado | E139: N/A | F139: Inyección | G139: Línea_048 | H139: Barril | I139: Colores | J139: 1 | K139: 1 | L139: =IFERROR(_xlfn.XLOOKUP(A139,$Q$2:$Q$155,$T$2:$T$155),1) -> 1 | M139: =IFERROR(VLOOKUP(A139,$Q$2:$S$1310,3,FALSE),"N/A") -> N/A | N139: =IFERROR(VLOOKUP(A139,Materiales!$A$1:$G$5090,7,FALSE),F139) -> Inyección | Q139: 2310040372 | R139: Formado Crayón Triangular Jumbo LYC Marrón | S139: Marrón | T139: =+VLOOKUP(S139,$W$15:$X$26,2,FALSE) -> 11
A140: 2310090503 | B140: Barril Para Resaltador 048 MK fluor Amarillo P.S. | C140: N/A | D140: Semiterminado | E140: N/A | F140: Inyección | G140: Línea_048 | H140: Barril | I140: Colores | J140: 1 | K140: 1 | L140: =IFERROR(_xlfn.XLOOKUP(A140,$Q$2:$Q$155,$T$2:$T$155),1) -> 1 | M140: =IFERROR(VLOOKUP(A140,$Q$2:$S$1310,3,FALSE),"N/A") -> N/A | N140: =IFERROR(VLOOKUP(A140,Materiales!$A$1:$G$5090,7,FALSE),F140) -> Inyección | Q140: 2310040370 | R140: Formado Crayón Triangular Jumbo LYC Negro | S140: Negro | T140: =+VLOOKUP(S140,$W$15:$X$26,2,FALSE) -> 12
A141: 2310090504 | B141: Barril Para Resaltador 048 MK fluor Verde P.S. | C141: N/A | D141: Semiterminado | E141: N/A | F141: Inyección | G141: Línea_048 | H141: Barril | I141: Colores | J141: 1 | K141: 1 | L141: =IFERROR(_xlfn.XLOOKUP(A141,$Q$2:$Q$155,$T$2:$T$155),1) -> 1 | M141: =IFERROR(VLOOKUP(A141,$Q$2:$S$1310,3,FALSE),"N/A") -> N/A | N141: =IFERROR(VLOOKUP(A141,Materiales!$A$1:$G$5090,7,FALSE),F141) -> Inyección | Q141: 2310040361 | R141: Formado Crayón Triangular Jumbo LYC Rojo | S141: Rojo | T141: =+VLOOKUP(S141,$W$15:$X$26,2,FALSE) -> 4
A142: 2310090487 | B142: Barril Para Resaltador 048 NP Grabado fluor Amarillo P.S. | C142: N/A | D142: Semiterminado | E142: N/A | F142: Inyección | G142: Línea_048 | H142: Barril | I142: Colores | J142: 1 | K142: 1 | L142: =IFERROR(_xlfn.XLOOKUP(A142,$Q$2:$Q$155,$T$2:$T$155),1) -> 1 | M142: =IFERROR(VLOOKUP(A142,$Q$2:$S$1310,3,FALSE),"N/A") -> N/A | N142: =IFERROR(VLOOKUP(A142,Materiales!$A$1:$G$5090,7,FALSE),F142) -> Inyección | Q142: 2310040371 | R142: Formado Crayón Triangular Jumbo LYC Rosado | S142: Rosado | T142: =+VLOOKUP(S142,$W$15:$X$26,2,FALSE) -> 3
A143: 2310090490 | B143: Barril Para Resaltador 048 NP Grabado fluor Naranja P.S. | C143: N/A | D143: Semiterminado | E143: N/A | F143: Inyección | G143: Línea_048 | H143: Barril | I143: Colores | J143: 1 | K143: 1 | L143: =IFERROR(_xlfn.XLOOKUP(A143,$Q$2:$Q$155,$T$2:$T$155),1) -> 1 | M143: =IFERROR(VLOOKUP(A143,$Q$2:$S$1310,3,FALSE),"N/A") -> N/A | N143: =IFERROR(VLOOKUP(A143,Materiales!$A$1:$G$5090,7,FALSE),F143) -> Inyección | Q143: 2310040365 | R143: Formado Crayón Triangular Jumbo LYC Verde Claro | S143: Verde Claro | T143: =+VLOOKUP(S143,$W$15:$X$26,2,FALSE) -> 5
... A155: 2310160460 | B155: Tapa Para Resaltador 048 fluorescente- N Naranja P.S. | C155: N/A | D155: Semiterminado | E155: N/A | F155: Inyección | G155: Línea_048 | H155: Tapa | I155: Colores | J155: 1 | K155: 1 | L155: =IFERROR(_xlfn.XLOOKUP(A155,$Q$2:$Q$155,$T$2:$T$155),1) -> 1 | M155: =IFERROR(VLOOKUP(A155,$Q$2:$S$1310,3,FALSE),"N/A") -> N/A | N155: =IFERROR(VLOOKUP(A155,Materiales!$A$1:$G$5090,7,FALSE),F155) -> Inyección | Q155: 2310040547 | R155: Formado Crayón Jumbo LYC Rojo | S155: Rojo | T155: =+VLOOKUP(S155,$W$15:$X$26,2,FALSE) -> 4
A156: 2310160461 | B156: Tapa Para Resaltador 048 fluorescente- N Rosado P.S. | C156: N/A | D156: Semiterminado | E156: N/A | F156: Inyección | G156: Línea_048 | H156: Tapa | I156: Colores | J156: 1 | K156: 1 | L156: =IFERROR(_xlfn.XLOOKUP(A156,$Q$2:$Q$155,$T$2:$T$155),1) -> 1 | M156: =IFERROR(VLOOKUP(A156,$Q$2:$S$1310,3,FALSE),"N/A") -> N/A | N156: =IFERROR(VLOOKUP(A156,Materiales!$A$1:$G$5090,7,FALSE),F156) -> Inyección
A157: 2310160462 | B157: Tapita Para Resaltador 048 fluorescente- N Amarillo P.S. | C157: N/A | D157: Semiterminado | E157: N/A | F157: Inyección | G157: Línea_048 | H157: Tapita | I157: Colores | J157: 1 | K157: 1 | L157: =IFERROR(_xlfn.XLOOKUP(A157,$Q$2:$Q$155,$T$2:$T$155),1) -> 1 | M157: =IFERROR(VLOOKUP(A157,$Q$2:$S$1310,3,FALSE),"N/A") -> N/A | N157: =IFERROR(VLOOKUP(A157,Materiales!$A$1:$G$5090,7,FALSE),F157) -> Inyección
A158: 2310160465 | B158: Tapita Para Resaltador 048 fluorescente- N Rosado P.S. | C158: N/A | D158: Semiterminado | E158: N/A | F158: Inyección | G158: Línea_048 | H158: Tapita | I158: Colores | J158: 1 | K158: 1 | L158: =IFERROR(_xlfn.XLOOKUP(A158,$Q$2:$Q$155,$T$2:$T$155),1) -> 1 | M158: =IFERROR(VLOOKUP(A158,$Q$2:$S$1310,3,FALSE),"N/A") -> N/A | N158: =IFERROR(VLOOKUP(A158,Materiales!$A$1:$G$5090,7,FALSE),F158) -> Inyección
A159: 2310160357 | B159: Tapa Para Resaltador 048 - N Amarillo P.S. | C159: N/A | D159: Semiterminado | E159: N/A | F159: Inyección | G159: Línea_048 | H159: Tapa | I159: Colores | J159: 1 | K159: 1 | L159: =IFERROR(_xlfn.XLOOKUP(A159,$Q$2:$Q$155,$T$2:$T$155),1) -> 1 | M159: =IFERROR(VLOOKUP(A159,$Q$2:$S$1310,3,FALSE),"N/A") -> N/A | N159: =IFERROR(VLOOKUP(A159,Materiales!$A$1:$G$5090,7,FALSE),F159) -> Inyección
A160: 2310160361 | B160: Tapita Para Resaltador 048 - N Amarillo P.S. | C160: N/A | D160: Semiterminado | E160: N/A | F160: Inyección | G160: Línea_048 | H160: Tapita | I160: Colores | J160: 1 | K160: 1 | L160: =IFERROR(_xlfn.XLOOKUP(A160,$Q$2:$Q$155,$T$2:$T$155),1) -> 1 | M160: =IFERROR(VLOOKUP(A160,$Q$2:$S$1310,3,FALSE),"N/A") -> N/A | N160: =IFERROR(VLOOKUP(A160,Materiales!$A$1:$G$5090,7,FALSE),F160) -> Inyección
A161: 2310160363 | B161: Tapita Para Resaltador 048 - N Verde P.S. | C161: N/A | D161: Semiterminado | E161: N/A | F161: Inyección | G161: Línea_048 | H161: Tapita | I161: Colores | J161: 1 | K161: 1 | L161: =IFERROR(_xlfn.XLOOKUP(A161,$Q$2:$Q$155,$T$2:$T$155),1) -> 1 | M161: =IFERROR(VLOOKUP(A161,$Q$2:$S$1310,3,FALSE),"N/A") -> N/A | N161: =IFERROR(VLOOKUP(A161,Materiales!$A$1:$G$5090,7,FALSE),F161) -> Inyección
A162: 2310160464 | B162: Tapita Para Resaltador 048 fluorescente- N Naranja P.S. | C162: N/A | D162: Semiterminado | E162: N/A | F162: Inyección | G162: Línea_048 | H162: Tapita | I162: Colores | J162: 1 | K162: 1 | L162: =IFERROR(_xlfn.XLOOKUP(A162,$Q$2:$Q$155,$T$2:$T$155),1) -> 1 | M162: =IFERROR(VLOOKUP(A162,$Q$2:$S$1310,3,FALSE),"N/A") -> N/A | N162: =IFERROR(VLOOKUP(A162,Materiales!$A$1:$G$5090,7,FALSE),F162) -> Inyección
A163: 2310160359 | B163: Tapa Para Resaltador 048 - N Verde P.S. | C163: N/A | D163: Semiterminado | E163: N/A | F163: Inyección | G163: Línea_048 | H163: Tapa | I163: Colores | J163: 1 | K163: 1 | L163: =IFERROR(_xlfn.XLOOKUP(A163,$Q$2:$Q$155,$T$2:$T$155),1) -> 1 | M163: =IFERROR(VLOOKUP(A163,$Q$2:$S$1310,3,FALSE),"N/A") -> N/A | N163: =IFERROR(VLOOKUP(A163,Materiales!$A$1:$G$5090,7,FALSE),F163) -> Inyección
A164: 2310160364 | B164: Tapita Para Resaltador 048 - N Rosado P.S. | C164: N/A | D164: Semiterminado | E164: N/A | F164: Inyección | G164: Línea_048 | H164: Tapita | I164: Colores | J164: 1 | K164: 1 | L164: =IFERROR(_xlfn.XLOOKUP(A164,$Q$2:$Q$155,$T$2:$T$155),1) -> 1 | M164: =IFERROR(VLOOKUP(A164,$Q$2:$S$1310,3,FALSE),"N/A") -> N/A | N164: =IFERROR(VLOOKUP(A164,Materiales!$A$1:$G$5090,7,FALSE),F164) -> Inyección
A165: 2310160358 | B165: Tapa Para Resaltador 048 - N Anaranjado P.S. | C165: N/A | D165: Semiterminado | E165: N/A | F165: Inyección | G165: Línea_048 | H165: Tapa | I165: Colores | J165: 1 | K165: 1 | L165: =IFERROR(_xlfn.XLOOKUP(A165,$Q$2:$Q$155,$T$2:$T$155),1) -> 1 | M165: =IFERROR(VLOOKUP(A165,$Q$2:$S$1310,3,FALSE),"N/A") -> N/A | N165: =IFERROR(VLOOKUP(A165,Materiales!$A$1:$G$5090,7,FALSE),F165) -> Inyección
A166: 2310160360 | B166: Tapa Para Resaltador 048 - N Rosado P.S. | C166: N/A | D166: Semiterminado | E166: N/A | F166: Inyección | G166: Línea_048 | H166: Tapa | I166: Colores | J166: 1 | K166: 1 | L166: =IFERROR(_xlfn.XLOOKUP(A166,$Q$2:$Q$155,$T$2:$T$155),1) -> 1 | M166: =IFERROR(VLOOKUP(A166,$Q$2:$S$1310,3,FALSE),"N/A") -> N/A | N166: =IFERROR(VLOOKUP(A166,Materiales!$A$1:$G$5090,7,FALSE),F166) -> Inyección
A167: 2310160525 | B167: Tapita Para Resaltador Pastel 048 - N Menta P.S. | C167: N/A | D167: Semiterminado | E167: N/A | F167: Inyección | G167: Línea_048 | H167: Tapita | I167: Colores | J167: 1 | K167: 1 | L167: =IFERROR(_xlfn.XLOOKUP(A167,$Q$2:$Q$155,$T$2:$T$155),1) -> 1 | M167: =IFERROR(VLOOKUP(A167,$Q$2:$S$1310,3,FALSE),"N/A") -> N/A | N167: =IFERROR(VLOOKUP(A167,Materiales!$A$1:$G$5090,7,FALSE),F167) -> Inyección
... A1691: 2310250047 | B1691: Limpiatipo Layconsa 35Gr Rosado Pastel/Blanco Pastel Granel | C1691: N/A | D1691: Semiterminado | E1691: N/A | F1691: Semiterminado | G1691: Ensamble | H1691: Colores Duo | I1691: Troquelado | J1691: 1 | K1691: 1 | L1691: =IFERROR(_xlfn.XLOOKUP(A1691,$Q$2:$Q$155,$T$2:$T$155),1) -> 1 | M1691: =IFERROR(VLOOKUP(A1691,$Q$2:$S$1310,3,FALSE),"N/A") -> N/A | N1691: =IFERROR(VLOOKUP(A1691,Materiales!$A$1:$G$5090,7,FALSE),F1691) -> Semiterminado
A1692: 2310440005 | B1692: Cartuchera Layconsa Jumbo Box Verde P.S. | C1692: N/A | D1692: Semiterminado | E1692: N/A | F1692: Otros | G1692: Etiquetado | H1692: #N/A | I1692: #N/A | J1692: 1 | K1692: 1 | L1692: =IFERROR(_xlfn.XLOOKUP(A1692,$Q$2:$Q$155,$T$2:$T$155),1) -> 1 | M1692: =IFERROR(VLOOKUP(A1692,$Q$2:$S$1310,3,FALSE),"N/A") -> N/A | N1692: =IFERROR(VLOOKUP(A1692,Materiales!$A$1:$G$5090,7,FALSE),F1692) -> Otros
A1693: 2310170004 | B1693: Base Para Tampón 3K P.S. | C1693: N/A | D1693: Semiterminado | E1693: N/A | F1693: Inyección | G1693: Otros | J1693: 1 | K1693: 1 | L1693: =IFERROR(_xlfn.XLOOKUP(A1693,$Q$2:$Q$155,$T$2:$T$155),1) -> 1 | M1693: =IFERROR(VLOOKUP(A1693,$Q$2:$S$1310,3,FALSE),"N/A") -> N/A | N1693: =IFERROR(VLOOKUP(A1693,Materiales!$A$1:$G$5090,7,FALSE),F1693) -> Inyección
A1694: 2310170033 | B1694: Base Para Tampón T2 P.S. | C1694: N/A | D1694: Semiterminado | E1694: N/A | F1694: Inyección | G1694: Otros | J1694: 1 | K1694: 1 | L1694: =IFERROR(_xlfn.XLOOKUP(A1694,$Q$2:$Q$155,$T$2:$T$155),1) -> 1 | M1694: =IFERROR(VLOOKUP(A1694,$Q$2:$S$1310,3,FALSE),"N/A") -> N/A | N1694: =IFERROR(VLOOKUP(A1694,Materiales!$A$1:$G$5090,7,FALSE),F1694) -> Inyección
A1695: 2310170034 | B1695: Base Mas Mota Blanco T2 | C1695: N/A | D1695: Semiterminado | E1695: N/A | F1695: Inyección | G1695: Otros | J1695: 1 | K1695: 1 | L1695: =IFERROR(_xlfn.XLOOKUP(A1695,$Q$2:$Q$155,$T$2:$T$155),1) -> 1 | M1695: =IFERROR(VLOOKUP(A1695,$Q$2:$S$1310,3,FALSE),"N/A") -> N/A | N1695: =IFERROR(VLOOKUP(A1695,Materiales!$A$1:$G$5090,7,FALSE),F1695) -> Inyección
A1696: 2310230088 | B1696: Frasco para Masita | C1696: N/A | D1696: Semiterminado | E1696: N/A | F1696: Inyección | G1696: Otros | J1696: 1 | K1696: 1 | L1696: =IFERROR(_xlfn.XLOOKUP(A1696,$Q$2:$Q$155,$T$2:$T$155),1) -> 1 | M1696: =IFERROR(VLOOKUP(A1696,$Q$2:$S$1310,3,FALSE),"N/A") -> N/A | N1696: =IFERROR(VLOOKUP(A1696,Materiales!$A$1:$G$5090,7,FALSE),F1696) -> Inyección
A1697: 2310230013 | B1697: Frascos Para Témperas Puppy Imp. Puppy Gris P.S. | C1697: N/A | D1697: Semiterminado | E1697: N/A | F1697: Inyección | G1697: Otros | J1697: 1 | K1697: 1 | L1697: =IFERROR(_xlfn.XLOOKUP(A1697,$Q$2:$Q$155,$T$2:$T$155),1) -> 1 | M1697: =IFERROR(VLOOKUP(A1697,$Q$2:$S$1310,3,FALSE),"N/A") -> N/A | N1697: =IFERROR(VLOOKUP(A1697,Materiales!$A$1:$G$5090,7,FALSE),F1697) -> Inyección
A1698: 2310230090 | B1698: Frasco 2 divisiones - Masita | C1698: N/A | D1698: Semiterminado | E1698: N/A | F1698: Inyección | G1698: Otros | J1698: 1 | K1698: 1 | L1698: =IFERROR(_xlfn.XLOOKUP(A1698,$Q$2:$Q$155,$T$2:$T$155),1) -> 1 | M1698: =IFERROR(VLOOKUP(A1698,$Q$2:$S$1310,3,FALSE),"N/A") -> N/A | N1698: =IFERROR(VLOOKUP(A1698,Materiales!$A$1:$G$5090,7,FALSE),F1698) -> Inyección
A1699: 2310230091 | B1699: Frasco 4 divisiones - Masita | C1699: N/A | D1699: Semiterminado | E1699: N/A | F1699: Inyección | G1699: Otros | J1699: 1 | K1699: 1 | L1699: =IFERROR(_xlfn.XLOOKUP(A1699,$Q$2:$Q$155,$T$2:$T$155),1) -> 1 | M1699: =IFERROR(VLOOKUP(A1699,$Q$2:$S$1310,3,FALSE),"N/A") -> N/A | N1699: =IFERROR(VLOOKUP(A1699,Materiales!$A$1:$G$5090,7,FALSE),F1699) -> Inyección
A1700: 2310230092 | B1700: Frasco Mediano para Masitas | C1700: N/A | D1700: Semiterminado | E1700: N/A | F1700: Inyección | G1700: Otros | J1700: 1 | K1700: 1 | L1700: =IFERROR(_xlfn.XLOOKUP(A1700,$Q$2:$Q$155,$T$2:$T$155),1) -> 1 | M1700: =IFERROR(VLOOKUP(A1700,$Q$2:$S$1310,3,FALSE),"N/A") -> N/A | N1700: =IFERROR(VLOOKUP(A1700,Materiales!$A$1:$G$5090,7,FALSE),F1700) -> Inyección
A1701: 2310230054 | B1701: Frasco Negro para Tinta LT4 P.S. | C1701: N/A | D1701: Semiterminado | E1701: N/A | F1701: Inyección | G1701: Otros | J1701: 1 | K1701: 1 | L1701: =IFERROR(_xlfn.XLOOKUP(A1701,$Q$2:$Q$155,$T$2:$T$155),1) -> 1 | M1701: =IFERROR(VLOOKUP(A1701,$Q$2:$S$1310,3,FALSE),"N/A") -> N/A | N1701: =IFERROR(VLOOKUP(A1701,Materiales!$A$1:$G$5090,7,FALSE),F1701) -> Inyección
A1702: 2310230056 | B1702: Frasco 126 Plata Para Tinta | C1702: N/A | D1702: Semiterminado | E1702: N/A | F1702: Soplado | G1702: Soplado | J1702: 1 | K1702: 1 | L1702: =IFERROR(_xlfn.XLOOKUP(A1702,$Q$2:$Q$155,$T$2:$T$155),1) -> 1 | M1702: =IFERROR(VLOOKUP(A1702,$Q$2:$S$1310,3,FALSE),"N/A") -> N/A | N1702: =IFERROR(VLOOKUP(A1702,Materiales!$A$1:$G$5090,7,FALSE),F1702) -> Soplado
A1703: 2310230032 | B1703: Frasco Rosado Ovalado Para Cola Sintética con Aplicador 250Gr P.S. | C1703: N/A | D1703: Semiterminado | E1703: N/A | F1703: Soplado | G1703: Otros | J1703: 1 | K1703: 1 | L1703: =IFERROR(_xlfn.XLOOKUP(A1703,$Q$2:$Q$155,$T$2:$T$155),1) -> 1 | M1703: =IFERROR(VLOOKUP(A1703,$Q$2:$S$1310,3,FALSE),"N/A") -> N/A | N1703: =IFERROR(VLOOKUP(A1703,Materiales!$A$1:$G$5090,7,FALSE),F1703) -> Soplado
A1704: 2310230086 | B1704: Frasco Azul Ovalado Para Cola Sintética 250 gr. P.S. | C1704: N/A | D1704: Semiterminado | E1704: N/A | F1704: Soplado | G1704: Otros | J1704: 1 | K1704: 1 | L1704: =IFERROR(_xlfn.XLOOKUP(A1704,$Q$2:$Q$155,$T$2:$T$155),1) -> 1 | M1704: =IFERROR(VLOOKUP(A1704,$Q$2:$S$1310,3,FALSE),"N/A") -> N/A | N1704: =IFERROR(VLOOKUP(A1704,Materiales!$A$1:$G$5090,7,FALSE),F1704) -> Soplado
... A1718: 2310230102 | B1718: Frasco Etiquetado Goma Escarchado Plateado 60 g. P.S. | C1718: N/A | D1718: Semiterminado | E1718: N/A | F1718: Semiterminado | G1718: Otros | J1718: 1 | K1718: 1 | L1718: =IFERROR(_xlfn.XLOOKUP(A1718,$Q$2:$Q$155,$T$2:$T$155),1) -> 1 | M1718: =IFERROR(VLOOKUP(A1718,$Q$2:$S$1310,3,FALSE),"N/A") -> N/A | N1718: =IFERROR(VLOOKUP(A1718,Materiales!$A$1:$G$5090,7,FALSE),F1718) -> Semiterminado
A1719: 2310310058 | B1719: Borrador Gris LA-80 Granel P.S. | C1719: N/A | D1719: Semiterminado | E1719: N/A | F1719: Otros | J1719: 1 | K1719: 1 | L1719: =IFERROR(_xlfn.XLOOKUP(A1719,$Q$2:$Q$155,$T$2:$T$155),1) -> 1 | M1719: =IFERROR(VLOOKUP(A1719,$Q$2:$S$1310,3,FALSE),"N/A") -> N/A | N1719: =IFERROR(VLOOKUP(A1719,Materiales!$A$1:$G$5090,7,FALSE),F1719) -> Otros
A1720: 2310310059 | B1720: Masa Borrador Gris P.S. | C1720: N/A | D1720: Semiterminado | E1720: N/A | F1720: Otros | J1720: 1 | K1720: 1 | L1720: =IFERROR(_xlfn.XLOOKUP(A1720,$Q$2:$Q$155,$T$2:$T$155),1) -> 1 | M1720: =IFERROR(VLOOKUP(A1720,$Q$2:$S$1310,3,FALSE),"N/A") -> N/A | N1720: =IFERROR(VLOOKUP(A1720,Materiales!$A$1:$G$5090,7,FALSE),F1720) -> Otros
A1721: 2310310017 | B1721: Borrador Cilíndrico Blanco Para Lápiz P.S. | C1721: N/A | D1721: Semiterminado | E1721: N/A | F1721: Otros | J1721: 1 | K1721: 1 | L1721: =IFERROR(_xlfn.XLOOKUP(A1721,$Q$2:$Q$155,$T$2:$T$155),1) -> 1 | M1721: =IFERROR(VLOOKUP(A1721,$Q$2:$S$1310,3,FALSE),"N/A") -> N/A | N1721: =IFERROR(VLOOKUP(A1721,Materiales!$A$1:$G$5090,7,FALSE),F1721) -> Otros
A1722: 2310310028 | B1722: Borrador Cilíndrico Rosado Neón Para Lápiz P.S. | C1722: N/A | D1722: Semiterminado | E1722: N/A | F1722: Otros | J1722: 1 | K1722: 1 | L1722: =IFERROR(_xlfn.XLOOKUP(A1722,$Q$2:$Q$155,$T$2:$T$155),1) -> 1 | M1722: =IFERROR(VLOOKUP(A1722,$Q$2:$S$1310,3,FALSE),"N/A") -> N/A | N1722: =IFERROR(VLOOKUP(A1722,Materiales!$A$1:$G$5090,7,FALSE),F1722) -> Otros
A1723: 2310310024 | B1723: Borrador Cilíndrico Naranja Neón Para Lápiz P.S. | C1723: N/A | D1723: Semiterminado | E1723: N/A | F1723: Otros | J1723: 1 | K1723: 1 | L1723: =IFERROR(_xlfn.XLOOKUP(A1723,$Q$2:$Q$155,$T$2:$T$155),1) -> 1 | M1723: =IFERROR(VLOOKUP(A1723,$Q$2:$S$1310,3,FALSE),"N/A") -> N/A | N1723: =IFERROR(VLOOKUP(A1723,Materiales!$A$1:$G$5090,7,FALSE),F1723) -> Otros
A1724: 2310310020 | B1724: Borrador Cilíndrico Rosado Claro Para Lápiz P.S. | C1724: N/A | D1724: Semiterminado | E1724: N/A | F1724: Otros | J1724: 1 | K1724: 1 | L1724: =IFERROR(_xlfn.XLOOKUP(A1724,$Q$2:$Q$155,$T$2:$T$155),1) -> 1 | M1724: =IFERROR(VLOOKUP(A1724,$Q$2:$S$1310,3,FALSE),"N/A") -> N/A | N1724: =IFERROR(VLOOKUP(A1724,Materiales!$A$1:$G$5090,7,FALSE),F1724) -> Otros
A1725: 2310310052 | B1725: Borrador Cilíndrico Celeste RT-P505 Para Lápiz P.S. | C1725: N/A | D1725: Semiterminado | E1725: N/A | F1725: Otros | J1725: 1 | K1725: 1 | L1725: =IFERROR(_xlfn.XLOOKUP(A1725,$Q$2:$Q$155,$T$2:$T$155),1) -> 1 | M1725: =IFERROR(VLOOKUP(A1725,$Q$2:$S$1310,3,FALSE),"N/A") -> N/A | N1725: =IFERROR(VLOOKUP(A1725,Materiales!$A$1:$G$5090,7,FALSE),F1725) -> Otros
A1726: 2310310025 | B1726: Borrador Cilíndrico Verde Neón Para Lápiz P.S. | C1726: N/A | D1726: Semiterminado | E1726: N/A | F1726: Otros | J1726: 1 | K1726: 1 | L1726: =IFERROR(_xlfn.XLOOKUP(A1726,$Q$2:$Q$155,$T$2:$T$155),1) -> 1 | M1726: =IFERROR(VLOOKUP(A1726,$Q$2:$S$1310,3,FALSE),"N/A") -> N/A | N1726: =IFERROR(VLOOKUP(A1726,Materiales!$A$1:$G$5090,7,FALSE),F1726) -> Otros
A1727: 2310310051 | B1727: Borrador Cilindrico Verde Claro RT-P405 Para Lápiz P.S. | C1727: N/A | D1727: Semiterminado | E1727: N/A | F1727: Otros | J1727: 1 | K1727: 1 | L1727: =IFERROR(_xlfn.XLOOKUP(A1727,$Q$2:$Q$155,$T$2:$T$155),1) -> 1 | M1727: =IFERROR(VLOOKUP(A1727,$Q$2:$S$1310,3,FALSE),"N/A") -> N/A | N1727: =IFERROR(VLOOKUP(A1727,Materiales!$A$1:$G$5090,7,FALSE),F1727) -> Otros
A1728: 2310310054 | B1728: Borrador Cilíndrico Azul RT-P501 Para Lápiz P.S. | C1728: N/A | D1728: Semiterminado | E1728: N/A | F1728: Otros | J1728: 1 | K1728: 1 | L1728: =IFERROR(_xlfn.XLOOKUP(A1728,$Q$2:$Q$155,$T$2:$T$155),1) -> 1 | M1728: =IFERROR(VLOOKUP(A1728,$Q$2:$S$1310,3,FALSE),"N/A") -> N/A | N1728: =IFERROR(VLOOKUP(A1728,Materiales!$A$1:$G$5090,7,FALSE),F1728) -> Otros
A1729: 2310310053 | B1729: Borrador Cilíndrico Violeta RT-P601 Para Lápiz P.S. | C1729: N/A | D1729: Semiterminado | E1729: N/A | F1729: Otros | J1729: 1 | K1729: 1 | L1729: =IFERROR(_xlfn.XLOOKUP(A1729,$Q$2:$Q$155,$T$2:$T$155),1) -> 1 | M1729: =IFERROR(VLOOKUP(A1729,$Q$2:$S$1310,3,FALSE),"N/A") -> N/A | N1729: =IFERROR(VLOOKUP(A1729,Materiales!$A$1:$G$5090,7,FALSE),F1729) -> Otros
A1730: 2310310021 | B1730: Borrador Cilíndrico Negro Para Lápiz P.S. | C1730: N/A | D1730: Semiterminado | E1730: N/A | F1730: Otros | J1730: 1 | K1730: 1 | L1730: =IFERROR(_xlfn.XLOOKUP(A1730,$Q$2:$Q$155,$T$2:$T$155),1) -> 1 | M1730: =IFERROR(VLOOKUP(A1730,$Q$2:$S$1310,3,FALSE),"N/A") -> N/A | N1730: =IFERROR(VLOOKUP(A1730,Materiales!$A$1:$G$5090,7,FALSE),F1730) -> Otros
... A1739: 2310040142 | B1739: Concentrado de Crayón Estándar Salmon | C1739: N/A | D1739: Semiterminado | E1739: N/A | F1739: Otros | J1739: 1 | K1739: 1 | L1739: =IFERROR(_xlfn.XLOOKUP(A1739,$Q$2:$Q$155,$T$2:$T$155),1) -> 1 | M1739: =IFERROR(VLOOKUP(A1739,$Q$2:$S$1310,3,FALSE),"N/A") -> N/A | N1739: =IFERROR(VLOOKUP(A1739,Materiales!$A$1:$G$5090,7,FALSE),F1739) -> Otros
A1740: 2310480014 | B1740: Cuad.Grap. Cuad. 80 Hj Arcoiris con Sticker c/ margen granel P.S. | C1740: N/A | D1740: Semiterminado | E1740: N/A | J1740: 1 | K1740: 1 | L1740: =IFERROR(_xlfn.XLOOKUP(A1740,$Q$2:$Q$155,$T$2:$T$155),1) -> 1 | M1740: =IFERROR(VLOOKUP(A1740,$Q$2:$S$1310,3,FALSE),"N/A") -> N/A | N1740: =IFERROR(VLOOKUP(A1740,Materiales!$A$1:$G$5090,7,FALSE),F1740) -> 0
A1741: 2310480011 | B1741: Cuad.Grap. 2X2. 92H Layconsa c/ diseño Inicial Hombre + Mujer granel P.S. | C1741: N/A | D1741: Semiterminado | E1741: N/A | J1741: 1 | K1741: 1 | L1741: =IFERROR(_xlfn.XLOOKUP(A1741,$Q$2:$Q$155,$T$2:$T$155),1) -> 1 | M1741: =IFERROR(VLOOKUP(A1741,$Q$2:$S$1310,3,FALSE),"N/A") -> N/A | N1741: =IFERROR(VLOOKUP(A1741,Materiales!$A$1:$G$5090,7,FALSE),F1741) -> 0
A1742: 2310480012 | B1742: Cuad. Grap. Ray. 92H Layconsa c/ diseño Primaria + Secundaria Mujer granel P.S. | C1742: N/A | D1742: Semiterminado | E1742: N/A | J1742: 1 | K1742: 1 | L1742: =IFERROR(_xlfn.XLOOKUP(A1742,$Q$2:$Q$155,$T$2:$T$155),1) -> 1 | M1742: =IFERROR(VLOOKUP(A1742,$Q$2:$S$1310,3,FALSE),"N/A") -> N/A | N1742: =IFERROR(VLOOKUP(A1742,Materiales!$A$1:$G$5090,7,FALSE),F1742) -> 0
A1743: 2310480015 | B1743: Cuad.Grap. Triple Reglón S 80 Hj Arcoiris con Sticker granel P.S. | C1743: N/A | D1743: Semiterminado | E1743: N/A | J1743: 1 | K1743: 1 | L1743: =IFERROR(_xlfn.XLOOKUP(A1743,$Q$2:$Q$155,$T$2:$T$155),1) -> 1 | M1743: =IFERROR(VLOOKUP(A1743,$Q$2:$S$1310,3,FALSE),"N/A") -> N/A | N1743: =IFERROR(VLOOKUP(A1743,Materiales!$A$1:$G$5090,7,FALSE),F1743) -> 0
A1744: 2310480034 | B1744: Tapa cuaderno anillado A4 COLORES PASTELES - Impreso - Plastificado - Armado | C1744: N/A | D1744: Semiterminado | E1744: N/A | J1744: 1 | K1744: 1 | L1744: =IFERROR(_xlfn.XLOOKUP(A1744,$Q$2:$Q$155,$T$2:$T$155),1) -> 1 | M1744: =IFERROR(VLOOKUP(A1744,$Q$2:$S$1310,3,FALSE),"N/A") -> N/A | N1744: =IFERROR(VLOOKUP(A1744,Materiales!$A$1:$G$5090,7,FALSE),F1744) -> 0
A1745: 2310480032 | B1745: Tapa cuaderno anillado A4 HOMBRE - Impreso - Plastificado - Acabado - Armado | C1745: N/A | D1745: Semiterminado | E1745: N/A | J1745: 1 | K1745: 1 | L1745: =IFERROR(_xlfn.XLOOKUP(A1745,$Q$2:$Q$155,$T$2:$T$155),1) -> 1 | M1745: =IFERROR(VLOOKUP(A1745,$Q$2:$S$1310,3,FALSE),"N/A") -> N/A | N1745: =IFERROR(VLOOKUP(A1745,Materiales!$A$1:$G$5090,7,FALSE),F1745) -> 0
A1746: 2310480035 | B1746: Tapa cuaderno anillado A4 COLORES SOLIDOS - Impreso - Plastificado - Armado | C1746: N/A | D1746: Semiterminado | E1746: N/A | J1746: 1 | K1746: 1 | L1746: =IFERROR(_xlfn.XLOOKUP(A1746,$Q$2:$Q$155,$T$2:$T$155),1) -> 1 | M1746: =IFERROR(VLOOKUP(A1746,$Q$2:$S$1310,3,FALSE),"N/A") -> N/A | N1746: =IFERROR(VLOOKUP(A1746,Materiales!$A$1:$G$5090,7,FALSE),F1746) -> 0
A1747: 2310480057 | B1747: CONA -Cuaderno Anillado A4 RAYADO | C1747: N/A | D1747: Semiterminado | E1747: N/A | J1747: 1 | K1747: 1 | L1747: =IFERROR(_xlfn.XLOOKUP(A1747,$Q$2:$Q$155,$T$2:$T$155),1) -> 1 | M1747: =IFERROR(VLOOKUP(A1747,$Q$2:$S$1310,3,FALSE),"N/A") -> N/A | N1747: =IFERROR(VLOOKUP(A1747,Materiales!$A$1:$G$5090,7,FALSE),F1747) -> 0
...

Sheet Tiempos
A1: Código Semi | B1: 0 | C1: Cantidad Base | D1: T.MO | E1: T.Maq | F1: Cant.Opr | G1: Maquina | H1: Tarifa Maquina | I1: Tarifa MO | J1: Proceso | K1: T.ciclo | L1: Cav. Oper | M1: Cav. Tot | N1: Componente
A2: 2110020095 | B2: Plumones Layconsa School 45 Estuche x 12 | C2: 8000 | D2: 72 | E2: 12 | F2: 6 | G2: ENCJ02 | H2: 259.0706 | I2: 9.02076 | J2: Encajado | K2: 0 | L2: 0 | M2: 0
A3: 2310210127 | B3: Plumones LYC School 45 Granel Azul NP P.S. | C3: 50000 | D3: 12 | E3: 12 | F3: 1 | G3: ENS02 | H3: 128.5658 | I3: 11.9658 | J3: Ensamble | K3: 0 | L3: 0 | M3: 0
A4: 2310210128 | B4: Plumones LYC School 45 Granel Negro NP P.S. | C4: 50000 | D4: 12 | E4: 12 | F4: 1 | G4: ENS02 | H4: 128.5658 | I4: 11.9658 | J4: Ensamble | K4: 0 | L4: 0 | M4: 0
A5: 2310210129 | B5: Plumones LYC School 45 Granel Rojo NP P.S. | C5: 50000 | D5: 12 | E5: 12 | F5: 1 | G5: ENS02 | H5: 128.5658 | I5: 11.9658 | J5: Ensamble | K5: 0 | L5: 0 | M5: 0
A6: 2310210130 | B6: Plumones LYC School 45 Granel Verde NP P.S. | C6: 50000 | D6: 12 | E6: 12 | F6: 1 | G6: ENS02 | H6: 128.5658 | I6: 11.9658 | J6: Ensamble | K6: 0 | L6: 0 | M6: 0
A7: 2310210131 | B7: Plumones LYC School 45 Granel Amarillo NP P.S. | C7: 50000 | D7: 12 | E7: 12 | F7: 1 | G7: ENS02 | H7: 128.5658 | I7: 11.9658 | J7: Ensamble | K7: 0 | L7: 0 | M7: 0
A8: 2310210132 | B8: Plumones LYC School 45 Granel Marrón NP P.S. | C8: 50000 | D8: 12 | E8: 12 | F8: 1 | G8: ENS02 | H8: 128.5658 | I8: 11.9658 | J8: Ensamble | K8: 0 | L8: 0 | M8: 0
A9: 2310210133 | B9: Plumones LYC School 45 Granel Anaranjado NP P.S. | C9: 50000 | D9: 12 | E9: 12 | F9: 1 | G9: ENS02 | H9: 128.5658 | I9: 11.9658 | J9: Ensamble | K9: 0 | L9: 0 | M9: 0
A10: 2310210134 | B10: Plumones LYC School 45 Granel Rosado NP P.S. | C10: 50000 | D10: 12 | E10: 12 | F10: 1 | G10: ENS02 | H10: 128.5658 | I10: 11.9658 | J10: Ensamble | K10: 0 | L10: 0 | M10: 0
A11: 2310210135 | B11: Plumones LYC School 45 Granel Violeta NP P.S. | C11: 50000 | D11: 12 | E11: 12 | F11: 1 | G11: ENS02 | H11: 128.5658 | I11: 11.9658 | J11: Ensamble | K11: 0 | L11: 0 | M11: 0
A12: 2310210136 | B12: Plumones LYC School 45 Granel Celeste NP P.S. | C12: 50000 | D12: 12 | E12: 12 | F12: 1 | G12: ENS02 | H12: 128.5658 | I12: 11.9658 | J12: Ensamble | K12: 0 | L12: 0 | M12: 0
A13: 2310210137 | B13: Plumones LYC School 45 Granel Verde Limon NP P.S. | C13: 50000 | D13: 12 | E13: 12 | F13: 1 | G13: ENS02 | H13: 128.5658 | I13: 11.9658 | J13: Ensamble | K13: 0 | L13: 0 | M13: 0
A14: 2310210138 | B14: Plumones LYC School 45 Granel Piel NP P.S. | C14: 50000 | D14: 12 | E14: 12 | F14: 1 | G14: ENS02 | H14: 128.5658 | I14: 11.9658 | J14: Ensamble | K14: 0 | L14: 0 | M14: 0
A15: 2310090439 | B15: Barril Para Plumón 045 - NP Azul | C15: 98742.857 | D15: 24 | E15: 24 | F15: 2 | G15: INY05 | H15: 37.8816 | I15: 9.82405 | J15: Inyección | K15: 24.5 | L15: 28 | M15: 32 | N15: Barril
A16: 2310160468 | B16: Tapa Para Plumón 045 - NP Azul | C16: 96000 | D16: 24 | E16: 24 | F16: 1 | G16: INY09 | H16: 7.1629 | I16: 9.64384 | J16: Inyección | K16: 21.6 | L16: 24 | M16: 24 | N16: Tapa
A17: 2310160480 | B17: Tapita Para Plumón 045 - NP Azul | C17: 86979.866 | D17: 24 | E17: 24 | F17: 1 | G17: INY13 | H17: 9.6456 | I17: 9.64384 | J17: Inyección | K17: 29.8 | L17: 30 | M17: 32 | N17: Tapita
A18: 2310180036 | B18: Tinta Plumón Lavable Azul P.S. | C18: 200 | D18: 4 | E18: 4 | F18: 1 | G18: AGIT01 | H18: 32.5465 | I18: 10.63879 | J18: MYT | K18: 0 | L18: 0 | M18: 0
A19: 2310090441 | B19: Barril Para Plumón 045 - NP Negro | C19: 98742.857 | D19: 24 | E19: 24 | F19: 2 | G19: INY05 | H19: 37.8816 | I19: 9.82405 | J19: Inyección | K19: 24.5 | L19: 28 | M19: 32 | N19: Barril
A20: 2310160470 | B20: Tapa Para Plumón 045 - NP Negro | C20: 96000 | D20: 24 | E20: 24 | F20: 1 | G20: INY09 | H20: 7.1629 | I20: 9.64384 | J20: Inyección | K20: 21.6 | L20: 24 | M20: 24 | N20: Tapa
A21: 2310160482 | B21: Tapita Para Plumón 045 - NP Negro | C21: 86979.866 | D21: 24 | E21: 24 | F21: 1 | G21: INY13 | H21: 9.6456 | I21: 9.64384 | J21: Inyección | K21: 29.8 | L21: 30 | M21: 32 | N21: Tapita
A22: 2310180042 | B22: Tinta Plumón Lavable Negro P.S. | C22: 200 | D22: 4 | E22: 4 | F22: 1 | G22: AGIT01 | H22: 32.5465 | I22: 10.63879 | J22: MYT | K22: 0 | L22: 0 | M22: 0
A23: 2310090440 | B23: Barril Para Plumón 045 - NPRojo | C23: 98742.857 | D23: 24 | E23: 24 | F23: 2 | G23: INY05 | H23: 37.8816 | I23: 9.82405 | J23: Inyección | K23: 24.5 | L23: 28 | M23: 32 | N23: Barril
A24: 2310160469 | B24: Tapa Para Plumón 045 - NP Rojo | C24: 96000 | D24: 24 | E24: 24 | F24: 1 | G24: INY09 | H24: 7.1629 | I24: 9.64384 | J24: Inyección | K24: 21.6 | L24: 24 | M24: 24 | N24: Tapa
A25: 2310160481 | B25: Tapita Para Plumón 045 - NP Rojo | C25: 86979.866 | D25: 24 | E25: 24 | F25: 1 | G25: INY13 | H25: 9.6456 | I25: 9.64384 | J25: Inyección | K25: 29.8 | L25: 30 | M25: 32 | N25: Tapita
A26: 2310180041 | B26: Tinta Plumón Lavable Rojo P.S. | C26: 200 | D26: 4 | E26: 4 | F26: 1 | G26: AGIT01 | H26: 32.5465 | I26: 10.63879 | J26: MYT | K26: 0 | L26: 0 | M26: 0
A27: 2310090442 | B27: Barril Para Plumón 045 - NP Verde | C27: 98742.857 | D27: 24 | E27: 24 | F27: 2 | G27: INY05 | H27: 37.8816 | I27: 9.82405 | J27: Inyección | K27: 24.5 | L27: 28 | M27: 32 | N27: Barril
A28: 2310160471 | B28: Tapa Para Plumón 045 - NP Verde | C28: 96000 | D28: 24 | E28: 24 | F28: 1 | G28: INY09 | H28: 7.1629 | I28: 9.64384 | J28: Inyección | K28: 21.6 | L28: 24 | M28: 24 | N28: Tapa
A29: 2310160483 | B29: Tapita Para Plumón 045 - NP Verde | C29: 86979.866 | D29: 24 | E29: 24 | F29: 1 | G29: INY13 | H29: 9.6456 | I29: 9.64384 | J29: Inyección | K29: 29.8 | L29: 30 | M29: 32 | N29: Tapita
A30: 2310180044 | B30: Tinta Plumón Lavable Verde P.S. | C30: 200 | D30: 4 | E30: 4 | F30: 1 | G30: AGIT01 | H30: 32.5465 | I30: 10.63879 | J30: MYT | K30: 0 | L30: 0 | M30: 0
A31: 2310090443 | B31: Barril Para Plumón 045 - NP Amarillo | C31: 98742.857 | D31: 24 | E31: 24 | F31: 2 | G31: INY05 | H31: 37.8816 | I31: 9.82405 | J31: Inyección | K31: 24.5 | L31: 28 | M31: 32 | N31: Barril
A32: 2310160472 | B32: Tapa Para Plumón 045 - NP Amarillo | C32: 96000 | D32: 24 | E32: 24 | F32: 1 | G32: INY09 | H32: 7.1629 | I32: 9.64384 | J32: Inyección | K32: 21.6 | L32: 24 | M32: 24 | N32: Tapa
A33: 2310160484 | B33: Tapita Para Plumón 045 - NP Amarillo | C33: 86979.866 | D33: 24 | E33: 24 | F33: 1 | G33: INY13 | H33: 9.6456 | I33: 9.64384 | J33: Inyección | K33: 29.8 | L33: 30 | M33: 32 | N33: Tapita
A34: 2310180035 | B34: Tinta Plumón Lavable Amarillo P.S. | C34: 200 | D34: 4 | E34: 4 | F34: 1 | G34: AGIT01 | H34: 32.5465 | I34: 10.63879 | J34: MYT | K34: 0 | L34: 0 | M34: 0
A35: 2310090444 | B35: Barril Para Plumón 045 - NP Marrón Oscuro | C35: 98742.857 | D35: 24 | E35: 24 | F35: 2 | G35: INY05 | H35: 37.8816 | I35: 9.82405 | J35: Inyección | K35: 24.5 | L35: 28 | M35: 32 | N35: Barril
A36: 2310160473 | B36: Tapa Para Plumón 045 - NP Marrón Oscuro | C36: 96000 | D36: 24 | E36: 24 | F36: 1 | G36: INY09 | H36: 7.1629 | I36: 9.64384 | J36: Inyección | K36: 21.6 | L36: 24 | M36: 24 | N36: Tapa
A37: 2310160485 | B37: Tapita Para Plumón 045 - NP Marrón Oscuro | C37: 86979.866 | D37: 24 | E37: 24 | F37: 1 | G37: INY13 | H37: 9.6456 | I37: 9.64384 | J37: Inyección | K37: 29.8 | L37: 30 | M37: 32 | N37: Tapita
A38: 2310180039 | B38: Tinta Plumón Lavable Marrón P.S. | C38: 200 | D38: 4 | E38: 4 | F38: 1 | G38: AGIT01 | H38: 32.5465 | I38: 10.63879 | J38: MYT | K38: 0 | L38: 0 | M38: 0
A39: 2310090447 | B39: Barril Para Plumón 045 - NP Anaranjado | C39: 98742.857 | D39: 24 | E39: 24 | F39: 2 | G39: INY05 | H39: 37.8816 | I39: 9.82405 | J39: Inyección | K39: 24.5 | L39: 28 | M39: 32 | N39: Barril
A40: 2310160476 | B40: Tapa Para Plumón 045 - NP Anaranjado | C40: 96000 | D40: 24 | E40: 24 | F40: 1 | G40: INY09 | H40: 7.1629 | I40: 9.64384 | J40: Inyección | K40: 21.6 | L40: 24 | M40: 24 | N40: Tapa
A41: 2310160488 | B41: Tapita Para Plumón 045 - NP Anaranjado | C41: 86979.866 | D41: 24 | E41: 24 | F41: 1 | G41: INY13 | H41: 9.6456 | I41: 9.64384 | J41: Inyección | K41: 29.8 | L41: 30 | M41: 32 | N41: Tapita
A42: 2310180047 | B42: Tinta Plumón Lavable Anaranjado P.S. | C42: 200 | D42: 4 | E42: 4 | F42: 1 | G42: AGIT01 | H42: 32.5465 | I42: 10.63879 | J42: MYT | K42: 0 | L42: 0 | M42: 0
A43: 2310090446 | B43: Barril Para Plumón 045 - NP Rosado | C43: 98742.857 | D43: 24 | E43: 24 | F43: 2 | G43: INY05 | H43: 37.8816 | I43: 9.82405 | J43: Inyección | K43: 24.5 | L43: 28 | M43: 32 | N43: Barril
A44: 2310160475 | B44: Tapa Para Plumón 045 - NP Rosado | C44: 96000 | D44: 24 | E44: 24 | F44: 1 | G44: INY09 | H44: 7.1629 | I44: 9.64384 | J44: Inyección | K44: 21.6 | L44: 24 | M44: 24 | N44: Tapa
A45: 2310160487 | B45: Tapita Para Plumón 045 - NP Rosado | C45: 86979.866 | D45: 24 | E45: 24 | F45: 1 | G45: INY13 | H45: 9.6456 | I45: 9.64384 | J45: Inyección | K45: 29.8 | L45: 30 | M45: 32 | N45: Tapita
A46: 2310180050 | B46: Tinta Plumón Lavable Fucsia P.S. | C46: 200 | D46: 4 | E46: 4 | F46: 1 | G46: AGIT01 | H46: 32.5465 | I46: 10.63879 | J46: MYT | K46: 0 | L46: 0 | M46: 0
A47: 2310090507 | B47: Barril Para Plumón 045 - NP Violeta | C47: 98742.857 | D47: 24 | E47: 24 | F47: 2 | G47: INY05 | H47: 37.8816 | I47: 9.82405 | J47: Inyección | K47: 24.5 | L47: 28 | M47: 32 | N47: Barril
A48: 2310160500 | B48: Tapa Para Plumón 045 - NP Violeta | C48: 96000 | D48: 24 | E48: 24 | F48: 1 | G48: INY09 | H48: 7.1629 | I48: 9.64384 | J48: Inyección | K48: 21.6 | L48: 24 | M48: 24 | N48: Tapa
A49: 2310160501 | B49: Tapita Para Plumón 045 - NP Violeta | C49: 86979.866 | D49: 24 | E49: 24 | F49: 1 | G49: INY13 | H49: 9.6456 | I49: 9.64384 | J49: Inyección | K49: 29.8 | L49: 30 | M49: 32 | N49: Tapita
A50: 2310180037 | B50: Tinta Plumón Lavable Violeta P.S. | C50: 200 | D50: 4 | E50: 4 | F50: 1 | G50: AGIT01 | H50: 32.5465 | I50: 10.63879 | J50: MYT | K50: 0 | L50: 0 | M50: 0
A51: 2310090448 | B51: Barril Para Plumón 045 - NP Celeste | C51: 98742.857 | D51: 24 | E51: 24 | F51: 2 | G51: INY05 | H51: 37.8816 | I51: 9.82405 | J51: Inyección | K51: 24.5 | L51: 28 | M51: 32 | N51: Barril
A52: 2310160477 | B52: Tapa Para Plumón 045 - NP Celeste | C52: 96000 | D52: 24 | E52: 24 | F52: 1 | G52: INY09 | H52: 7.1629 | I52: 9.64384 | J52: Inyección | K52: 21.6 | L52: 24 | M52: 24 | N52: Tapa
A53: 2310160489 | B53: Tapita Para Plumón 045 - NP Celeste | C53: 86979.866 | D53: 24 | E53: 24 | F53: 1 | G53: INY13 | H53: 9.6456 | I53: 9.64384 | J53: Inyección | K53: 29.8 | L53: 30 | M53: 32 | N53: Tapita
A54: 2310180051 | B54: Tinta Plumón Lavable Celeste P.S. | C54: 200 | D54: 4 | E54: 4 | F54: 1 | G54: AGIT01 | H54: 32.5465 | I54: 10.63879 | J54: MYT | K54: 0 | L54: 0 | M54: 0
A55: 2310090445 | B55: Barril Para Plumón 045 - NP Verde Claro | C55: 98742.857 | D55: 24 | E55: 24 | F55: 2 | G55: INY05 | H55: 37.8816 | I55: 9.82405 | J55: Inyección | K55: 24.5 | L55: 28 | M55: 32 | N55: Barril
A56: 2310160474 | B56: Tapa Para Plumón 045 - NP Verde Claro | C56: 96000 | D56: 24 | E56: 24 | F56: 1 | G56: INY09 | H56: 7.1629 | I56: 9.64384 | J56: Inyección | K56: 21.6 | L56: 24 | M56: 24 | N56: Tapa
A57: 2310160486 | B57: Tapita Para Plumón 045 - NP Verde Claro | C57: 86979.866 | D57: 24 | E57: 24 | F57: 1 | G57: INY13 | H57: 9.6456 | I57: 9.64384 | J57: Inyección | K57: 29.8 | L57: 30 | M57: 32 | N57: Tapita
A58: 2310180045 | B58: Tinta Plumón Lavable Verde Claro P.S. | C58: 200 | D58: 4 | E58: 4 | F58: 1 | G58: AGIT01 | H58: 32.5465 | I58: 10.63879 | J58: MYT | K58: 0 | L58: 0 | M58: 0
A59: 2310090450 | B59: Barril Para Plumón 045 - NP Piel | C59: 98742.857 | D59: 24 | E59: 24 | F59: 2 | G59: INY05 | H59: 37.8816 | I59: 9.82405 | J59: Inyección | K59: 24.5 | L59: 28 | M59: 32 | N59: Barril
A60: 2310160479 | B60: Tapa Para Plumón 045 - NP Piel | C60: 96000 | D60: 24 | E60: 24 | F60: 1 | G60: INY09 | H60: 7.1629 | I60: 9.64384 | J60: Inyección | K60: 21.6 | L60: 24 | M60: 24 | N60: Tapa
A61: 2310160491 | B61: Tapita Para Plumón 045 - NP Piel | C61: 86979.866 | D61: 24 | E61: 24 | F61: 1 | G61: INY13 | H61: 9.6456 | I61: 9.64384 | J61: Inyección | K61: 29.8 | L61: 30 | M61: 32 | N61: Tapita
A62: 2310180040 | B62: Tinta Plumón Lavable Piel P.S. | C62: 200 | D62: 4 | E62: 4 | F62: 1 | G62: AGIT01 | H62: 32.5465 | I62: 10.63879 | J62: MYT | K62: 0 | L62: 0 | M62: 0
A63: 2310180048 | B63: Intermedio T.A. - Marcador | C63: 200 | D63: 4 | E63: 4 | F63: 1 | G63: AGIT01 | H63: 32.5465 | I63: 10.63879 | J63: MYT | K63: 0 | L63: 0 | M63: 0
A64: 2140040002 | B64: Limpiatipos Layconsa x 35 gr. | C64: 40000 | D64: 72 | E64: 12 | F64: 6 | G64: TERMOEN | H64: 262.6743 | I64: 8.13623 | J64: Termoen | K64: 0 | L64: 0 | M64: 0
A65: 2310250019 | B65: Limpiatipo Layconsa 35Gr Azul Granel | C65: 20000 | D65: 108 | E65: 12 | F65: 9 | G65: TROQ01 | H65: 346.2525 | I65: 8.275 | J65: Troquelado | K65: 0 | L65: 0 | M65: 0
A66: 2310160005 | B66: Tapa Para Limpiatipos x 35gr P.S. | C66: 30104.53 | D66: 24 | E66: 24 | F66: 1 | G66: INY03 | H66: 21.945 | I66: 9.98803 | J66: Inyección | K66: 11.48 | L66: 4 | M66: 6 | N66: Tapa
A67: 2310170002 | B67: Base Para Limpiatipos x 35gr P.S. | C67: 41739.13 | D67: 24 | E67: 24 | F67: 1 | G67: INY01 | H67: 24.2766 | I67: 9.98803 | J67: Inyección | K67: 10.35 | L67: 5 | M67: 6 | N67: Base
A68: 2310250012 | B68: Masa Para Limpiatipos x 35gr Azul LYC P.S. | C68: 600 | D68: 16 | E68: 12 | F68: 1 | G68: MOL_CAL01 | H68: 124.2997 | I68: 13.60902 | J68: MYT | K68: 0 | L68: 0 | M68: 0
A69: 2310250021 | B69: Limpiatipo Layconsa 35Gr Rosado Granel | C69: 20000 | D69: 108 | E69: 12 | F69: 9 | G69: TROQ01 | H69: 346.2525 | I69: 8.275 | J69: Troquelado | K69: 0 | L69: 0 | M69: 0
A70: 2310250009 | B70: Masa Para Limpiatipos x 35gr Rosado P.S. | C70: 600 | D70: 16 | E70: 12 | F70: 1 | G70: MOL_CAL01 | H70: 124.2997 | I70: 13.60902 | J70: MYT | K70: 0 | L70: 0 | M70: 0
A71: 2310250022 | B71: Limpiatipo Layconsa 35Gr Verde Neón Granel | C71: 20000 | D71: 108 | E71: 12 | F71: 9 | G71: TROQ01 | H71: 346.2525 | I71: 8.275 | J71: Troquelado | K71: 0 | L71: 0 | M71: 0
A72: 2310250007 | B72: Masa Para Limpiatipos x 35gr Verde Neón P.S. | C72: 600 | D72: 16 | E72: 12 | F72: 1 | G72: MOL_CAL01 | H72: 124.2997 | I72: 13.60902 | J72: MYT | K72: 0 | L72: 0 | M72: 0
A73: 2310250030 | B73: Limpiatipo Layconsa 35Gr Violeta Granel P.S. | C73: 20000 | D73: 108 | E73: 12 | F73: 9 | G73: TROQ01 | H73: 346.2525 | I73: 8.275 | J73: Troquelado | K73: 0 | L73: 0 | M73: 0
A74: 2310250015 | B74: Masa Para Limpiatipos x 35gr Violeta P.S. | C74: 600 | D74: 16 | E74: 12 | F74: 1 | G74: MOL_CAL01 | H74: 124.2997 | I74: 13.60902 | J74: MYT | K74: 0 | L74: 0 | M74: 0
A75: 2310250031 | B75: Limpiatipo Layconsa 35Gr Turquesa Granel P.S. | C75: 20000 | D75: 108 | E75: 12 | F75: 9 | G75: TROQ01 | H75: 346.2525 | I75: 8.275 | J75: Troquelado | K75: 0 | L75: 0 | M75: 0
A76: 2310250029 | B76: Masa Para Limpiatipos x 35gr Turquesa P.S. | C76: 600 | D76: 16 | E76: 12 | F76: 1 | G76: MOL_CAL01 | H76: 124.2997 | I76: 13.60902 | J76: MYT | K76: 0 | L76: 0 | M76: 0
A77: 2310250032 | B77: Limpiatipo Layconsa 35Gr Anaranjado Granel P.S. | C77: 20000 | D77: 108 | E77: 12 | F77: 9 | G77: TROQ01 | H77: 346.2525 | I77: 8.275 | J77: Troquelado | K77: 0 | L77: 0 | M77: 0
A78: 2310250014 | B78: Masa Para Limpiatipos x 35gr Anaranjado P.S. | C78: 600 | D78: 16 | E78: 12 | F78: 1 | G78: MOL_CAL01 | H78: 124.2997 | I78: 13.60902 | J78: MYT | K78: 0 | L78: 0 | M78: 0
A79: 2110020322 | B79: Marcador Layconsa Jumbo L-47 x 12 Colores NT Estuche | C79: 6000 | D79: 72 | E79: 12 | F79: 6 | G79: ENCJ01 | H79: 172.7865 | I79: 9.18112 | J79: Encajado | K79: 0 | L79: 0 | M79: 0
... A81: 2310090491 | B81: Barril Para Marcador LYC Serigrafiado 047 - MK Azul Imp. Blanco | C81: 25000 | D81: 12 | E81: 12 | F81: 1 | G81: IMP01 | H81: 13.2053 | I81: 9.40015 | J81: Serigrafiado | K81: 0 | L81: 0 | M81: 0
A82: 2310090457 | B82: Barril Para Marcador 042 - NP Azul P.S. | C82: 68844.622 | D82: 24 | E82: 24 | F82: 2 | G82: INY04 | H82: 20.7705 | I82: 9.98803 | J82: Inyección | K82: 25.1 | L82: 20 | M82: 20 | N82: Barril
A83: 2310160238 | B83: Tapa Para Marcador 042 - N Azul P.S. | C83: 60631.579 | D83: 24 | E83: 24 | F83: 1 | G83: INY15 | H83: 11.5246 | I83: 9.97595 | J83: Inyección | K83: 22.8 | L83: 16 | M83: 15 | N83: Tapa
A84: 2310160248 | B84: Tapita Para Marcador 042 - N Azul | C84: 74482.759 | D84: 24 | E84: 24 | F84: 1 | G84: INY11 | H84: 10.979 | I84: 9.64384 | J84: Inyección | K84: 23.2 | L84: 20 | M84: 20 | N84: Tapita
A85: 2310210150 | B85: Marcador LYC Jumbo 047 - MK Negro Granel P.S. | C85: 25000 | D85: 24 | E85: 12 | F85: 2 | G85: ENS01 | H85: 64.1264 | I85: 10.91894 | J85: Ensamble | K85: 0 | L85: 0 | M85: 0
A86: 2310090492 | B86: Barril Para Marcador LYC Serigrafiado 047 - MK Negro Imp. Blanco | C86: 25000 | D86: 12 | E86: 12 | F86: 1 | G86: IMP01 | H86: 13.2053 | I86: 9.40015 | J86: Serigrafiado | K86: 0 | L86: 0 | M86: 0
A87: 2310090458 | B87: Barril Para Marcador 042 - NP Negro P.S. | C87: 68844.622 | D87: 24 | E87: 24 | F87: 2 | G87: INY04 | H87: 20.7705 | I87: 9.98803 | J87: Inyección | K87: 25.1 | L87: 20 | M87: 20 | N87: Barril
A88: 2310160239 | B88: Tapa Para Marcador 042 - N Negro P.S. | C88: 60631.579 | D88: 24 | E88: 24 | F88: 1 | G88: INY15 | H88: 11.5246 | I88: 9.97595 | J88: Inyección | K88: 22.8 | L88: 16 | M88: 15 | N88: Tapa
A89: 2310160249 | B89: Tapita Para Marcador 042 - N Negro | C89: 74482.759 | D89: 24 | E89: 24 | F89: 1 | G89: INY11 | H89: 10.979 | I89: 9.64384 | J89: Inyección | K89: 23.2 | L89: 20 | M89: 20 | N89: Tapita
A90: 2310210151 | B90: Marcador LYC Jumbo 047 - MK Rojo Granel P.S. | C90: 25000 | D90: 24 | E90: 12 | F90: 2 | G90: ENS01 | H90: 64.1264 | I90: 10.91894 | J90: Ensamble | K90: 0 | L90: 0 | M90: 0
A91: 2310090493 | B91: Barril Para Marcador LYC Serigrafiado 047 - MK Rojo Imp. Blanco | C91: 25000 | D91: 12 | E91: 12 | F91: 1 | G91: IMP01 | H91: 13.2053 | I91: 9.40015 | J91: Serigrafiado | K91: 0 | L91: 0 | M91: 0
A92: 2310090459 | B92: Barril Para Marcador 042 - NP Rojo P.S. | C92: 68844.622 | D92: 24 | E92: 24 | F92: 2 | G92: INY04 | H92: 20.7705 | I92: 9.98803 | J92: Inyección | K92: 25.1 | L92: 20 | M92: 20 | N92: Barril
A93: 2310160240 | B93: Tapa Para Marcador 042 - N Rojo P.S. | C93: 60631.579 | D93: 24 | E93: 24 | F93: 1 | G93: INY15 | H93: 11.5246 | I93: 9.97595 | J93: Inyección | K93: 22.8 | L93: 16 | M93: 15 | N93: Tapa
A94: 2310160250 | B94: Tapita Para Marcador 042 - N Rojo | C94: 74482.759 | D94: 24 | E94: 24 | F94: 1 | G94: INY11 | H94: 10.979 | I94: 9.64384 | J94: Inyección | K94: 23.2 | L94: 20 | M94: 20 | N94: Tapita
A95: 2310210152 | B95: Marcador LYC Jumbo 047 - MK Verde Granel P.S. | C95: 25000 | D95: 24 | E95: 12 | F95: 2 | G95: ENS01 | H95: 64.1264 | I95: 10.91894 | J95: Ensamble | K95: 0 | L95: 0 | M95: 0
A96: 2310090494 | B96: Barril Para Marcador LYC Serigrafiado 047 - MK Verde Imp. Blanco | C96: 25000 | D96: 12 | E96: 12 | F96: 1 | G96: IMP01 | H96: 13.2053 | I96: 9.40015 | J96: Serigrafiado | K96: 0 | L96: 0 | M96: 0
A97: 2310090460 | B97: Barril Para Marcador 042 - NP Verde P.S. | C97: 68844.622 | D97: 24 | E97: 24 | F97: 2 | G97: INY04 | H97: 20.7705 | I97: 9.98803 | J97: Inyección | K97: 25.1 | L97: 20 | M97: 20 | N97: Barril
A98: 2310160241 | B98: Tapa Para Marcador 042 - N Verde P.S. | C98: 60631.579 | D98: 24 | E98: 24 | F98: 1 | G98: INY15 | H98: 11.5246 | I98: 9.97595 | J98: Inyección | K98: 22.8 | L98: 16 | M98: 15 | N98: Tapa
A99: 2310160251 | B99: Tapita Para Marcador 042 - N Verde | C99: 74482.759 | D99: 24 | E99: 24 | F99: 1 | G99: INY11 | H99: 10.979 | I99: 9.64384 | J99: Inyección | K99: 23.2 | L99: 20 | M99: 20 | N99: Tapita
A100: 2310210153 | B100: Marcador LYC Jumbo 047 - MK Amarillo Granel P.S. | C100: 25000 | D100: 24 | E100: 12 | F100: 2 | G100: ENS01 | H100: 64.1264 | I100: 10.91894 | J100: Ensamble | K100: 0 | L100: 0 | M100: 0
A101: 2310090495 | B101: Barril Para Marcador LYC Serigrafiado 047 - MK Amarillo Imp. Blanco | C101: 25000 | D101: 12 | E101: 12 | F101: 1 | G101: IMP01 | H101: 13.2053 | I101: 9.40015 | J101: Serigrafiado | K101: 0 | L101: 0 | M101: 0
...

Sheet OP
A1: BELNR_ID | B1: ItemCode | C1: Descripción del artículo | D1: Estado | E1: TYP | F1: WhsCode | G1: NombreAlmacen | H1: Responsable | I1: CantidadOrden | J1: Entregado | K1: Cliente | L1: FechaDocumento | M1: Columna1 | N1: Buscar
A2: 3 | B2: 2310230097 | C2: Frasco Para Témperas 30 cc NP P.S. | D2: CERRADO | E2: ÚTILES_LIMA | F2: ALMA070 | G2: Almacén Producción Inyección | H2: ANGEL | I2: 402000 | J2: 402000 | K2: Frascos Para Témperas 30 cc NP P.S. | L2: 45845 | N2: =+VLOOKUP(A2,Ordenes!$A$1:$A$669,1,FALSE) -> #N/A
A3: 4 | B3: 2310090459 | C3: Barril Para Marcador 042 - NP Rojo P.S. | D3: CERRADO | E3: ÚTILES_LIMA | F3: ALMA070 | G3: Almacén Producción Inyección | H3: ANGEL | I3: 128083 | J3: 126900 | K3: Barril Para Marcador 042 - NP Rojo P.S. | L3: 45845 | N3: =+VLOOKUP(A3,Ordenes!$A$1:$A$669,1,FALSE) -> #N/A
A4: 5 | B4: 2310090457 | C4: Barril Para Marcador 042 - NP Azul P.S. | D4: CERRADO | E4: ÚTILES_LIMA | F4: ALMA070 | G4: Almacén Producción Inyección | H4: ANGEL | I4: 179861 | J4: 179861 | K4: Barril Para Marcador 042 - NP Azul P.S. | L4: 45845 | N4: =+VLOOKUP(A4,Ordenes!$A$1:$A$669,1,FALSE) -> #N/A
A5: 6 | B5: 2310090460 | C5: Barril Para Marcador 042 - NP Verde P.S. | D5: CERRADO | E5: ÚTILES_LIMA | F5: ALMA070 | G5: Almacén Producción Inyección | H5: ANGEL | I5: 193487 | J5: 193220 | K5: Barril Para Marcador 042 - NP Verde P.S. | L5: 45845 | N5: =+VLOOKUP(A5,Ordenes!$A$1:$A$669,1,FALSE) -> #N/A
A6: 7 | B6: 2310090448 | C6: Barril Para Plumón 045 - NP Celeste | D6: CERRADO | E6: ÚTILES_LIMA | F6: ALMA070 | G6: Almacén Producción Inyección | H6: ANGEL | I6: 196272 | J6: 196272 | K6: Barril Para Plumón 045 - NP Celeste | L6: 45845 | N6: =+VLOOKUP(A6,Ordenes!$A$1:$A$669,1,FALSE) -> #N/A
A7: 8 | B7: 2310090445 | C7: Barril Para Plumón 045 - NP Verde Claro | D7: CERRADO | E7: ÚTILES_LIMA | F7: ALMA070 | G7: Almacén Producción Inyección | H7: ANGEL | I7: 196272 | J7: 194800 | K7: Barril Para Plumón 045 - NP Verde Claro | L7: 45845 | N7: =+VLOOKUP(A7,Ordenes!$A$1:$A$669,1,FALSE) -> #N/A
A8: 9 | B8: 2310090442 | C8: Barril Para Plumón 045 - NP Verde | D8: CERRADO | E8: ÚTILES_LIMA | F8: ALMA070 | G8: Almacén Producción Inyección | H8: ANGEL | I8: 196272 | J8: 196800 | K8: Barril Para Plumón 045 - NP Verde | L8: 45845 | N8: =+VLOOKUP(A8,Ordenes!$A$1:$A$669,1,FALSE) -> #N/A
A9: 10 | B9: 2310230002 | C9: Frasco Para Témperas 30 cc P.S. | D9: CERRADO | E9: ÚTILES_LIMA | F9: ALMA070 | G9: Almacén Producción Inyección | H9: ANGEL | I9: 600606 | J9: 594000 | K9: Frascos Para Témperas P.S. | L9: 45845 | N9: =+VLOOKUP(A9,Ordenes!$A$1:$A$669,1,FALSE) -> #N/A
A10: 11 | B10: 2310160476 | C10: Tapa Para Plumón 045 - NP Anaranjado | D10: CERRADO | E10: ÚTILES_LIMA | F10: ALMA070 | G10: Almacén Producción Inyección | H10: ANGEL | I10: 212548 | J10: 212550 | K10: Tapa Para Plumón 045 - NP Anaranjado | L10: 45845 | N10: =+VLOOKUP(A10,Ordenes!$A$1:$A$669,1,FALSE) -> #N/A
A11: 12 | B11: 2310160469 | C11: Tapa Para Plumón 045 - NP Rojo | D11: CERRADO | E11: ÚTILES_LIMA | F11: ALMA070 | G11: Almacén Producción Inyección | H11: ANGEL | I11: 173736 | J11: 173736 | K11: Tapa Para Plumón 045 - NP Rojo | L11: 45845 | N11: =+VLOOKUP(A11,Ordenes!$A$1:$A$669,1,FALSE) -> #N/A
A12: 13 | B12: 2310160471 | C12: Tapa Para Plumón 045 - NP Verde | D12: CERRADO | E12: ÚTILES_LIMA | F12: ALMA070 | G12: Almacén Producción Inyección | H12: ANGEL | I12: 222000 | J12: 224000 | K12: Tapa Para Plumón 045 - NP Verde | L12: 45845 | N12: =+VLOOKUP(A12,Ordenes!$A$1:$A$669,1,FALSE) -> #N/A
A13: 14 | B13: 2310160539 | C13: Tapa Base Dosificador P/Cola Rojo paleta P.S. | D13: CERRADO | E13: ÚTILES_LIMA | F13: ALMA070 | G13: Almacén Producción Inyección | H13: ANGEL | I13: 225684 | J13: 0 | K13: Tapa Base Dosificador Rojo paleta P.S. | L13: 45845 | N13: =+VLOOKUP(A13,Ordenes!$A$1:$A$669,1,FALSE) -> #N/A
... A321: 462 | B321: 2140110657 | C321: Cuad. Grap. Ray. Sweet Layconsa 80 H | D321: CERRADO | E321: CUADERNOS_LIMA | F321: ALMA073 | G321: Almacén Producción Cuadernos | H321: BERNARDO | I321: 1500 | J321: 0 | K321: disponible | L321: 45870 | N321: =+VLOOKUP(A321,Ordenes!$A$1:$A$669,1,FALSE) -> #N/A
A322: 466 | D322: CERRADO | E322: CUADERNOS_LIMA | H322: SIN RESPONSABLE | I322: 0 | J322: 0 | K322: Cuad. Grap. Ray. Kawaii Layconsa 80 H. | L322: 45870 | N322: =+VLOOKUP(A322,Ordenes!$A$1:$A$669,1,FALSE) -> #N/A
A323: 467 | B323: 2140110658 | C323: Cuad. Grap. Ray. Mandalas Layconsa 80 H | D323: CERRADO | E323: CUADERNOS_LIMA | F323: ALMA073 | G323: Almacén Producción Cuadernos | H323: BERNARDO | I323: 4500 | J323: 4525 | K323: Cuad. Grap. Ray. Mandalas Layconsa 80 H | L323: 45870 | N323: =+VLOOKUP(A323,Ordenes!$A$1:$A$669,1,FALSE) -> #N/A
A324: 468 | B324: 2140110661 | C324: Cuad. Grap. Ray. Fast Racer Layconsa 80 H | D324: CERRADO | E324: CUADERNOS_LIMA | F324: ALMA073 | G324: Almacén Producción Cuadernos | H324: BERNARDO | I324: 10000 | J324: 10026 | K324: Cuad. Grap. Ray. Fast Racer Layconsa 80 H | L324: 45870 | N324: =+VLOOKUP(A324,Ordenes!$A$1:$A$669,1,FALSE) -> #N/A
A325: 470 | B325: 2140110613 | C325: Cuad. Grap. Cuadr. Princess Club Layconsa 80 H | D325: CERRADO | E325: CUADERNOS_LIMA | F325: ALMA073 | G325: Almacén Producción Cuadernos | H325: BERNARDO | I325: 59000 | J325: 59175 | K325: Cuad. Grap. Cuadr. Princess Club Layconsa 80 H | L325: 45870 | N325: =+VLOOKUP(A325,Ordenes!$A$1:$A$669,1,FALSE) -> #N/A
A326: 471 | B326: 2140110615 | C326: Cuad. Grap. Cuadr. Unicornios Layconsa 80 H | D326: CERRADO | E326: CUADERNOS_LIMA | F326: ALMA073 | G326: Almacén Producción Cuadernos | H326: BERNARDO | I326: 24500 | J326: 24525 | K326: Cuad. Grap. Cuadr. Unicornios Layconsa 80 H | L326: 45870 | N326: =+VLOOKUP(A326,Ordenes!$A$1:$A$669,1,FALSE) -> #N/A
A327: 472 | B327: 2310040547 | C327: Formado Crayón Jumbo LYC Rojo | D327: CERRADO | E327: ÚTILES_LIMA | F327: ALMA072 | G327: Almacén Producción Masas y Tintas | H327: MATIAS | I327: 25000 | J327: 18254 | K327: Formado Crayón Jumbo LYC Rojo | L327: 45873 | N327: =+VLOOKUP(A327,Ordenes!$A$1:$A$669,1,FALSE) -> #N/A
A328: 473 | B328: 2310040548 | C328: Formado Crayón Jumbo LYC Amarillo | D328: CERRADO | E328: ÚTILES_LIMA | F328: ALMA072 | G328: Almacén Producción Masas y Tintas | H328: MATIAS | I328: 25000 | J328: 29970 | K328: Formado Crayón Jumbo LYC Amarillo | L328: 45873 | N328: =+VLOOKUP(A328,Ordenes!$A$1:$A$669,1,FALSE) -> #N/A
A329: 474 | B329: 2310040549 | C329: Formado Crayón Jumbo LYC Blanco | D329: CERRADO | E329: ÚTILES_LIMA | F329: ALMA072 | G329: Almacén Producción Masas y Tintas | H329: MATIAS | I329: 25000 | J329: 26253 | K329: Formado Crayón Jumbo LYC Blanco | L329: 45873 | N329: =+VLOOKUP(A329,Ordenes!$A$1:$A$669,1,FALSE) -> #N/A
A330: 475 | B330: 2310040550 | C330: Formado Crayón Jumbo LYC Anaranjado | D330: CERRADO | E330: ÚTILES_LIMA | F330: ALMA072 | G330: Almacén Producción Masas y Tintas | H330: MATIAS | I330: 25000 | J330: 27114 | K330: Formado Crayón Jumbo LYC Anaranjado | L330: 45873 | N330: =+VLOOKUP(A330,Ordenes!$A$1:$A$669,1,FALSE) -> #N/A
A331: 476 | B331: 2310040551 | C331: Formado Crayón Jumbo LYC Verde Claro | D331: CERRADO | E331: ÚTILES_LIMA | F331: ALMA072 | G331: Almacén Producción Masas y Tintas | H331: MATIAS | I331: 25000 | J331: 27573 | K331: Formado Crayón Jumbo LYC Verde Claro | L331: 45873 | N331: =+VLOOKUP(A331,Ordenes!$A$1:$A$669,1,FALSE) -> #N/A
A332: 477 | B332: 2310040552 | C332: Formado Crayón Jumbo LYC Verde Oscuro | D332: CERRADO | E332: ÚTILES_LIMA | F332: ALMA072 | G332: Almacén Producción Masas y Tintas | H332: MATIAS | I332: 25000 | J332: 27133 | K332: Formado Crayón Jumbo LYC Verde Oscuro | L332: 45873 | N332: =+VLOOKUP(A332,Ordenes!$A$1:$A$669,1,FALSE) -> #N/A
A333: 478 | B333: 2310040553 | C333: Formado Crayón Jumbo LYC Celeste | D333: CERRADO | E333: ÚTILES_LIMA | F333: ALMA072 | G333: Almacén Producción Masas y Tintas | H333: MATIAS | I333: 25000 | J333: 26931 | K333: Formado Crayón Jumbo LYC Celeste | L333: 45873 | N333: =+VLOOKUP(A333,Ordenes!$A$1:$A$669,1,FALSE) -> #N/A
A334: 479 | B334: 2310040554 | C334: Formado Crayón Jumbo LYC Azul | D334: CERRADO | E334: ÚTILES_LIMA | F334: ALMA072 | G334: Almacén Producción Masas y Tintas | H334: MATIAS | I334: 25000 | J334: 27052 | K334: Formado Crayón Jumbo LYC Azul | L334: 45873 | N334: =+VLOOKUP(A334,Ordenes!$A$1:$A$669,1,FALSE) -> #N/A
... A1325: 1831 | B1325: 2310090491 | C1325: Barril Para Marcador LYC Serigrafiado 047 - MK Azul Imp. Blanco | D1325: CERRADO | E1325: ÚTILES_LIMA | F1325: ALMA071 | G1325: Almacén Producción Ensamble | H1325: ISAIAS | I1325: 20000 | J1325: 21420 | K1325: Barril Para Marcador LYC Serigrafiado 047 - MK Azul Imp. Blanco | L1325: 45957 | N1325: =+VLOOKUP(A1325,Ordenes!$A$1:$A$669,1,FALSE) -> #N/A
A1326: 1832 | D1326: CERRADO | E1326: CUADERNOS_LIMA | H1326: SIN RESPONSABLE | I1326: 0 | J1326: 0 | K1326: Cuad. Grap. 1x1 c/mco rojo 80 H. Layconsa Puppy | L1326: 45957 | N1326: =+VLOOKUP(A1326,Ordenes!$A$1:$A$669,1,FALSE) -> #N/A
A1327: 1833 | B1327: 2110210003 | C1327: Folder Layconsa A4 Cut Pets c/Fastener colores surtidos | D1327: CERRADO | E1327: ÚTILES_LIMA | F1327: ALMA071 | G1327: Almacén Producción Ensamble | H1327: ISAIAS | I1327: 4000 | J1327: 3988 | K1327: Folder Layconsa A4 Cut Pets c/Fastener colores surtidos | L1327: 45957 | N1327: =+VLOOKUP(A1327,Ordenes!$A$1:$A$669,1,FALSE) -> #N/A
A1328: 1834 | B1328: 2110210004 | C1328: Folder Layconsa A4 Kawaii c/Fastener colores surtidos | D1328: CERRADO | E1328: ÚTILES_LIMA | F1328: ALMA071 | G1328: Almacén Producción Ensamble | H1328: ISAIAS | I1328: 2500 | J1328: 2500 | K1328: Folder Layconsa A4 Kawaii c/Fastener colores surtidos | L1328: 45957 | N1328: =+VLOOKUP(A1328,Ordenes!$A$1:$A$669,1,FALSE) -> #N/A
A1329: 1835 | B1329: 2110210006 | C1329: Folder Layconsa A4 Unicorns c/Fastener colores surtidos | D1329: CERRADO | E1329: ÚTILES_LIMA | F1329: ALMA071 | G1329: Almacén Producción Ensamble | H1329: ISAIAS | I1329: 1500 | J1329: 1497 | K1329: Folder Layconsa A4 Unicorns c/Fastener colores surtidos | L1329: 45957 | N1329: =+VLOOKUP(A1329,Ordenes!$A$1:$A$669,1,FALSE) -> #N/A
A1330: 1836 | B1330: 2110210009 | C1330: Folder Layconsa A4 Pre-Escolar Niña c/Fastener colores surtidos | D1330: CERRADO | E1330: ÚTILES_LIMA | F1330: ALMA071 | G1330: Almacén Producción Ensamble | H1330: ISAIAS | I1330: 2000 | J1330: 1996 | K1330: Folder Layconsa A4 Pre-Escolar Niña c/Fastener colores surtidos | L1330: 45957 | N1330: =+VLOOKUP(A1330,Ordenes!$A$1:$A$669,1,FALSE) -> #N/A
A1331: 1837 | B1331: 2110210025 | C1331: Folder Layconsa A4 Femenino c/Fastener colores y diseños surtidos | D1331: CERRADO | E1331: ÚTILES_LIMA | F1331: ALMA071 | G1331: Almacén Producción Ensamble | H1331: ISAIAS | I1331: 4492 | J1331: 4492 | K1331: Folder Layconsa A4 Femenino c/Fastener colores y diseños surtidos | L1331: 45957 | N1331: =+VLOOKUP(A1331,Ordenes!$A$1:$A$669,1,FALSE) -> #N/A
A1332: 1838 | B1332: 2110210010 | C1332: Folder Layconsa Oficio Cut Pets c/Fastener colores surtidos | D1332: CERRADO | E1332: ÚTILES_LIMA | F1332: ALMA071 | G1332: Almacén Producción Ensamble | H1332: ISAIAS | I1332: 2000 | J1332: 1996 | K1332: Folder Layconsa Oficio Cut Pets c/Fastener colores surtidos | L1332: 45957 | N1332: =+VLOOKUP(A1332,Ordenes!$A$1:$A$669,1,FALSE) -> #N/A
A1333: 1839 | B1333: 2110210011 | C1333: Folder Layconsa Oficio Kawaii c/Fastener colores surtidos | D1333: CERRADO | E1333: ÚTILES_LIMA | F1333: ALMA071 | G1333: Almacén Producción Ensamble | H1333: ISAIAS | I1333: 3000 | J1333: 2989 | K1333: Folder Layconsa Oficio Kawaii c/Fastener colores surtidos | L1333: 45957 | N1333: =+VLOOKUP(A1333,Ordenes!$A$1:$A$669,1,FALSE) -> #N/A
A1334: 1840 | B1334: 2110210012 | C1334: Folder Layconsa Oficio Princess c/Fastener colores surtidos | D1334: CERRADO | E1334: ÚTILES_LIMA | F1334: ALMA071 | G1334: Almacén Producción Ensamble | H1334: ISAIAS | I1334: 1000 | J1334: 998 | K1334: Folder Layconsa Oficio Princess c/Fastener colores surtidos | L1334: 45957 | N1334: =+VLOOKUP(A1334,Ordenes!$A$1:$A$669,1,FALSE) -> #N/A
A1335: 1841 | B1335: 2110210013 | C1335: Folder Layconsa Oficio Unicorns c/Fastener colores surtidos | D1335: CERRADO | E1335: ÚTILES_LIMA | F1335: ALMA071 | G1335: Almacén Producción Ensamble | H1335: ISAIAS | I1335: 2000 | J1335: 1995 | K1335: Folder Layconsa Oficio Unicorns c/Fastener colores surtidos | L1335: 45957 | N1335: =+VLOOKUP(A1335,Ordenes!$A$1:$A$669,1,FALSE) -> #N/A
A1336: 1842 | B1336: 2110210014 | C1336: Folder Layconsa Oficio Sweet c/Fastener colores surtidos | D1336: CERRADO | E1336: ÚTILES_LIMA | F1336: ALMA071 | G1336: Almacén Producción Ensamble | H1336: ISAIAS | I1336: 2000 | J1336: 1493 | K1336: Folder Layconsa Oficio Sweet c/Fastener colores surtidos | L1336: 45957 | N1336: =+VLOOKUP(A1336,Ordenes!$A$1:$A$669,1,FALSE) -> #N/A
A1337: 1843 | B1337: 2110210015 | C1337: Folder Layconsa Oficio Madala c/Fastener colores surtidos | D1337: CERRADO | E1337: ÚTILES_LIMA | F1337: ALMA071 | G1337: Almacén Producción Ensamble | H1337: ISAIAS | I1337: 2000 | J1337: 1988 | K1337: Folder Layconsa Oficio Madala c/Fastener colores surtidos | L1337: 45957 | N1337: =+VLOOKUP(A1337,Ordenes!$A$1:$A$669,1,FALSE) -> #N/A
A1338: 1844 | B1338: 2110210016 | C1338: Folder Layconsa Oficio Pre-Escolar Niña c/Fastener colores surtidos | D1338: CERRADO | E1338: ÚTILES_LIMA | F1338: ALMA071 | G1338: Almacén Producción Ensamble | H1338: ISAIAS | I1338: 3000 | J1338: 2991 | K1338: Folder Layconsa Oficio Pre-Escolar Niña c/Fastener colores surtidos | L1338: 45957 | N1338: =+VLOOKUP(A1338,Ordenes!$A$1:$A$669,1,FALSE) -> #N/A
... A2828: 3986 | B2828: 2310360001 | C2828: Tubito Para Bolígrafo 036 | D2828: ABIERTO | E2828: ÚTILES_LIMA | F2828: ALMA071 | G2828: Almacén Producción Ensamble | H2828: ISAIAS | I2828: 330000 | J2828: 0 | K2828: Tubito Para Bolígrafo 036 | L2828: 46121 | N2828: =+VLOOKUP(A2828,Ordenes!$A$1:$A$669,1,FALSE) -> 3986

Sheet Stock
A1: Número de artículo | B1: Descripción del artículo | C1: Código de almacén | D1: Nombre de almacén | E1: En stock | F1: UnidadMedida | G1: Definido | H1: Solicitado | I1: Precio promedio
A2: 1900010018 | B2: Lápiz de Grafito EF Estudiante HB Colores Surtidos | C2: ALMA001 | D2: Almacén Principal Arequipa | E2: 108 | F2: PZ/1 | G2: 0 | H2: 0 | I2: 0.175093
A3: 1900010022 | B3: Lápiz de Grafito Hexagonal 482-2 c/casquillo y borrador EF | C3: ALMA001 | D3: Almacén Principal Arequipa | E3: 7968 | F3: PZ/1 | G3: 0 | H3: 0 | I3: 0.17339
A4: 1900030002 | B4: Plastilina Delgada Bester x 10 | C4: ALMA013 | D4: Almacén Lima Nicolás Ayllón (013) | E4: 8 | F4: PZ/1 | G4: 0 | H4: 0 | I4: 1.03
A5: 1900030003 | B5: Plastilina Jumbo Bester x 10 | C5: ALMA013 | D5: Almacén Lima Nicolás Ayllón (013) | E5: 12 | F5: PZ/1 | G5: 0 | H5: 0 | I5: 1.403333
A6: 1900100008 | B6: Plumones Layconsa School 45 Estuche x 24 | C6: ALMA002 | D6: Almacén Principal Lima (002) | E6: 525 | F6: PZ/1 | G6: 0 | H6: 0 | I6: 4.00261
A7: 1901000019 | B7: Bifoliado EF | C7: ALMA001 | D7: Almacén Principal Arequipa | E7: 5300 | F7: PZ/1 | G7: 0 | H7: 0 | I7: 0.125208
A8: 2000010040 | B8: Cinta Epson 8755 (FX-1050) Original | C8: ALMA002 | D8: Almacén Principal Lima (002) | E8: 5 | F8: PZ/1 | G8: 0 | H8: 0 | I8: 14.338
A9: 2000010071 | B9: Cinta Epson FX/LQ-2170 (S015086) (MRK) | C9: ALMA002 | D9: Almacén Principal Lima (002) | E9: 4 | F9: PZ/1 | G9: 0 | H9: 0 | I9: 60.7175
A10: 2000010115 | B10: Cinta Epson SO15337 (LQ-590) | C10: ALMA002 | D10: Almacén Principal Lima (002) | E10: 5 | F10: PZ/1 | G10: 0 | H10: 0 | I10: 45.228
A11: 2000020074 | B11: Goma en Barra Layconsa x 8 gr. | C11: ALMA001 | D11: Almacén Principal Arequipa | E11: 0 | F11: PZ/1 | G11: 7200 | H11: 200160 | I11: 0.24
A12: 2000020074 | B12: Goma en Barra Layconsa x 8 gr. | C12: ALMA002 | D12: Almacén Principal Lima (002) | E12: 20627 | F12: PZ/1 | G12: 780 | H12: 38910 | I12: 0.241197
A13: 2000020074 | B13: Goma en Barra Layconsa x 8 gr. | C13: ALMA013 | D13: Almacén Lima Nicolás Ayllón (013) | E13: 23760 | F13: PZ/1 | G13: 0 | H13: 0 | I13: 0.253627
... A10262: 2610020058 | B10262: Floculante (Tecnofloc 2540) | C10262: ALMA001 | D10262: Almacén Principal Arequipa | E10262: 60.85 | F10262: KL/1000 | G10262: 0 | H10262: 0 | I10262: 25.209367

Sheet BOM
A1: Código LYC | B1: Posición | C1: Descripción | D1: Und LYC | E1: Qty | F1: Ceco | G1: Componente | H1: Descripción | I1: Und LYC 2 | J1: Qty 2
A2: 2000050591 | B2: 10 | C2: 03 Bolígrafos retráctil Roll click L-64 Layconsa az/ng/rj Blister | D2: BLx1 | E2: 12000 | F2: Blister | G2: 2000050592 | H2: Bolígrafo retráctil Roll click L-64 azul Layconsa | I2: PZ/1 | J2: 1500
A3: 2000050591 | B3: 20 | C3: 03 Bolígrafos retráctil Roll click L-64 Layconsa az/ng/rj Blister | D3: BLx1 | E3: 12000 | F3: Blister | G3: 2000050593 | H3: Bolígrafo retráctil Roll click L-64 negro Layconsa | I3: PZ/1 | J3: 1500
A4: 2000050591 | B4: 30 | C4: 03 Bolígrafos retráctil Roll click L-64 Layconsa az/ng/rj Blister | D4: BLx1 | E4: 12000 | F4: Blister | G4: 2000050594 | H4: Bolígrafo retráctil Roll click L-64 rojo Layconsa | I4: PZ/1 | J4: 1500
A5: 2000050591 | B5: 40 | C5: 03 Bolígrafos retráctil Roll click L-64 Layconsa az/ng/rj Blister | D5: BLx1 | E5: 12000 | F5: Blister | G5: 2320071496 | H5: Respaldo 03 Bolígrafos retráctil Roll click L-64 LYC az/ng/rj Blister | I5: PZ/1 | J5: 1520
A6: 2000050591 | B6: 50 | C6: 03 Bolígrafos retráctil Roll click L-64 Layconsa az/ng/rj Blister | D6: BLx1 | E6: 12000 | F6: Blister | G6: 2500030045 | H6: Cajón C/I 51.5x29.5x22.5 cm (LYC) pote cola sintética x 220 gr | I6: PZ/1 | J6: 13
A7: 2000050591 | B7: 60 | C7: 03 Bolígrafos retráctil Roll click L-64 Layconsa az/ng/rj Blister | D7: BLx1 | E7: 12000 | F7: Blister | G7: 2500150007 | H7: Cinta embalaje transparente 45 mc x 2" x 100 mt | I7: ROLL/1 | J7: 2
A8: 2000050591 | B8: 70 | C8: 03 Bolígrafos retráctil Roll click L-64 Layconsa az/ng/rj Blister | D8: BLx1 | E8: 12000 | F8: Blister | G8: 2500150004 | H8: Cinta Adh Transparente 3/4 x 72 Yds. - Planta | I8: PZ/1 | J8: 1
A9: 2000050591 | B9: 80 | C9: 03 Bolígrafos retráctil Roll click L-64 Layconsa az/ng/rj Blister | D9: BLx1 | E9: 12000 | F9: Blister | G9: 2500090065 | H9: Bolsa Para Blíster de 10x15x1 | I9: PZ/1 | J9: 250
A10: 2000050597 | B10: 10 | C10: 03 Bolígrafos retráctil Gelly click L-61 Layconsa az/ng/rj Blister | D10: BLx1 | E10: 12000 | F10: Blister | G10: 2000050588 | H10: Bolígrafo retráctil gelly click L-61 azul Layconsa | I10: PZ/1 | J10: 1500
A11: 2000050597 | B11: 20 | C11: 03 Bolígrafos retráctil Gelly click L-61 Layconsa az/ng/rj Blister | D11: BLx1 | E11: 12000 | F11: Blister | G11: 2000050589 | H11: Bolígrafo retráctil gelly click L-61 negro Layconsa | I11: PZ/1 | J11: 1500
A12: 2000050597 | B12: 30 | C12: 03 Bolígrafos retráctil Gelly click L-61 Layconsa az/ng/rj Blister | D12: BLx1 | E12: 12000 | F12: Blister | G12: 2000050590 | H12: Bolígrafo retráctil gelly click L-61 rojo Layconsa | I12: PZ/1 | J12: 1500
A13: 2000050597 | B13: 40 | C13: 03 Bolígrafos retráctil Gelly click L-61 Layconsa az/ng/rj Blister | D13: BLx1 | E13: 12000 | F13: Blister | G13: 2320071495 | H13: Respaldo 03 Bolígrafos retráctil Gelly click L-61 LYC az/ng/rj Blister | I13: PZ/1 | J13: 1520
... A728: 2110100139 | B728: 70 | C728: Tinta Para Marcador de Pizarra Layconsa L-126 Verde | D728: PZ/1 | E728: 12000 | F728: Ensamblado - Marcador | G728: 2410110088 | H728: Tinta Pizarra Verde WB 7339.1 | I728: KL/1000 | J728: 336
A729: 2110100225 | B729: 10 | C729: 02 Bol.TRIPLUS (azu/roj)+01 Resaltador neón amarillo+01 Corrector Líquido 9ml | D729: BLx1 | E729: 1000 | G729: 2000050601 | H729: Bolígrafo TRIPLUS L-35F azul Presentacion 50 Layconsa | I729: PZ/1 | J729: 1000
A730: 2110100225 | B730: 20 | C730: 02 Bol.TRIPLUS (azu/roj)+01 Resaltador neón amarillo+01 Corrector Líquido 9ml | D730: BLx1 | E730: 1000 | G730: 2000050603 | H730: Bolígrafo TRIPLUS L-35F rojo Presentacion 50 Layconsa | I730: PZ/1 | J730: 1000
A731: 2110100225 | B731: 30 | C731: 02 Bol.TRIPLUS (azu/roj)+01 Resaltador neón amarillo+01 Corrector Líquido 9ml | D731: BLx1 | E731: 1000 | G731: 2000070139 | H731: Resaltador Layconsa L-48 Amarillo | I731: PZ/1 | J731: 1000
A732: 2110100225 | B732: 40 | C732: 02 Bol.TRIPLUS (azu/roj)+01 Resaltador neón amarillo+01 Corrector Líquido 9ml | D732: BLx1 | E732: 1000 | G732: 2000150041 | H732: Corrector Líquido ergonómico Layconsa 9ml | I732: PZ/1 | J732: 1000
A733: 2110100225 | B733: 50 | C733: 02 Bol.TRIPLUS (azu/roj)+01 Resaltador neón amarillo+01 Corrector Líquido 9ml | D733: BLx1 | E733: 1000 | G733: 2320071524 | H733: Respaldo 02 Bol.TRIPLUS (azu/roj)+01 Resaltador amarillo+01 Corrector 9ml | I733: PZ/1 | J733: 1000
A734: 2110100225 | B734: 60 | C734: 02 Bol.TRIPLUS (azu/roj)+01 Resaltador neón amarillo+01 Corrector Líquido 9ml | D734: BLx1 | E734: 1000 | G734: 2500090065 | H734: Bolsa Para Blíster de 10x15x1 | I734: PZ/1 | J734: 100
A735: 2110100225 | B735: 70 | C735: 02 Bol.TRIPLUS (azu/roj)+01 Resaltador neón amarillo+01 Corrector Líquido 9ml | D735: BLx1 | E735: 1000 | G735: 2500030226 | H735: Cajón Para Plumones LYC School 45x12pz 34x31x36.00cm | I735: PZ/1 | J735: 10
A736: 2110100225 | B736: 80 | C736: 02 Bol.TRIPLUS (azu/roj)+01 Resaltador neón amarillo+01 Corrector Líquido 9ml | D736: BLx1 | E736: 1000 | G736: 2500150004 | H736: Cinta Adh Transparente 3/4 x 72 Yds. - Planta | I736: PZ/1 | J736: 1
A737: 2110100225 | B737: 90 | C737: 02 Bol.TRIPLUS (azu/roj)+01 Resaltador neón amarillo+01 Corrector Líquido 9ml | D737: BLx1 | E737: 1000 | G737: 2500150007 | H737: Cinta embalaje transparente 45 mc x 2" x 100 mt | I737: ROLL/1 | J737: 0.25
A738: 2110100227 | B738: 10 | C738: 01 Tijera escolar + 01 Silicona de 100 ml. | D738: BLx1 | E738: 1650 | F738: Blister | G738: 2000630065 | H738: Tijera Escolar Layconsa 5" Colores surtidos | I738: PZ/1 | J738: 1650
A739: 2110100227 | B739: 20 | C739: 01 Tijera escolar + 01 Silicona de 100 ml. | D739: BLx1 | E739: 1650 | F739: Blister | G739: 2000020080 | H739: Pegamento Silicona Líquida de 100ml | I739: PZ/1 | J739: 1650
A740: 2110100227 | B740: 30 | C740: 01 Tijera escolar + 01 Silicona de 100 ml. | D740: BLx1 | E740: 1650 | F740: Blister | G740: 2500030019 | H740: Cajón 205 C/I 33.0x22.7x17cm (LYC) cola sintetica c/aplicador x 250 gr | I740: PZ/1 | J740: 70
A741: 2110100227 | B741: 40 | C741: 01 Tijera escolar + 01 Silicona de 100 ml. | D741: BLx1 | E741: 1650 | F741: Blister | G741: 2320071503 | H741: Respaldo Tijera escolar + Silicona de 100 ml. Blister | I741: PZ/1 | J741: 1670
A742: 2110100227 | B742: 50 | C742: 01 Tijera escolar + 01 Silicona de 100 ml. | D742: BLx1 | E742: 1650 | F742: Blister | G742: 2500150007 | H742: Cinta embalaje transparente 45 mc x 2" x 100 mt | I742: ROLL/1 | J742: 4
A743: 2110100227 | B743: 60 | C743: 01 Tijera escolar + 01 Silicona de 100 ml. | D743: BLx1 | E743: 1650 | F743: Blister | G743: 2500150004 | H743: Cinta Adh Transparente 3/4 x 72 Yds. - Planta | I743: PZ/1 | J743: 2
A744: 2110100227 | B744: 70 | C744: 01 Tijera escolar + 01 Silicona de 100 ml. | D744: BLx1 | E744: 1650 | F744: Blister | G744: 2500090019 | H744: Bolsa Para Tablero Acrílico de 10x15x1 | I744: PZ/1 | J744: 140
A745: 2110100244 | B745: 10 | C745: Pack escolar Layconsa Agroindustria | D745: PAK/1 | E745: 1000 | F745: Blister | G745: 2140110604 | H745: Cuad. Grap. A4 Cuadr. 80 H Layconsa Estudiante | I745: PZ/1 | J745: 5
A746: 2110100244 | B746: 20 | C746: Pack escolar Layconsa Agroindustria | D746: PAK/1 | E746: 1000 | F746: Blister | G746: 2000140133 | H746: Lápiz Color Layconsa Largos x 12 Triangular | I746: PZ/1 | J746: 1
A747: 2110100244 | B747: 30 | C747: Pack escolar Layconsa Agroindustria | D747: PAK/1 | E747: 1000 | F747: Blister | G747: 2110020095 | H747: Plumones Layconsa School 45 Estuche x 12 | I747: PZ/1 | J747: 1
A748: 2110100244 | B748: 40 | C748: Pack escolar Layconsa Agroindustria | D748: PAK/1 | E748: 1000 | F748: Blister | G748: 2000140106 | H748: Lápiz Hexagonal Layconsa Súper Grafito 2B | I748: PZ/1 | J748: 2
A749: 2110100244 | B749: 50 | C749: Pack escolar Layconsa Agroindustria | D749: PAK/1 | E749: 1000 | F749: Blister | G749: 2110080227 | H749: Bolígrafo Layconsa crystal L-036 Azul | I749: PZ/1 | J749: 2
... A800: 2110120124 | B800: 80 | C800: 03 Marcador Para Pizarra Layconsa L-123 Blister | D800: BLx1 | E800: 3270 | F800: Blister | G800: 2500090019 | H800: Bolsa Para Tablero Acrílico de 10x15x1 | I800: PZ/1 | J800: 275
A801: 2110120140 | B801: 10 | C801: Goma en Barra Layconsa 21gr Blister | D801: BLx1 | E801: 1000 | G801: 2000020075 | H801: Goma en Barra Layconsa x 21gr. | I801: PZ/1 | J801: 1000
A802: 2110120140 | B802: 20 | C802: Goma en Barra Layconsa 21gr Blister | D802: BLx1 | E802: 1000 | G802: 2320070365 | H802: Respaldo LYC Goma Barra x 21gr | I802: PZ/1 | J802: 1000
A803: 2110120140 | B803: 30 | C803: Goma en Barra Layconsa 21gr Blister | D803: BLx1 | E803: 1000 | G803: 2500090065 | H803: Bolsa Para Blíster de 10x15x1 | I803: PZ/1 | J803: 100
A804: 2110120140 | B804: 40 | C804: Goma en Barra Layconsa 21gr Blister | D804: BLx1 | E804: 1000 | G804: 2500030047 | H804: Cajón Para Bandeja Portapapeles 54.8 mm x 38 mm x 29.4 mm | I804: PZ/1 | J804: 10
A805: 2110120140 | B805: 50 | C805: Goma en Barra Layconsa 21gr Blister | D805: BLx1 | E805: 1000 | G805: 2500150004 | H805: Cinta Adh Transparente 3/4 x 72 Yds. - Planta | I805: PZ/1 | J805: 1
A806: 2110120140 | B806: 60 | C806: Goma en Barra Layconsa 21gr Blister | D806: BLx1 | E806: 1000 | G806: 2500150007 | H806: Cinta embalaje transparente 45 mc x 2" x 100 mt | I806: ROLL/1 | J806: 0.25
A807: 2110120276 | B807: 10 | C807: 03 Bolígrafos L-036 Fine Azul/Negro/Rojo Blister | D807: BLx1 | E807: 2720 | F807: Blister | G807: 2310190035 | H807: Bolígrafo Layconsa L-036 Fine Azul Granel P.S. | I807: PZ/1 | J807: 2720
A808: 2110120276 | B808: 20 | C808: 03 Bolígrafos L-036 Fine Azul/Negro/Rojo Blister | D808: BLx1 | E808: 2720 | F808: Blister | G808: 2310190036 | H808: Bolígrafo Layconsa L-036 Fine Negro Granel P.S. | I808: PZ/1 | J808: 2720
A809: 2110120276 | B809: 30 | C809: 03 Bolígrafos L-036 Fine Azul/Negro/Rojo Blister | D809: BLx1 | E809: 2720 | F809: Blister | G809: 2310190037 | H809: Bolígrafo Layconsa L-036 Fine Rojo Granel P.S. | I809: PZ/1 | J809: 2720
A810: 2110120276 | B810: 40 | C810: 03 Bolígrafos L-036 Fine Azul/Negro/Rojo Blister | D810: BLx1 | E810: 2720 | F810: Blister | G810: 2320070685 | H810: Respaldo 03 Bolígrafos L-036 Fine Azul/Negro/Rojo Blister | I810: PZ/1 | J810: 2720
A811: 2110120276 | B811: 50 | C811: 03 Bolígrafos L-036 Fine Azul/Negro/Rojo Blister | D811: BLx1 | E811: 2720 | F811: Blister | G811: 2500030045 | H811: Cajón C/I 51.5x29.5x22.5 cm (LYC) pote cola sintética x 220 gr | I811: PZ/1 | J811: 24
A812: 2110120276 | B812: 60 | C812: 03 Bolígrafos L-036 Fine Azul/Negro/Rojo Blister | D812: BLx1 | E812: 2720 | F812: Blister | G812: 2500150007 | H812: Cinta embalaje transparente 45 mc x 2" x 100 mt | I812: ROLL/1 | J812: 4
A813: 2110120276 | B813: 70 | C813: 03 Bolígrafos L-036 Fine Azul/Negro/Rojo Blister | D813: BLx1 | E813: 2720 | F813: Blister | G813: 2500150004 | H813: Cinta Adh Transparente 3/4 x 72 Yds. - Planta | I813: PZ/1 | J813: 2
A814: 2110120276 | B814: 80 | C814: 03 Bolígrafos L-036 Fine Azul/Negro/Rojo Blister | D814: BLx1 | E814: 2720 | F814: Blister | G814: 2500090019 | H814: Bolsa Para Tablero Acrílico de 10x15x1 | I814: PZ/1 | J814: 230
A815: 2110120306 | B815: 10 | C815: 01 Corrector Liquido Layconsa Blister | D815: BLx1 | E815: 1200 | G815: 2000150041 | H815: Corrector Líquido ergonómico Layconsa 9ml | I815: PZ/1 | J815: 1200
A816: 2110120306 | B816: 20 | C816: 01 Corrector Liquido Layconsa Blister | D816: BLx1 | E816: 1200 | G816: 2320071335 | H816: Respaldo 1 Corrector Líquido ergonómico Layconsa 9 ml. | I816: PZ/1 | J816: 1200
A817: 2110120306 | B817: 30 | C817: 01 Corrector Liquido Layconsa Blister | D817: BLx1 | E817: 1200 | G817: 2500090065 | H817: Bolsa Para Blíster de 10x15x1 | I817: PZ/1 | J817: 100
A818: 2110120306 | B818: 40 | C818: 01 Corrector Liquido Layconsa Blister | D818: BLx1 | E818: 1200 | G818: 2500030226 | H818: Cajón Para Plumones LYC School 45x12pz 34x31x36.00cm | I818: PZ/1 | J818: 10
A819: 2110120306 | B819: 50 | C819: 01 Corrector Liquido Layconsa Blister | D819: BLx1 | E819: 1200 | G819: 2500150004 | H819: Cinta Adh Transparente 3/4 x 72 Yds. - Planta | I819: PZ/1 | J819: 1
A820: 2110120306 | B820: 60 | C820: 01 Corrector Liquido Layconsa Blister | D820: BLx1 | E820: 1200 | G820: 2500150007 | H820: Cinta embalaje transparente 45 mc x 2" x 100 mt | I820: ROLL/1 | J820: 0.25
A821: 2110120349 | B821: 10 | C821: 1 Corrector Líquido ergonómico Layconsa 9 ml. | D821: PZ/1 | E821: 600 | F821: Blister | G821: 2000150041 | H821: Corrector Líquido ergonómico Layconsa 9ml | I821: PZ/1 | J821: 600
A822: 2110120349 | B822: 20 | C822: 1 Corrector Líquido ergonómico Layconsa 9 ml. | D822: PZ/1 | E822: 600 | F822: Blister | G822: 2320071335 | H822: Respaldo 1 Corrector Líquido ergonómico Layconsa 9 ml. | I822: PZ/1 | J822: 610
A823: 2110120349 | B823: 30 | C823: 1 Corrector Líquido ergonómico Layconsa 9 ml. | D823: PZ/1 | E823: 600 | F823: Blister | G823: 2500030045 | H823: Cajón C/I 51.5x29.5x22.5 cm (LYC) pote cola sintética x 220 gr | I823: PZ/1 | J823: 3
A824: 2110120349 | B824: 40 | C824: 1 Corrector Líquido ergonómico Layconsa 9 ml. | D824: PZ/1 | E824: 600 | F824: Blister | G824: 2500150007 | H824: Cinta embalaje transparente 45 mc x 2" x 100 mt | I824: ROLL/1 | J824: 1
A825: 2110120349 | B825: 50 | C825: 1 Corrector Líquido ergonómico Layconsa 9 ml. | D825: PZ/1 | E825: 600 | F825: Blister | G825: 2500150004 | H825: Cinta Adh Transparente 3/4 x 72 Yds. - Planta | I825: PZ/1 | J825: 1
A826: 2110120349 | B826: 60 | C826: 1 Corrector Líquido ergonómico Layconsa 9 ml. | D826: PZ/1 | E826: 600 | F826: Blister | G826: 2500090019 | H826: Bolsa Para Tablero Acrílico de 10x15x1 | I826: PZ/1 | J826: 50
A827: 2110120374 | B827: 10 | C827: Tajador Layconsa Tri-3 c/dep. triple Blister | D827: BLx1 | E827: 1200 | G827: 2000600049 | H827: Tajador Layconsa Tri-3 c/dep. triple | I827: PZ/1 | J827: 1200
A828: 2110120374 | B828: 20 | C828: Tajador Layconsa Tri-3 c/dep. triple Blister | D828: BLx1 | E828: 1200 | G828: 2320071375 | H828: Respaldo Tajador Layconsa Tri-3 c/dep. triple Blíster | I828: PZ/1 | J828: 1200
A829: 2110120374 | B829: 30 | C829: Tajador Layconsa Tri-3 c/dep. triple Blister | D829: BLx1 | E829: 1200 | G829: 2500030226 | H829: Cajón Para Plumones LYC School 45x12pz 34x31x36.00cm | I829: PZ/1 | J829: 20
A830: 2110120374 | B830: 40 | C830: Tajador Layconsa Tri-3 c/dep. triple Blister | D830: BLx1 | E830: 1200 | G830: 2500090020 | H830: Bolsa de PP Cristal Para Bandeja Portapapeles 1 Piso | I830: PZ/1 | J830: 100
A831: 2110120374 | B831: 50 | C831: Tajador Layconsa Tri-3 c/dep. triple Blister | D831: BLx1 | E831: 1200 | G831: 2500150004 | H831: Cinta Adh Transparente 3/4 x 72 Yds. - Planta | I831: PZ/1 | J831: 1
A832: 2110120374 | B832: 60 | C832: Tajador Layconsa Tri-3 c/dep. triple Blister | D832: BLx1 | E832: 1200 | G832: 2500150007 | H832: Cinta embalaje transparente 45 mc x 2" x 100 mt | I832: ROLL/1 | J832: 0.25
A833: 2110120425 | B833: 10 | C833: Borrador LA-20 + Tajador con depósito doble 513 | D833: BLx1 | E833: 2340 | F833: Blister | G833: 2000030052 | H833: Borrador Blanco LA-20 c/Plastificado | I833: PZ/1 | J833: 2340
A834: 2110120425 | B834: 20 | C834: Borrador LA-20 + Tajador con depósito doble 513 | D834: BLx1 | E834: 2340 | F834: Blister | G834: 2000600053 | H834: Tajador Layconsa 513 c/dep. doble | I834: PZ/1 | J834: 2340
A835: 2110120425 | B835: 30 | C835: Borrador LA-20 + Tajador con depósito doble 513 | D835: BLx1 | E835: 2340 | F835: Blister | G835: 2320071457 | H835: Respaldo Borrador LA-20 + Tajador con depósito doble 513 | I835: PZ/1 | J835: 2350
A836: 2110120425 | B836: 40 | C836: Borrador LA-20 + Tajador con depósito doble 513 | D836: BLx1 | E836: 2340 | F836: Blister | G836: 2500030047 | H836: Cajón Para Bandeja Portapapeles 54.8 mm x 38 mm x 29.4 mm | I836: PZ/1 | J836: 20
A837: 2110120425 | B837: 50 | C837: Borrador LA-20 + Tajador con depósito doble 513 | D837: BLx1 | E837: 2340 | F837: Blister | G837: 2500150007 | H837: Cinta embalaje transparente 45 mc x 2" x 100 mt | I837: ROLL/1 | J837: 3
A838: 2110120425 | B838: 60 | C838: Borrador LA-20 + Tajador con depósito doble 513 | D838: BLx1 | E838: 2340 | F838: Blister | G838: 2500150004 | H838: Cinta Adh Transparente 3/4 x 72 Yds. - Planta | I838: PZ/1 | J838: 1
A839: 2110120425 | B839: 70 | C839: Borrador LA-20 + Tajador con depósito doble 513 | D839: BLx1 | E839: 2340 | F839: Blister | G839: 2500090019 | H839: Bolsa Para Tablero Acrílico de 10x15x1 | I839: PZ/1 | J839: 195
A840: 2110120430 | B840: 10 | C840: Bol. crystal L-036 (a,n,r) + corrector 4ml Blister | D840: BLx1 | E840: 260 | F840: Blister | G840: 2310190035 | H840: Bolígrafo Layconsa L-036 Fine Azul Granel P.S. | I840: PZ/1 | J840: 260
A841: 2110120430 | B841: 20 | C841: Bol. crystal L-036 (a,n,r) + corrector 4ml Blister | D841: BLx1 | E841: 260 | F841: Blister | G841: 2310190036 | H841: Bolígrafo Layconsa L-036 Fine Negro Granel P.S. | I841: PZ/1 | J841: 260
A842: 2110120430 | B842: 30 | C842: Bol. crystal L-036 (a,n,r) + corrector 4ml Blister | D842: BLx1 | E842: 260 | F842: Blister | G842: 2310190037 | H842: Bolígrafo Layconsa L-036 Fine Rojo Granel P.S. | I842: PZ/1 | J842: 260
A843: 2110120430 | B843: 40 | C843: Bol. crystal L-036 (a,n,r) + corrector 4ml Blister | D843: BLx1 | E843: 260 | F843: Blister | G843: 2000150040 | H843: Corrector Líquido 4ml Layconsa x 3 colores variados | I843: PZ/1 | J843: 260
A844: 2110120430 | B844: 50 | C844: Bol. crystal L-036 (a,n,r) + corrector 4ml Blister | D844: BLx1 | E844: 260 | F844: Blister | G844: 2320071476 | H844: Respaldo 3 lapiceros Crystall L-36 (rojo, azul y negro) + Correctos liquido 4ml | I844: PZ/1 | J844: 270
... A855: 2110120433 | B855: 70 | C855: 01 Tijera escolar + 01 goma en barra de 21g Blister | D855: BL/1 | E855: 710 | F855: Blister | G855: 2500090019 | H855: Bolsa Para Tablero Acrílico de 10x15x1 | I855: PZ/1 | J855: 60
A856: 2110120443 | B856: 10 | C856: 03 Bolígrafos TRI L-035 Azul/1Negro/1Rojo Blister | D856: BLx1 | E856: 1200 | G856: 2000050601 | H856: Bolígrafo TRIPLUS L-35F azul Presentacion 50 Layconsa | I856: PZ/1 | J856: 1200
A857: 2110120443 | B857: 20 | C857: 03 Bolígrafos TRI L-035 Azul/1Negro/1Rojo Blister | D857: BLx1 | E857: 1200 | G857: 2000050602 | H857: Bolígrafo TRIPLUS L-35F negro Presentacion 50 Layconsa | I857: PZ/1 | J857: 1200
A858: 2110120443 | B858: 30 | C858: 03 Bolígrafos TRI L-035 Azul/1Negro/1Rojo Blister | D858: BLx1 | E858: 1200 | G858: 2000050603 | H858: Bolígrafo TRIPLUS L-35F rojo Presentacion 50 Layconsa | I858: PZ/1 | J858: 1200
A859: 2110120443 | B859: 40 | C859: 03 Bolígrafos TRI L-035 Azul/1Negro/1Rojo Blister | D859: BLx1 | E859: 1200 | G859: 2320050844 | H859: Blister caja bolígrafo triplus x 1 Azul/1Negro/1Rojo Blister | I859: PZ/1 | J859: 1200
A860: 2110120443 | B860: 50 | C860: 03 Bolígrafos TRI L-035 Azul/1Negro/1Rojo Blister | D860: BLx1 | E860: 1200 | G860: 2500030226 | H860: Cajón Para Plumones LYC School 45x12pz 34x31x36.00cm | I860: PZ/1 | J860: 20
A861: 2140010024 | B861: 10 | C861: Borrador Layconsa Mixto LA-40 | D861: PZ/1 | E861: 100000 | F861: Borrador | G861: 2310310001 | H861: Masa BR Roja P.S. | I861: KL/1000 | J861: 1446.2831
A862: 2140010024 | B862: 20 | C862: Borrador Layconsa Mixto LA-40 | D862: PZ/1 | E862: 100000 | F862: Borrador | G862: 2310310002 | H862: Masa BR Azul P.S. | I862: KL/1000 | J862: 16.038697
A863: 2140010024 | B863: 30 | C863: Borrador Layconsa Mixto LA-40 | D863: PZ/1 | E863: 100000 | F863: Borrador | G863: 2320050508 | H863: Cajita Layconsa Borrador LA-40 | I863: PZ/1 | J863: 2510.1833
A864: 2140010024 | B864: 40 | C864: Borrador Layconsa Mixto LA-40 | D864: PZ/1 | E864: 100000 | F864: Borrador | G864: 2500030118 | H864: Cajón Layconsa 21 x 23.9 x 18.2cm | I864: PZ/1 | J864: 123.47251
A865: 2140010024 | B865: 50 | C865: Borrador Layconsa Mixto LA-40 | D865: PZ/1 | E865: 100000 | F865: Borrador | G865: 2500150004 | H865: Cinta Adh Transparente 3/4 x 72 Yds. - Planta | I865: PZ/1 | J865: 1.2729124
A866: 2140010024 | B866: 60 | C866: Borrador Layconsa Mixto LA-40 | D866: PZ/1 | E866: 100000 | F866: Borrador | G866: 2600045244 | H866: Ribbon L288 CERA | I866: PZ/1 | J866: 6.3645621
A867: 2140040002 | B867: 10 | C867: Limpiatipos Layconsa x 35 gr. | D867: PZ/1 | E867: 120000 | F867: Limpiatipo | G867: 2310250019 | H867: Limpiatipo Layconsa 35Gr Azul Granel | I867: PZ/1 | J867: 20000
A868: 2140040002 | B868: 20 | C868: Limpiatipos Layconsa x 35 gr. | D868: PZ/1 | E868: 120000 | F868: Limpiatipo | G868: 2310250021 | H868: Limpiatipo Layconsa 35Gr Rosado Granel | I868: PZ/1 | J868: 20000
A869: 2140040002 | B869: 30 | C869: Limpiatipos Layconsa x 35 gr. | D869: PZ/1 | E869: 120000 | F869: Limpiatipo | G869: 2310250022 | H869: Limpiatipo Layconsa 35Gr Verde Neón Granel | I869: PZ/1 | J869: 20000
A870: 2140040002 | B870: 40 | C870: Limpiatipos Layconsa x 35 gr. | D870: PZ/1 | E870: 120000 | F870: Limpiatipo | G870: 2310250030 | H870: Limpiatipo Layconsa 35Gr Violeta Granel P.S. | I870: PZ/1 | J870: 20000
A871: 2140040002 | B871: 50 | C871: Limpiatipos Layconsa x 35 gr. | D871: PZ/1 | E871: 120000 | F871: Limpiatipo | G871: 2310250031 | H871: Limpiatipo Layconsa 35Gr Turquesa Granel P.S. | I871: PZ/1 | J871: 20000
A872: 2140040002 | B872: 60 | C872: Limpiatipos Layconsa x 35 gr. | D872: PZ/1 | E872: 120000 | F872: Limpiatipo | G872: 2310250032 | H872: Limpiatipo Layconsa 35Gr Anaranjado Granel P.S. | I872: PZ/1 | J872: 20000
... A1049: 2310390064 | B1049: 70 | C1049: Peine Patrullero Rojo Sin Cola 16A Lucas | D1049: PZ/1 | E1049: 43050 | F1049: Ensamble | G1049: 2410200005 | H1049: Disolvente Retardador Vinilico | I1049: LT/1000 | J1049: 1
A1050: 2310390064 | B1050: 80 | C1050: Peine Patrullero Rojo Sin Cola 16A Lucas | D1050: PZ/1 | E1050: 43050 | F1050: Ensamble | G1050: 2430860001 | H1050: Estearato de Zinc | I1050: KL/1000 | J1050: 0.8
...

Sheet Materiales
A1: Codigo | B1: Descripción | C1: UM | D1: TIPO DE COMPRA | E1: MOQ | F1: LT-días | G1: Tipo | H1: Columna1 | I1: Columna2 | J1: División
A2: 2320040200 | B2: Caja para Plumones Layconsa school 45 x 12 pz. | C2: ML/1000 | D2: NACIONAL | E2: 1000 | G2: Cajas | H2: 1 | I2: 232004 | J2: Útiles
A3: 2320040429 | B3: Caja para Marcadores Layconsa 47 x 12 pz. Amarillo - Marron | C3: ML/1000 | D3: NACIONAL | E3: 1000 | G3: Cajas | H3: 1 | I3: 232004 | J3: Útiles
A4: 2320050052 | B4: Cajita P´Témperas Set x 7 (PT) | C4: ML/1000 | D4: NACIONAL | E4: 1000 | G4: Cajitas | H4: 1 | I4: 232005 | J4: Útiles
A5: 2320050055 | B5: Cajita P´ Témperas Sueltas x 30 (PT) | C5: ML/1000 | D5: NACIONAL | E5: 1000 | G5: Cajitas | H5: 1 | I5: 232005 | J5: Útiles
A6: 2320050073 | B6: Cajita Crayón JUMBO x 12 | C6: ML/1000 | D6: NACIONAL | E6: 1000 | G6: Cajitas | H6: 1 | I6: 232005 | J6: Útiles
A7: 2320050085 | B7: Cajita Témpera Set x 6 Neón P.T. | C7: ML/1000 | D7: NACIONAL | E7: 1000 | G7: Cajitas | H7: 1 | I7: 232005 | J7: Útiles
A8: 2320050205 | B8: Cajita Crayola Puppy Jumbo Neón x 6 | C8: ML/1000 | D8: NACIONAL | E8: 1000 | G8: Cajitas | H8: 1 | I8: 232005 | J8: Útiles
A9: 2320050366 | B9: Caja para Marcadores Layconsa L-123 x 12 pz. Azul | C9: ML/1000 | D9: NACIONAL | E9: 1000 | G9: Cajitas | H9: 1 | I9: 232005 | J9: Útiles
A10: 2320050367 | B10: Caja para Marcadores Layconsa L-123 x 12 pz. Negro | C10: ML/1000 | D10: NACIONAL | E10: 1000 | G10: Cajitas | H10: 1 | I10: 232005 | J10: Útiles
A11: 2320050368 | B11: Caja para Marcadores Layconsa L-123 x 12 pz. Rojo | C11: ML/1000 | D11: NACIONAL | E11: 1000 | G11: Cajitas | H11: 1 | I11: 232005 | J11: Útiles
A12: 2320050369 | B12: Caja para Marcadores Layconsa L-123 x 12 pz. Verde | C12: ML/1000 | D12: NACIONAL | E12: 1000 | G12: Cajitas | H12: 1 | I12: 232005 | J12: Útiles
A13: 2320050508 | B13: Cajita Layconsa Borrador LA-40 | C13: ML/1000 | D13: NACIONAL | E13: 1000 | G13: Cajitas | H13: 1 | I13: 232005 | J13: Útiles
... A55: 2320071471 | B55: Etiqueta Crayon Jumbo LYC Azul | C55: ML/1000 | D55: NACIONAL | E55: 1000 | G55: Etiquetas | H55: 1 | I55: 232007 | J55: Útiles
A56: 2410090004 | B56: Pigmento Fire Red FEX-15 | C56: KL/1000 | D56: NACIONAL | E56: 10 | F56: 7 | G56: Pigmentos | H56: 1 | I56: 241009 | J56: Útiles
A57: 2410090036 | B57: Pigmento Astral Pink FEX-1 | C57: KL/1000 | D57: NACIONAL | E57: 10 | F57: 7 | G57: Pigmentos | H57: 1 | I57: 241009 | J57: Útiles
A58: 2410090048 | B58: Masterbach Amarillo 11026/2 | C58: KL/1000 | D58: NACIONAL | E58: 25 | F58: 9 | G58: Masterbach | H58: 1 | I58: 241009 | J58: Útiles
A59: 2410090057 | B59: Masterbach Azul 15052/1 | C59: KL/1000 | D59: NACIONAL | E59: 25 | F59: 9 | G59: Masterbach | H59: 1 | I59: 241009 | J59: Útiles
A60: 2410090079 | B60: Pigmento Panax Violet 605 | C60: KL/1000 | D60: NACIONAL | E60: 10 | F60: 7 | G60: Pigmentos | H60: 1 | I60: 241009 | J60: Útiles
A61: 2410090106 | B61: Pigmento Stellar Green FEX-8 | C61: KL/1000 | D61: NACIONAL | E61: 10 | F61: 7 | G61: Pigmentos | H61: 1 | I61: 241009 | J61: Útiles
A62: 2410090110 | B62: Pigmento Amarillo Lunar Yellow FEX-27 | C62: KL/1000 | D62: NACIONAL | E62: 10 | F62: 7 | G62: Pigmentos | H62: 1 | I62: 241009 | J62: Útiles
A63: 2410090127 | B63: Pigmento Verde V-13512 | C63: KL/1000 | D63: NACIONAL | E63: 10 | F63: 7 | G63: Pigmentos | H63: 1 | I63: 241009 | J63: Útiles
A64: 2410090129 | B64: Pigmento Azul Ftalocianina 1501-C | C64: KL/1000 | D64: NACIONAL | E64: 10 | F64: 7 | G64: Pigmentos | H64: 1 | I64: 241009 | J64: Útiles
A65: 2410090130 | B65: Pigmento Amarillo 151-C | C65: KL/1000 | D65: NACIONAL | E65: 10 | F65: 7 | G65: Pigmentos | H65: 1 | I65: 241009 | J65: Útiles
A66: 2410090131 | B66: Pigmento Verde Fluor | C66: KL/1000 | D66: NACIONAL | E66: 10 | F66: 7 | G66: Pigmentos | H66: 1 | I66: 241009 | J66: Útiles
A67: 2410090132 | B67: Pigmento Alsa Colors 4010 | C67: KL/1000 | D67: NACIONAL | E67: 10 | F67: 7 | G67: Pigmentos | H67: 1 | I67: 241009 | J67: Útiles
... A108: 2410090317 | B108: Pigmento Prosphere S-17 Yellow | C108: KL/1000 | D108: NACIONAL | E108: 10 | F108: 7 | G108: Pigmentos | H108: 1 | I108: 241009 | J108: Útiles
A109: 2410100007 | B109: Poliestireno Cristal | C109: KL/1000 | D109: NACIONAL | G109: Otros | H109: 1 | I109: 241010 | J109: Útiles
A110: 2410100010 | B110: San | C110: KL/1000 | D110: NACIONAL | E110: 25 | F110: 7 | G110: Resinas | H110: 1 | I110: 241010 | J110: Útiles
A111: 2410100014 | B111: Paletas Burbujas Blanca para Témpera | C111: ML/1000 | D111: NACIONAL | E111: 100000 | F111: 10 | G111: Paletas | H111: 1 | I111: 241010 | J111: Útiles
A112: 2410110027 | B112: Tinta Para Bolígrafo Negra Dokumental | C112: KL/1000 | D112: IMPORTADO | E112: 140 | F112: 120 | G112: Tintas | H112: 1 | I112: 241011 | J112: Útiles
A113: 2410110028 | B113: Tinta Para Bolígrafo Verde Dokumental | C113: KL/1000 | D113: IMPORTADO | E113: 140 | F113: 120 | G113: Tintas | H113: 1 | I113: 241011 | J113: Útiles
A114: 2410110036 | B114: Tintas Para Bolígrafo Rojo Dokumental | C114: KL/1000 | D114: IMPORTADO | E114: 140 | F114: 120 | G114: Tintas | H114: 1 | I114: 241011 | J114: Útiles
A115: 2410110037 | B115: Tintas Para Bolígrafo Azul Dokumental | C115: KL/1000 | D115: IMPORTADO | E115: 140 | F115: 120 | G115: Tintas | H115: 1 | I115: 241011 | J115: Útiles
A116: 2410110038 | B116: Tinta Bolígrafo Amarillo | C116: KL/1000 | D116: IMPORTADO | E116: 140 | F116: 120 | G116: Tintas | H116: 1 | I116: 241011 | J116: Útiles
A117: 2410110039 | B117: Tinta Bolígrafo Turquesa | C117: ML/1000 | D117: IMPORTADO | E117: 20 | F117: 90 | G117: Tintas | H117: 1 | I117: 241011 | J117: Útiles
A118: 2410110040 | B118: Tinta Bolígrafo Marrón | C118: ML/1000 | D118: IMPORTADO | E118: 20 | F118: 90 | G118: Tintas | H118: 1 | I118: 241011 | J118: Útiles
A119: 2410110041 | B119: Tinta Bolígrafo Naranja 068 PG3 | C119: ML/1000 | D119: IMPORTADO | E119: 20 | F119: 90 | G119: Tintas | H119: 1 | I119: 241011 | J119: Útiles
A120: 2410110043 | B120: Tinta Bolígrafo Rosado 0614 PG3 | C120: ML/1000 | D120: IMPORTADO | E120: 20 | F120: 90 | G120: Tintas | H120: 1 | I120: 241011 | J120: Útiles
A121: 2410110044 | B121: Tinta Bolígrafo Violeta | C121: ML/1000 | D121: IMPORTADO | E121: 20 | F121: 90 | G121: Tintas | H121: 1 | I121: 241011 | J121: Útiles
A122: 2410110073 | B122: Tinta Marcador Magico CC 3260 yellow to red | C122: ML/1000 | D122: IMPORTADO | G122: Tintas | H122: 1 | I122: 241011 | J122: Útiles
A123: 2410110074 | B123: Tinta Marcador Magico CC 3261 orange to pink | C123: ML/1000 | D123: IMPORTADO | G123: Tintas | H123: 1 | I123: 241011 | J123: Útiles
A124: 2410110075 | B124: Tinta Marcador Magico CC 3220 red to yellow | C124: ML/1000 | D124: IMPORTADO | G124: Tintas | H124: 1 | I124: 241011 | J124: Útiles
A125: 2410110076 | B125: Tinta Marcador Magico CC 3202 blue to turquoise | C125: ML/1000 | D125: IMPORTADO | G125: Tintas | H125: 1 | I125: 241011 | J125: Útiles
A126: 2410110077 | B126: Tinta Marcador Magico CC 3233 green to orange | C126: ML/1000 | D126: IMPORTADO | G126: Tintas | H126: 1 | I126: 241011 | J126: Útiles
A127: 2410110078 | B127: Tinta Marcador Magico CC 3200 blue to yellow | C127: ML/1000 | D127: IMPORTADO | G127: Tintas | H127: 1 | I127: 241011 | J127: Útiles
A128: 2410110079 | B128: Tinta Marcador Magico CC 3241 violet to pink | C128: ML/1000 | D128: IMPORTADO | G128: Tintas | H128: 1 | I128: 241011 | J128: Útiles
A129: 2410110080 | B129: Tinta Marcador Magico CC 3250 brown to green | C129: ML/1000 | D129: IMPORTADO | G129: Tintas | H129: 1 | I129: 241011 | J129: Útiles
A130: 2410110081 | B130: Tinta Marcador Magico CC 3213 black to pink | C130: ML/1000 | D130: IMPORTADO | G130: Tintas | H130: 1 | I130: 241011 | J130: Útiles
A131: 2410110082 | B131: Tinta Marcador Magico Revelador LF 4205.1. | C131: ML/1000 | D131: IMPORTADO | G131: Tintas | H131: 1 | I131: 241011 | J131: Útiles
A132: 2410110088 | B132: Tinta Pizarra Verde WB 7339.1 | C132: KL/1000 | D132: IMPORTADO | E132: 100 | F132: 90 | G132: Tintas | H132: 1 | I132: 241011 | J132: Útiles
A133: 2410110089 | B133: Tinta Pizarra Rojo WB 7322.1 | C133: KL/1000 | D133: IMPORTADO | E133: 100 | F133: 90 | G133: Tintas | H133: 1 | I133: 241011 | J133: Útiles
A134: 2410110090 | B134: Tinta Pizarra Negro WB 7311.1 | C134: KL/1000 | D134: IMPORTADO | E134: 100 | F134: 90 | G134: Tintas | H134: 1 | I134: 241011 | J134: Útiles
A135: 2410110091 | B135: Tinta Pizarra Azul WB 7302.1 | C135: KL/1000 | D135: IMPORTADO | E135: 100 | F135: 90 | G135: Tintas | H135: 1 | I135: 241011 | J135: Útiles
A136: 2410110103 | B136: Tinta Pizarra Anaranjado WB 7362.1 | C136: KL/1000 | D136: IMPORTADO | E136: 100 | F136: 90 | G136: Tintas | H136: 1 | I136: 241011 | J136: Útiles
A137: 2410110104 | B137: Tinta Pizarra Magenta WB 7342.1 | C137: KL/1000 | D137: IMPORTADO | E137: 100 | F137: 90 | G137: Tintas | H137: 1 | I137: 241011 | J137: Útiles
A138: 2410110105 | B138: Tinta Pizarra Violeta WB 7341.1 | C138: KL/1000 | D138: IMPORTADO | E138: 100 | F138: 90 | G138: Tintas | H138: 1 | I138: 241011 | J138: Útiles
A139: 2410110106 | B139: Tinta Pizarra Yellow-Green WB 7336.1 | C139: KL/1000 | D139: IMPORTADO | E139: 100 | F139: 90 | G139: Tintas | H139: 1 | I139: 241011 | J139: Útiles
A140: 2410120036 | B140: Licowax PE 520 Fine Crain (Cera A) | C140: KL/1000 | D140: NACIONAL | E140: 25 | F140: 7 | G140: Varios | H140: 1 | I140: 241012 | J140: Útiles
A141: 2410120037 | B141: Vaselina Líquida | C141: KL/1000 | D141: NACIONAL | E141: 40 | F141: 7 | G141: Otros | H141: 1 | I141: 241012 | J141: Útiles
A142: 2410120051 | B142: Cera Oppanol (N-150) | C142: KL/1000 | D142: NACIONAL PERO IMPORTADO | E142: 960 | F142: 120 | G142: Varios | H142: 1 | I142: 241012 | J142: Útiles
A143: 2410120053 | B143: Aceite ANPQ 22 Brinco | C143: LT/1000 | D143: NACIONAL | E143: 1000 | F143: 7 | G143: Varios | H143: 1 | I143: 241012 | J143: Útiles
... A147: 2410160010 | B147: Remache (Rivet) 7.5 x 40 ( XR-060-40 070 00000) | C147: PZ/1 | D147: IMPORTADO | E147: 10 | F147: 90 | G147: Remache tablero | H147: 1 | I147: 241016 | J147: Útiles
A148: 2410170035 | B148: Film PVC Ctristal 110 mm x 100 mic | C148: ML/1000 | D148: IMPORTADO | G148: Film | H148: 1 | I148: 241017 | J148: Útiles
A149: 2410170036 | B149: Film PVC Ctristal 245 mm x 120 mic | C149: ML/1000 | D149: IMPORTADO | G149: Film | H149: 1 | I149: 241017 | J149: Útiles
A150: 2410170037 | B150: Filtro 042 (CPE2873) | C150: ML/1000 | D150: IMPORTADO | E150: 2000000 | F150: 90 | G150: Filtros | H150: 1 | I150: 241017 | J150: Útiles
A151: 2410170038 | B151: Punta carga 042 | C151: ML/1000 | D151: IMPORTADO | E151: 100000 | F151: 90 | G151: Puntas | H151: 1 | I151: 241017 | J151: Útiles
A152: 2410170050 | B152: Punta Poliester 6x5.3x29.5mm Marcador 123 (045) ET-060PN(T) | C152: ML/1000 | D152: IMPORTADO | E152: 1200 | F152: 240 | G152: Puntas | H152: 1 | I152: 241017 | J152: Útiles
A153: 2410170057 | B153: Tinta indeleble negro ma 2110 | C153: KL/1000 | D153: IMPORTADO | E153: 140 | F153: 120 | G153: Tintas | H153: 1 | I153: 241017 | J153: Útiles
A154: 2410170058 | B154: Tinta indeleble azul ma 2101 | C154: KL/1000 | D154: IMPORTADO | E154: 140 | F154: 120 | G154: Tintas | H154: 1 | I154: 241017 | J154: Útiles
A155: 2410170071 | B155: Filtro 045 (CPE3119) | C155: ML/1000 | D155: IMPORTADO | E155: 1000000 | F155: 90 | G155: Filtros | H155: 1 | I155: 241017 | J155: Útiles
A156: 2410170091 | B156: Film Para Marcador 023 LYC | C156: ML/1000 | D156: IMPORTADO | E156: 160000 | F156: 70 | G156: Film | H156: 1 | I156: 241017 | J156: Útiles
A157: 2410170092 | B157: Film PET Transferencia 10.5x7cm Marcador L123 | C157: ML/1000 | D157: IMPORTADO | E157: 160000 | F157: 70 | G157: Film | H157: 1 | I157: 241017 | J157: Útiles
A158: 2410170205 | B158: Film PET Transferencia 10x7cm Marcador 047 | C158: ML/1000 | D158: IMPORTADO | E158: 160000 | F158: 70 | G158: Film | H158: 1 | I158: 241017 | J158: Útiles
A159: 2410170233 | B159: Punta Poliester Marcador L-47 ( 4.60 X 30 MM) MEI KEKE | C159: ML/1000 | D159: IMPORTADO | E159: 1000000 | F159: 90 | G159: Puntas | H159: 1 | I159: 241017 | J159: Útiles
A160: 2410170238 | B160: Film PET Transferencia 10x7cm Marcador 047 Azul | C160: ML/1000 | D160: IMPORTADO | E160: 160000 | F160: 70 | G160: Film | H160: 1 | I160: 241017 | J160: Útiles
A161: 2410170239 | B161: Film PET Transferencia 10x7cm Marcador 047 Rojo | C161: ML/1000 | D161: IMPORTADO | E161: 160000 | F161: 70 | G161: Film | H161: 1 | I161: 241017 | J161: Útiles
... A175: 2410260003 | B175: Acelerador de Vulcanización TMTD | C175: KL/1000 | D175: NACIONAL | E175: 25 | F175: 7 | G175: Varios | H175: 1 | I175: 241026 | J175: Útiles
A176: 2410260013 | B176: Blanqueador Optico | C176: KL/1000 | D176: NACIONAL | G176: Otros | H176: 1 | I176: 241026 | J176: Útiles
A177: 2410260028 | B177: Byk W-966 | C177: KL/1000 | D177: NACIONAL | G177: Otros | H177: 1 | I177: 241026 | J177: Útiles
A178: 2410290002 | B178: Malla para Serigrafiado # 150 Nylon 34W x 158cm Ancho | C178: MT/100 | D178: NACIONAL | E178: 1 | F178: 7 | G178: Malla | H178: 1 | I178: 241029 | J178: Útiles
A179: 2410290046 | B179: Polietileno Alta Densidad Soplado LH 7350 | C179: KL/1000 | D179: IMPORTADO Y NACIONAL | E179: 25 | F179: 15 | G179: Resinas | H179: 1 | I179: 241029 | J179: Útiles
A180: 2410290066 | B180: Retardador DL-1000 | C180: LT/1000 | D180: NACIONAL | E180: 1 | F180: 7 | G180: Retardador | H180: 1 | I180: 241029 | J180: Útiles
A181: 2410290067 | B181: Catalizador Exc | C181: KL/1000 | D181: NACIONAL | E181: 1 | F181: 5 | G181: Catalizador | H181: 1 | I181: 241029 | J181: Útiles
A182: 2410290068 | B182: Excelite Blanco Ultra | C182: KL/1000 | D182: NACIONAL | E182: 25 | F182: 7 | G182: Excelite | H182: 1 | I182: 241029 | J182: Útiles
A183: 2410290090 | B183: Poliretano con Perfil Doble 25x5mm - Duitt | C183: MT/100 | D183: NACIONAL | E183: 1 | F183: 5 | G183: Poliretano | H183: 1 | I183: 241029 | J183: Útiles
A184: 2410290109 | B184: Emulsión Dirasol 22x900ml | C184: PZ/1 | D184: NACIONAL | E184: 1 | F184: 5 | G184: Emulsiones | H184: 1 | I184: 241029 | J184: Útiles
A185: 2410290111 | B185: Pincel Plástico Plateado de 17cm | C185: ML/1000 | D185: IMPORTADO | E185: 100000 | F185: 120 | G185: Pinceles | H185: 1 | I185: 241029 | J185: Útiles
A186: 2410290142 | B186: Polipropileno 20H92N | C186: KL/1000 | D186: NACIONAL PERO IMPORTADO | E186: 25 | F186: 45 | G186: Resinas | H186: 1 | I186: 241029 | J186: Útiles
A187: 2410290153 | B187: Polipropileno 40H | C187: KL/1000 | D187: NACIONAL PERO IMPORTADO | E187: 25 | F187: 45 | G187: Resinas | H187: 1 | I187: 241029 | J187: Útiles
A188: 2410290156 | B188: Cinta 43x122 Blanco PP | C188: ROLL/1 | D188: NACIONAL | E188: 300 | F188: 7 | G188: Varios | H188: 1 | I188: 241029 | J188: Útiles
A189: 2410290210 | B189: Alcohol Polivinilico Celvol 203 | C189: KL/1000 | D189: NACIONAL | E189: 25 | F189: 7 | G189: Alcohol | H189: 1 | I189: 241029 | J189: Útiles
... A226: 2430520005 | B226: Dióxido de Titanio CR-506 | C226: KL/1000 | D226: NACIONAL | E226: 25 | F226: 7 | G226: Varios | H226: 1 | I226: 243052 | J226: Útiles
A227: 2430520006 | B227: Dióxido de Titanio Tioxhua R-216 | C227: KL/1000 | D227: NACIONAL | G227: Otros | H227: 1 | I227: 243052 | J227: Útiles
A228: 2430530004 | B228: Tiza Malla 325 Blanca Imprimantes | C228: KL/1000 | D228: NACIONAL | E228: 40 | F228: 7 | G228: Varios | H228: 1 | I228: 243053 | J228: Útiles
A229: 2430530010 | B229: Carbonato de calcio M-400 (Tiza Cisne) | C229: KL/1000 | D229: NACIONAL | E229: 25 | F229: 7 | G229: Varios | H229: 1 | I229: 243053 | J229: Útiles
A230: 2430540001 | B230: Talco Blanco Micronizado | C230: KL/1000 | D230: NACIONAL | E230: 40 | F230: 7 | G230: Varios | H230: 1 | I230: 243054 | J230: Útiles
A231: 2430550009 | B231: Caolín PZ 600 (Silicato de Aluminio) | C231: KL/1000 | D231: NACIONAL | E231: 25 | F231: 7 | G231: Varios | H231: 1 | I231: 243055 | J231: Útiles
A232: 2430550010 | B232: Caolín malla 400 ( Silicato de aluminio) | C232: KL/1000 | D232: NACIONAL | E232: 25 | F232: 7 | G232: Varios | H232: 1 | I232: 243055 | J232: Útiles
A233: 2430580001 | B233: Dispersión al Agua Negro | C233: KL/1000 | D233: NACIONAL | E233: 25 | F233: 7 | G233: Dispersión | H233: 1 | I233: 243058 | J233: Útiles
...
